Workbook
Name _MailAutoSig: '2023'!$E$20
Name _MailAutoSig: '2024'!$E$20
Name _MailAutoSig: '2025'!$E$20
Name _MailAutoSig: '2026'!$E$20
Name _MailAutoSig: '2026 sandbox)'!$E$20

Sheet 2026 sandbox)
G1: 2026
A2: Forecast | C2: Jan | D2: Feb | E2: Mar | F2: Apr | G2: May | H2: Jun | I2: Jul | J2: Aug | K2: Sept | L2: Oct | M2: Nov | N2: Dec | O2: YTD Total
A3: Recurring Sales Invoiced | B3: Agreement | C3: 294517 | D3: 287630 | E3: 296845 | F3: 197915 | O3: =SUM(C3:N3) -> 1076907 | Q3: NOTES:
B4: New Agreement in Std | O4: =SUM(C4:N4) -> 0 | Q4: Agreement invoices that go out on the 8th of the month:
B5: ITMS | O5: =SUM(C5:N5) -> 0 | Q5: ARC - comprehensive services $84,000
B6: Licensing | O6: =SUM(F6:N6) -> 0 | Q6: Invoiced on 8th of month: BUNZL - de Mexico - invoiced this month for this month. Includes overages from last month. $17k
B7: Comprehensive Services | O7: =SUM(C7:N7) -> 0 | Q7: License Agreements = $38,000
B8: Other | O8: =SUM(C8:N8) -> 0
A10: New Sales Invoiced [INPUTS] | B10: Standard | C10: 106724 | D10: 147864 | E10: 126944 | F10: 49818 | O10: =SUM(C10:N10) -> 431350
B11: Miscellaneous - Invoiced | C11: 1642 | D11: 2385 | E11: 5357 | F11: 460 | O11: =SUM(C11:N11) -> 9844
B12: Credit Memo - Invoiced | C12: -630 | D12: -17761 | E12: -12220 | F12: -618 | O12: =SUM(C12:N12) -> -31229
E13: 5212
A14: Pending and Projected Sales | B14: Pending Project Milestones | F14: =5400+10250+1800 -> 17450 | G14: =1800+1800+1800 -> 5400 | H14: =1125 -> 1125 | O14: =SUM(C14:N14) -> 23975 | T14: =R20-R21-R22 -> 66787
B15: Hubspot Pipeline at 40% | O15: =SUM(C15:N15) -> 0
B16: OPPS High Forecast (inputs)
B17: OPPS Low Forecast (inputs)
A19: Total | B19: Total Revenue | C19: =C3+C10+C11+C12 -> 402253 | D19: =D3+D10+D11+D12 -> 420118 | E19: =E3+E10+E11+E12 -> 416926 | F19: =F3+F10+F11+F12 -> 247575 | G19: =G3+G10+G11+G12 -> 0 | H19: =H3+H10+H11+H12 -> 0 | I19: =I3+I10+I11+I12 -> 0 | J19: =J3+J10+J11+J12 -> 0 | ... M19: =M3+M10+M11+M12 -> 0 | N19: =N3+N6+N10+N11+N12 -> 0 | O19: =SUM(C19:N19) -> 1486872 | R19: AGREEMENT | S19: Breakdown
B20: High | C20: =C3+C5+C6+C10+C11+C16+C12 -> 402253 | D20: =D3+D5+D6+D10+D11+D16+D12 -> 420118 | E20: =E3+E5+E6+E10+E11+E16+E12+E14 -> 416926 | F20: =F19+F16 -> 247575 | G20: =G3+G5+G6+G10+G11+G16+G12+G14 -> 5400 | H20: =H3+H5+H6+H10+H11+H16+H12+H14 -> 1125 | I20: =I3+I5+I6+I10+I11+I16+I12+I14 -> 0 | J20: =J3+J5+J6+J10+J11+J16+J12+J14 -> 0 | K20: =K3+K5+K6+K7+K8+K10+K11+K12+K14+K16 -> 0 | L20: =L3+L5+L6+L7+L8+L10+L11+L12+L14+L16 -> 0 | M20: =M3+M5+M6+M7+M8+M10+M11+M12+M14+M16 -> 0 | N20: =N3+N5+N6+N7+N8+N10+N11+N12+N14+N16 -> 0 | R20: 310492 | S20: TOTAL
B21: Low | C21: =C3+C5+C6+C10+C11+C12+C17 -> 402253 | D21: =D3+D5+D6+D10+D11+D12+D17 -> 420118 | E21: =E3+E5+E6+E10+E11+E12+E17+E14 -> 416926 | F21: =F19+F17 -> 247575 | G21: =G3+G5+G6+G10+G11+G12+G17+G14 -> 5400 | H21: =H3+H5+H6+H10+H11+H12+H17+H14 -> 1125 | I21: =I3+I5+I6+I10+I11+I12+I17+I14 -> 0 | J21: =J3+J5+J6+J10+J11+J12+J17+J14 -> 0 | K21: =K3+K5+K6+K7+K8+K10+K11+K12+K14+K17 -> 0 | L21: =L3+L5+L6+L7+L8+L10+L11+L12+L14+L17 -> 0 | M21: =M3+M5+M6+M7+M8+M10+M11+M12+M14+M17 -> 0 | N21: =N3+N5+N6+N7+N8+N10+N11+N12+N14+N17 -> 0 | R21: =84424+9675 -> 94099 | S21: Comp Services + Project (BUNZL de Mex)
A22: Gap (/mo) | B22: Revenue to Goal | C22: =C19-C26 -> 2253 | D22: =D19-D26 -> 20118 | E22: =E19-E26 -> 16926 | F22: =F19-F26 -> -152425 | G22: =G19-G26 -> -400000 | H22: =H19-H26 -> -400000 | I22: =I19-I26 -> -400000 | J22: =J19-J26 -> -400000 | ... N22: =N19-N26 -> -400001 | O22: =SUM(C22:N22) -> -3313129 | R22: 149606 | S22: Managed Services
R23: =R20-R21-R22 -> 66787 | S23: Licensing/Server (Agreement)
A24: Rolling Actual/Forecast | B24: Actual | C24: =C19 -> 402253 | D24: =C24+D19 -> 822371 | E24: =D24+E19 -> 1239297 | F24: =E24+F19 -> 1486872 | G24: =F24+G19 -> 1486872 | H24: =G24+H19 -> 1486872 | I24: =H24+I19 -> 1486872 | J24: =I24+J19 -> 1486872 | K24: =J24+K19 -> 1486872 | ... N24: =M24+N19 -> 1486872 | O24: =N24 -> 1486872
B25: Actual ROLLING | C25: =C19 -> 402253 | D25: =C25+D19 -> 822371 | E25: =D25+E19 -> 1239297 | F25: =E25+F19 -> 1486872 | G25: =F25+G19 -> 1486872 | H25: =G25+H19 -> 1486872 | I25: =H25+I19 -> 1486872 | J25: =I25+J19 -> 1486872 | K25: =J25+K19 -> 1486872 | ... N25: =M25+N19 -> 1486872
A26: Monthly Goal | B26: Revenue GOAL | C26: 400000 | D26: 400000 | E26: 400000 | F26: 400000 | G26: 400000 | H26: 400000 | I26: 400000 | J26: 400000 | K26: 400000 | L26: 400000 | M26: 400000 | N26: 400001 | O26: =SUM(C26:N26) -> 4800001 | Q26: cogs | R26: rev
B27: Rolling GOAL | C27: =C26 -> 400000 | D27: =C27+D26 -> 800000 | E27: =D27+E26 -> 1200000 | F27: =E27+F26 -> 1600000 | G27: =F27+G26 -> 2000000 | H27: =G27+H26 -> 2400000 | I27: =H27+I26 -> 2800000 | J27: =I27+J26 -> 3200000 | K27: =J27+K26 -> 3600000 | ... N27: =M27+N26 -> 4800001 | O27: =N27 -> 4800001 | Q27: 55014 | R27: 84424 | S27: arc | T27: =R27-Q27 -> 29410 | U27: =T27/R27 -> 0.34836066
A28: Rolling Goal | C28: =C24-C27 -> 2253 | D28: =D24-D27 -> 22371 | E28: =E24-E27 -> 39297 | F28: =F24-F27 -> -113128 | G28: =G24-G27 -> -513128 | H28: =H24-H27 -> -913128 | I28: =I24-I27 -> -1313128 | J28: =J24-J27 -> -1713128 | ... N28: =N24-N27 -> -3313129 | O28: =N28 -> -3313129 | T28: =R28-Q28 -> 0
A29: Rolling Goal | C29: Jan | D29: Feb | E29: Mar | F29: Apr | G29: May | H29: Jun | I29: Jul | J29: Aug | K29: Sept | L29: Oct | M29: Nov | N29: Dec | O29: 2019 | T29: =R29-Q29 -> 0
A30: Rolling Goal | C30: =SUMIFS(#REF!,#REF!,1,#REF!,2019,#REF!,"open") -> #REF! | D30: =SUMIFS(#REF!,#REF!,2,#REF!,2019,#REF!,"open") -> #REF! | E30: =SUMIFS(#REF!,#REF!,3,#REF!,2019,#REF!,"open") -> #REF! | F30: =SUMIFS(#REF!,#REF!,4,#REF!,2019,#REF!,"open") -> #REF! | G30: =SUMIFS(#REF!,#REF!,5,#REF!,2019,#REF!,"open") -> #REF! | H30: =SUMIFS(#REF!,#REF!,6,#REF!,2019,#REF!,"open") -> #REF! | I30: =SUMIFS(#REF!,#REF!,7,#REF!,2019,#REF!,"open") -> #REF! | J30: =SUMIFS(#REF!,#REF!,8,#REF!,2019,#REF!,"open") -> #REF! | K30: =SUMIFS(#REF!,#REF!,9,#REF!,2019,#REF!,"open") -> #REF! | L30: =SUMIFS(#REF!,#REF!,10,#REF!,2019,#REF!,"open") -> #REF! | M30: =SUMIFS(#REF!,#REF!,11,#REF!,2019,#REF!,"open") -> #REF! | N30: =SUMIFS(#REF!,#REF!,12,#REF!,2019,#REF!,"open") -> #REF! | O30: =SUM(C30:N30) -> #REF! | T30: =R30-Q30 -> 0
A31: Rolling Goal | C31: =SUMIFS(#REF!,#REF!,1,#REF!,2019,#REF!,"*",#REF!,"open") -> #REF! | D31: =SUMIFS(#REF!,#REF!,2,#REF!,2019,#REF!,"*",#REF!,"open") -> #REF! | E31: =SUMIFS(#REF!,#REF!,3,#REF!,2019,#REF!,"*",#REF!,"open") -> #REF! | F31: =SUMIFS(#REF!,#REF!,4,#REF!,2019,#REF!,"*",#REF!,"open") -> #REF! | G31: =SUMIFS(#REF!,#REF!,5,#REF!,2019,#REF!,"*",#REF!,"open") -> #REF! | H31: =SUMIFS(#REF!,#REF!,6,#REF!,2019,#REF!,"*",#REF!,"open") -> #REF! | I31: =SUMIFS(#REF!,#REF!,7,#REF!,2019,#REF!,"*",#REF!,"open") -> #REF! | J31: =SUMIFS(#REF!,#REF!,8,#REF!,2019,#REF!,"*",#REF!,"open") -> #REF! | K31: =SUMIFS(#REF!,#REF!,9,#REF!,2019,#REF!,"*",#REF!,"open") -> #REF! | L31: =SUMIFS(#REF!,#REF!,10,#REF!,2019,#REF!,"*",#REF!,"open") -> #REF! | M31: =SUMIFS(#REF!,#REF!,11,#REF!,2019,#REF!,"*",#REF!,"open") -> #REF! | N31: =SUMIFS(#REF!,#REF!,12,#REF!,2019,#REF!,"*",#REF!,"open") -> #REF! | O31: =SUM(C31:N31) -> #REF! | T31: =R31-Q31 -> 0
B32: Rolling GOAL Difference | C32: =C19-C26 -> 2253 | D32: =D19-D26+C32 -> 22371 | E32: =E19-E26+D32 -> 39297 | F32: =F19-F26+E32 -> -113128 | G32: =G19-G26+F32 -> -513128 | Q32: 6228 | R32: 9675 | S32: bunzl de mex | T32: =R32-Q32 -> 3447 | U32: =28/95 -> 0.29473684
A34: This green area does not roll into other areas. This is | B34: Project Revenue - Agreements | C34: =20000+95079 -> 115079 | D34: =20000+95079 -> 115079 | E34: =20000+95079 -> 115079 | O34: =SUM(C34:N34) -> 345237 | Q34: =SUM(Q27:Q33) -> 61242 | R34: =SUM(R27:R33) -> 94099
A35: a subset of AGREEMENT revenue. | B35: Project COGS Agreements (input) | C35: 68924 | D35: 68925 | E35: 68926 | O35: =SUM(C35:N35) -> 206775
A36: Breakdown reporting only | B36: Project Agreement Margin $ | C36: =C34-C35 -> 46155 | D36: =D34-D35 -> 46154 | E36: =E34-E35 -> 46153 | O36: =SUM(C36:N36) -> 138462 | Q36: =R34-Q34 -> 32857 | R36: =Q36/R34 -> 0.34917481
B37: Project Agreement Margin % | C37: =C36/C34 -> 0.40107231 | D37: =D36/D34 -> 0.40106362 | E37: =E36/E34 -> 0.40105493 | O37: =O36/O34 -> 0.40106362
B38: Agreement Revenue | C38: =C3 -> 294517 | D38: =D3 -> 287630 | E38: =E3 -> 296845 | F38: 197915 | G38: =G3 -> 0 | H38: =H3 -> 0 | I38: =I3 -> 0 | J38: =J3 -> 0 | K38: =K3 -> 0 | L38: =L3 -> 0 | M38: =M3 -> 0 | N38: =N3 -> 0 | O38: =SUM(C38:N38) -> 1076907
B39: Agreement COGS (input) | C39: 102260 | D39: 99927 | E39: 106236 | F39: 42127 | O39: =SUM(C39:N39) -> 350550
B40: Agreement Margin $ | C40: =C38-C39 -> 192257 | D40: =D38-D39 -> 187703 | E40: =E38-E39 -> 190609 | F40: =F38-F39 -> 155788 | G40: =G38-G39 -> 0 | H40: =H38-H39 -> 0 | I40: =I38-I39 -> 0 | J40: =J38-J39 -> 0 | ... N40: =N38-N39 -> 0 | O40: =SUM(C40:N40) -> 726357
B41: Agreement Margin % | C41: =C40/C38 -> 0.65278745 | D41: =D40/D38 -> 0.65258492 | E41: =E40/E38 -> 0.64211626 | F41: =F40/F38 -> 0.787146 | G41: =G40/G38 -> #DIV/0! | H41: =H40/H38 -> #DIV/0! | I41: =I40/I38 -> #DIV/0! | J41: =J40/J38 -> #DIV/0! | ... O41: =O40/O38 -> 0.67448443
B42: AGREEMENT MARGIN Reduction (previous month) | F42: =F40-E40 -> -34821
B43: Standard Revenue (w Misc & CMs) | C43: 107736 | D43: 132487 | E43: 120081 | F43: 49661 | O43: =SUM(C43:N43) -> 409965
B44: Standard Misc COGS (input) | C44: 67536 | D44: 83944 | E44: 76229 | F44: 32544 | O44: =SUM(C44:N44) -> 260253
B45: Standard Margin $ | C45: =C43-C44 -> 40200 | D45: =D43-D44 -> 48543 | E45: =E43-E44 -> 43852 | F45: =F43-F44 -> 17117 | G45: =G43-G44 -> 0 | H45: =H43-H44 -> 0 | I45: =I43-I44 -> 0 | J45: =J43-J44 -> 0 | ... N45: =N43-N44 -> 0 | O45: =SUM(C45:N45) -> 149712
B46: Standard Margin % | C46: =C45/C43 -> 0.37313433 | D46: =D45/D43 -> 0.36639821 | E46: =E45/E43 -> 0.36518683 | F46: =F45/F43 -> 0.34467691 | G46: =G45/G43 -> #DIV/0! | H46: =H45/H43 -> #DIV/0! | I46: =I45/I43 -> #DIV/0! | J46: =J45/J43 -> #DIV/0! | ... O46: =O45/O43 -> 0.36518239
B47: STANDARD MARGIN Reduction (previous month) | F47: =F45-E45 -> -26735
B49: Miscellaneous COGS (input)
B50: TOTAL Revenue | C50: =C38+C43 -> 402253 | D50: =D38+D43 -> 420117 | E50: =E38+E43 -> 416926 | F50: =F38+F43 -> 247576 | G50: =G38+G43 -> 0 | H50: =H38+H43 -> 0 | I50: =I38+I43 -> 0 | J50: =J38+J43 -> 0 | ... N50: =N38+N43 -> 0 | O50: =SUM(C50:N50) -> 1486872
B51: TOTAL COGS | C51: =C39+C44 -> 169796 | D51: =D39+D44 -> 183871 | E51: =E39+E44 -> 182465 | F51: =F39+F44 -> 74671 | G51: =G39+G44+G49 -> 0 | H51: =H39+H44+H49 -> 0 | I51: =I39+I44+I49 -> 0 | J51: =J39+J44+J49 -> 0 | K51: =K39+K44+K49 -> 0 | L51: =L39+L44+L49 -> 0 | M51: =M39+M44+M49 -> 0 | N51: =N39+N44+N49 -> 0 | O51: =SUM(C51:N51) -> 610803
B52: TOTAL [Blended] Margin $ | C52: =C50-C51 -> 232457 | D52: =D50-D51 -> 236246 | E52: =E50-E51 -> 234461 | F52: =F50-F51 -> 172905 | G52: =G50-G51 -> 0 | H52: =H50-H51 -> 0 | I52: =I50-I51 -> 0 | J52: =J50-J51 -> 0 | ... N52: =N50-N51 -> 0 | O52: =SUM(C52:N52) -> 876069
B53: TOTAL [Blended] Margin % | C53: =C52/C50 -> 0.57788755 | D53: =D52/D50 -> 0.56233383 | E53: =E52/E50 -> 0.56235639 | F53: =F52/F50 -> 0.69839161 | G53: =G52/G50 -> #DIV/0! | H53: =H52/H50 -> #DIV/0! | I53: =I52/I50 -> #DIV/0! | J53: =J52/J50 -> #DIV/0! | ... O53: =O52/O50 -> 0.5892027
B54: TARGET Minimum MARGIN (input) | C54: 223000 | D54: 223000 | E54: 223000 | F54: 204000 | G54: 200000 | H54: 200000 | I54: 200000 | J54: 200000 | K54: 200000 | L54: 200000 | M54: 200000 | N54: 200000 | O54: =SUM(C54:N54) -> 2473000
B55: $ Over TARGET MARGIN (Profit) | C55: =C52-C54 -> 9457 | D55: =D52-D54 -> 13246 | E55: =E52-E54 -> 11461 | F55: =F52-F54 -> -31095 | G55: =G52-G54 -> -200000 | H55: =H52-H54 -> -200000 | I55: =I52-I54 -> -200000 | J55: =J52-J54 -> -200000 | ... N55: =N52-N54 -> -200000 | O55: =SUM(C55:N55) -> -1596931
B56: Net Profit % | C56: =C55/C19 -> 0.023510079 | D56: =D55/D19 -> 0.031529237 | E56: =E55/E19 -> 0.027489291 | F56: =F55/F19 -> -0.1255983 | G56: =G55/G19 -> #DIV/0! | H56: =H55/H19 -> #DIV/0! | I56: =I55/I19 -> #DIV/0! | J56: =J55/J19 -> #DIV/0! | ... N56: =N55/N19 -> #DIV/0!
B58: Profit GOAL at Target 18% | C58: =C19*0.18 -> 72405.54 | D58: =D19*0.18 -> 75621.24 | E58: =E19*0.18 -> 75046.68 | F58: =F19*0.18 -> 44563.5 | G58: =G19*0.18 -> 0 | H58: =H19*0.18 -> 0 | I58: =I19*0.18 -> 0 | J58: =J19*0.18 -> 0 | ... N58: =N19*0.18 -> 0 | O58: =SUM(C58:N58) -> 267636.96 | P58: 18% Goal
A60: RECURRING SERVICES - UP/DOWN
A62: Managed Services (only) | B62: End of 2025...2026 Start… | C62: 145911 | D62: =C62 -> 145911 | E62: =D62 -> 145911 | F62: =E62 -> 145911 | G62: =F62 -> 145911 | H62: =G62 -> 145911 | I62: =H62 -> 145911 | J62: =I62 -> 145911 | K62: =J62 -> 145911 | ... N62: =M62 -> 145911 | O62: =SUM(C62:N62) -> 1750932
O63: =SUM(C63:N63) -> 0
B64: BUNZL - 2 year agreement reduction | C64: -5000 | D64: -5000 | E64: -5000 | F64: -5000 | G64: -5000 | H64: -5000 | I64: -5000 | J64: -5000 | K64: -5000 | L64: -5000 | M64: -5000 | N64: -5000 | O64: =SUM(C64:N64) -> -60000
B65: Act reduction - leaving | C65: -5730 | D65: -5730 | E65: -5730 | F65: -5730 | G65: -5730 | H65: -5730 | I65: -5730 | J65: -5730 | K65: -5730 | L65: -5730 | M65: -5730 | N65: -5730 | O65: =SUM(C65:N65) -> -68760
B66: FS Unlimited: MS Agrmt began 1/15 | C66: 302 | D66: 550 | E66: 550 | F66: 550 | G66: 550 | H66: 550 | I66: 550 | J66: 550 | K66: 550 | L66: 550 | M66: 550 | N66: 550 | O66: =SUM(C66:N66) -> 6352
B67: Amelia Newcomb Dressage: MS Agrmt began 1/19 | C67: 301.61 | D67: 850 | E67: 850 | F67: 850 | G67: 850 | H67: 850 | I67: 850 | J67: 850 | K67: 850 | L67: 850 | M67: 850 | N67: 850 | O67: =SUM(C67:N67) -> 9651.61
B68: Designated Brokers: Adtl 4 MS Tier 1 Wkstns | F68: 300 | G68: 300 | H68: 300 | I68: 300 | J68: 300 | K68: 300 | L68: 300 | M68: 300 | N68: 300 | O68: =SUM(C68:N68) -> 2700
B69: TransGo: Adtl 2 MS Tier 1 Wkstns | F69: 100 | G69: 100 | H69: 100 | I69: 100 | J69: 100 | K69: 100 | L69: 100 | M69: 100 | N69: 100 | O69: =SUM(C69:N69) -> 900
B70: Vinyl Works: Adtl 6 MS Tier 2 Wkstns | F70: 510 | G70: 510 | H70: 510 | I70: 510 | J70: 510 | K70: 510 | L70: 510 | M70: 510 | N70: 510 | O70: =SUM(C70:N70) -> 4590
B71: Realworld - increase | F71: 510 | G71: 510 | H71: 510 | I71: 510 | J71: 510 | K71: 510 | L71: 510 | M71: 510 | N71: 510 | O71: =SUM(C71:N71) -> 4590
B72: Autism Systems - increase | F72: 325 | G72: 325 | H72: 325 | I72: 325 | J72: 325 | K72: 325 | L72: 325 | M72: 325 | N72: 325 | O72: =SUM(C72:N72) -> 2925
B73: Fire Sprinkler - increase | F73: 269 | G73: 269 | H73: 269 | I73: 269 | J73: 269 | K73: 269 | L73: 269 | M73: 269 | N73: 269 | O73: =SUM(C73:N73) -> 2421
B74: Secure Money Adivisors - increase | G74: 1615 | H74: 1615 | I74: 1615 | J74: 1615 | K74: 1615 | L74: 1615 | M74: 1615 | N74: 1615 | O74: =SUM(C74:N74) -> 12920
B75: FS Unlimited: Wkstn adjustment | E75: -50 | F75: -50 | G75: -50 | H75: -50 | I75: -50 | J75: -50 | K75: -50 | L75: -50 | M75: -50 | N75: -50 | O75: =SUM(C75:N75) -> -500
B76: Pelage - increase | F76: 425 | G76: 425 | H76: 425 | I76: 425 | J76: 425 | K76: 425 | L76: 425 | M76: 425 | N76: 425 | O76: =SUM(M76:N76) -> 850
B77: Dot by Dot - increase | G77: 60 | H77: 60 | I77: 60 | J77: 60 | K77: 60 | L77: 60 | M77: 60 | N77: 60 | O77: =SUM(M77:N77) -> 120
B78: Sea Ranch - leaving | I78: -2500 | J78: -2500 | K78: -2500 | L78: -2500 | M78: -2500 | N78: -2500 | O78: =SUM(M78:N78) -> -5000
B79: CWS - increase | F79: 385 | G79: 385 | H79: 385 | I79: 385 | J79: 385 | K79: 385 | L79: 385 | M79: 385 | N79: 385 | O79: =SUM(M79:N79) -> 770
B80: Conejo | G80: -5500 | H80: -5500 | I80: -5500 | J80: -5500 | K80: -5500 | L80: -5500 | M80: -5500 | N80: -5500 | O80: =SUM(M80:N80) -> -11000
B81: Toro | O81: =SUM(M81:N81) -> 0
O82: =SUM(M82:N82) -> 0
O83: =SUM(M83:N83) -> 0
O84: =N84 -> 0
B86: TOTAL NET | C86: =SUM(C62:C85) -> 135784.61 | D86: =SUM(D62:D85) -> 136581 | E86: =SUM(E62:E85) -> 136531 | F86: =SUM(F62:F85) -> 139355 | G86: =SUM(G62:G85) -> 135530 | H86: =SUM(H62:H85) -> 135530 | I86: =SUM(I62:I85) -> 133030 | J86: =SUM(J62:J85) -> 133030 | ... O86: =SUM(O62:O85) -> 1654461.6
B87: Increase month over month | C87: =C86-C62 -> -10126.39 | D87: =D86-C86 -> 796.39 | E87: =E86-D86 -> -50 | F87: =F86-E86 -> 2824 | G87: =G86-F86 -> -3825 | H87: =H86-G86 -> 0 | I87: =I86-H86 -> -2500 | J87: =J86-I86 -> 0 | K87: =K86-J86 -> 0 | ... N87: =N86-M86 -> 0 | O87: =SUM(C87:N87) -> -12881
B90: Rolling NET Increase over 2023 (total) | C90: =C86-C62 -> -10126.39 | D90: =D86-D62 -> -9330 | E90: =E86-E62 -> -9380 | F90: =F86-F62 -> -6556 | G90: =G86-G62 -> -10381 | H90: =H86-H62 -> -10381 | I90: =I86-I62 -> -12881 | J90: =J86-J62 -> -12881 | ... O90: =O86-O62 -> -96470.39
B92: ACTUAL MS ONLY per CW | E92: 138827
B93: Likely different based on MS revenue invoiced via Std/Misc for first month or two | E93: =E92-E86 -> 2296
E97: $187k | F97: High water mark - Dec 2024
H106: 1 | I106: 2 | J106: 3 | K106: 4 | L106: 5 | M106: 6 | N106: 7 | O106: 8 | P106: 10
G107: 2022 | H107: 2023 | I107: 2024 | J107: 2025 | K107: 2026 | L107: 2027 | M107: 2028 | N107: 2029 | O107: 2030 | P107: 2032
F109: MS Monthly | H109: 185000 | I109: =H109+50000 -> 235000 | J109: =I109+50000 -> 285000 | K109: =J109+50000 -> 335000 | L109: =K109+50000 -> 385000 | M109: =L109+50000 -> 435000 | N109: =M109+50000 -> 485000 | O109: =N109+50000 -> 535000 | P109: =#REF!+50000 -> #REF!
F111: Project Mo + Recurring Other | G111: =G109*1.5 -> 0 | H111: 130000 | I111: 400000 | J111: =J109*1.5 -> 427500 | K111: =K109*1.5 -> 502500 | L111: =L109*1.5 -> 577500 | M111: =M109*1.5 -> 652500 | N111: =N109*1.5 -> 727500 | O111: =O109*1.5 -> 802500 | P111: =P109*1.5 -> #REF!
F113: One Off Sales | H113: 100000
F115: Mo Total | G115: =SUM(G109:G114) -> 0 | H115: =SUM(H109:H114) -> 415000 | I115: =SUM(I109:I114) -> 635000 | J115: =SUM(J109:J114) -> 712500 | K115: =SUM(K109:K114) -> 837500 | L115: =SUM(L109:L114) -> 962500 | M115: =SUM(M109:M114) -> 1087500 | N115: =SUM(N109:N114) -> 1212500 | ... P115: =SUM(P109:P114) -> #REF!
F117: Annual Rev | G117: =G115*12 -> 0 | H117: =H115*12 -> 4980000 | I117: =I115*12 -> 7620000 | J117: =J115*12 -> 8550000 | K117: =K115*12 -> 10050000 | L117: =L115*12 -> 11550000 | M117: =M115*12 -> 13050000 | N117: =N115*12 -> 14550000 | ... P117: =P115*12 -> #REF!

Sheet Profitablility
E1: April | F1: 2026
E3: Agreement Revenue | F3: ='2026'!F3 -> 204317 | I3: =F3 -> 204317 | Q3: 1073
E4: Agreement COGS | F4: ='2026'!F39 -> 46377 | Q4: 5500
E5: Margin | F5: =F3-F4 -> 157940 | Q5: 4000
Q6: 4000
E7: Standard Revenue All | F7: ='2026'!F42 -> 101526 | I7: =F7 -> 101526
E8: Standard COGS NET | F8: ='2026'!F43 -> 67479
E9: Margin | F9: =F7-F8 -> 34047
E11: TOTAL Margin | F11: =F5+F9 -> 191987
E13: EXPENSES | F13: 205000 | K13: 131k in total payroll across all platforms | O13: 35k in expense | Q13: $165k total
E15: Co-Marketing Dollars - added | F15: =(12500+4000)/3 -> 5500 | I15: AvePoint and Barracuda | L15: 5.5k x 3 months
E17: NET Profitability | F17: =F11-F13+F15 -> -7513 | I17: Month to date
E19: Additional Cash Required | F19: 20000
E21: Total Cash NET | F21: =F17-F19 -> -27513 | I21: Month to date
E24: Project Additional Revenue | F24: 40000 | I24: Expected additional revenue based on YTD trend
E25: Margin expected - uses MTD trend | F25: ='2026'!F45 -> 0.33535252 | I25: MTD margin trend
E26: Net Expected Margin | F26: =F24*F25 -> 13414.101
E28: NET Profitability | F28: =F17+F26 -> 5901.1008 | I28: =F28/I32 -> 0.019294543
E29: NET CASH | F29: =F21+F26 -> -14098.899
I32: =I3+I7 -> 305843 | J32: Total Revenue MTD
I33: =I32*0.18 -> 55051.74 | J33: 0.18
I34: =F28 -> 5901.1008 | J34: =I34/I32 -> 0.019294543
I36: =I32+F24 -> 345843 | J36: Total Revenue Projected
I37: =I36*J37 -> 62251.74 | J37: 0.18

Sheet 2026
G1: 2026
A2: Forecast | C2: Jan | D2: Feb | E2: Mar | F2: Apr | G2: May | H2: Jun | I2: Jul | J2: Aug | K2: Sept | L2: Oct | M2: Nov | N2: Dec | O2: YTD Total
A3: Recurring Sales Invoiced | B3: Agreement | C3: 294517 | D3: 287630 | E3: 296845 | F3: 204317 | O3: =SUM(C3:N3) -> 1083309 | Q3: NOTES:
B4: New Agreement in Std | O4: =SUM(C4:N4) -> 0 | Q4: Agreement invoices that go out on the 8th of the month:
B5: ITMS | O5: =SUM(C5:N5) -> 0 | Q5: ARC - comprehensive services $84,000
B6: Licensing | O6: =SUM(F6:N6) -> 0 | Q6: Invoiced on 8th of month: BUNZL - de Mexico - invoiced this month for this month. Includes overages from last month. $17k
B7: Comprehensive Services | O7: =SUM(C7:N7) -> 0 | Q7: License Agreements = $38,000
B8: Other | O8: =SUM(C8:N8) -> 0
A10: New Sales Invoiced [INPUTS] | B10: Standard | C10: 106724 | D10: 147864 | E10: 126944 | F10: 101029 | O10: =SUM(C10:N10) -> 482561
B11: Miscellaneous - Invoiced | C11: 1642 | D11: 2385 | E11: 5357 | F11: 1295 | O11: =SUM(C11:N11) -> 10679
B12: Credit Memo - Invoiced | C12: -630 | D12: -17761 | E12: -12220 | F12: -5118 | O12: =SUM(C12:N12) -> -35729
E13: 5212
A14: Pending and Projected Sales | B14: Pending Project Milestones | G14: =10250+1800 -> 12050 | H14: =1125 -> 1125 | I14: 3600 | O14: =SUM(C14:N14) -> 16775 | T14: =R20-R21-R22 -> 66787
B15: Hubspot Pipeline at 40% | O15: =SUM(C15:N15) -> 0
B16: OPPS High Forecast (inputs)
B17: OPPS Low Forecast (inputs)
A19: Total | B19: Total Revenue | C19: =C3+C10+C11+C12 -> 402253 | D19: =D3+D10+D11+D12 -> 420118 | E19: =E3+E10+E11+E12 -> 416926 | F19: =F3+F10+F11+F12 -> 301523 | G19: =G3+G10+G11+G12 -> 0 | H19: =H3+H10+H11+H12 -> 0 | I19: =I3+I10+I11+I12 -> 0 | J19: =J3+J10+J11+J12 -> 0 | ... M19: =M3+M10+M11+M12 -> 0 | N19: =N3+N6+N10+N11+N12 -> 0 | O19: =SUM(C19:N19) -> 1540820 | R19: AGREEMENT | S19: Breakdown
B20: High | C20: =C3+C5+C6+C10+C11+C16+C12 -> 402253 | D20: =D3+D5+D6+D10+D11+D16+D12 -> 420118 | E20: =E3+E5+E6+E10+E11+E16+E12+E14 -> 416926 | F20: =F19+F16 -> 301523 | G20: =G3+G5+G6+G10+G11+G16+G12+G14 -> 12050 | H20: =H3+H5+H6+H10+H11+H16+H12+H14 -> 1125 | I20: =I3+I5+I6+I10+I11+I16+I12+I14 -> 3600 | J20: =J3+J5+J6+J10+J11+J16+J12+J14 -> 0 | K20: =K3+K5+K6+K7+K8+K10+K11+K12+K14+K16 -> 0 | L20: =L3+L5+L6+L7+L8+L10+L11+L12+L14+L16 -> 0 | M20: =M3+M5+M6+M7+M8+M10+M11+M12+M14+M16 -> 0 | N20: =N3+N5+N6+N7+N8+N10+N11+N12+N14+N16 -> 0 | R20: 310492 | S20: TOTAL
B21: Low | C21: =C3+C5+C6+C10+C11+C12+C17 -> 402253 | D21: =D3+D5+D6+D10+D11+D12+D17 -> 420118 | E21: =E3+E5+E6+E10+E11+E12+E17+E14 -> 416926 | F21: =F19+F17 -> 301523 | G21: =G3+G5+G6+G10+G11+G12+G17+G14 -> 12050 | H21: =H3+H5+H6+H10+H11+H12+H17+H14 -> 1125 | I21: =I3+I5+I6+I10+I11+I12+I17+I14 -> 3600 | J21: =J3+J5+J6+J10+J11+J12+J17+J14 -> 0 | K21: =K3+K5+K6+K7+K8+K10+K11+K12+K14+K17 -> 0 | L21: =L3+L5+L6+L7+L8+L10+L11+L12+L14+L17 -> 0 | M21: =M3+M5+M6+M7+M8+M10+M11+M12+M14+M17 -> 0 | N21: =N3+N5+N6+N7+N8+N10+N11+N12+N14+N17 -> 0 | R21: =84424+9675 -> 94099 | S21: Comp Services + Project (BUNZL de Mex)
A22: Gap (/mo) | B22: Revenue to Goal | C22: =C19-C26 -> 2253 | D22: =D19-D26 -> 20118 | E22: =E19-E26 -> 16926 | F22: =F19-F26 -> -98477 | G22: =G19-G26 -> -400000 | H22: =H19-H26 -> -400000 | I22: =I19-I26 -> -400000 | J22: =J19-J26 -> -400000 | ... N22: =N19-N26 -> -400001 | O22: =SUM(C22:N22) -> -3259181 | R22: 149606 | S22: Managed Services
R23: =R20-R21-R22 -> 66787 | S23: Licensing/Server (Agreement)
A24: Rolling Actual/Forecast | B24: Actual | C24: =C19 -> 402253 | D24: =C24+D19 -> 822371 | E24: =D24+E19 -> 1239297 | F24: =E24+F19 -> 1540820 | G24: =F24+G19 -> 1540820 | H24: =G24+H19 -> 1540820 | I24: =H24+I19 -> 1540820 | J24: =I24+J19 -> 1540820 | K24: =J24+K19 -> 1540820 | ... N24: =M24+N19 -> 1540820 | O24: =N24 -> 1540820
B25: Actual ROLLING | C25: =C19 -> 402253 | D25: =C25+D19 -> 822371 | E25: =D25+E19 -> 1239297 | F25: =E25+F19 -> 1540820 | G25: =F25+G19 -> 1540820 | H25: =G25+H19 -> 1540820 | I25: =H25+I19 -> 1540820 | J25: =I25+J19 -> 1540820 | K25: =J25+K19 -> 1540820 | ... N25: =M25+N19 -> 1540820
A26: Monthly Goal | B26: Revenue GOAL | C26: 400000 | D26: 400000 | E26: 400000 | F26: 400000 | G26: 400000 | H26: 400000 | I26: 400000 | J26: 400000 | K26: 400000 | L26: 400000 | M26: 400000 | N26: 400001 | O26: =SUM(C26:N26) -> 4800001 | Q26: cogs | R26: rev
B27: Rolling GOAL | C27: =C26 -> 400000 | D27: =C27+D26 -> 800000 | E27: =D27+E26 -> 1200000 | F27: =E27+F26 -> 1600000 | G27: =F27+G26 -> 2000000 | H27: =G27+H26 -> 2400000 | I27: =H27+I26 -> 2800000 | J27: =I27+J26 -> 3200000 | K27: =J27+K26 -> 3600000 | ... N27: =M27+N26 -> 4800001 | O27: =N27 -> 4800001 | Q27: 55014 | R27: 84424 | S27: arc | T27: =R27-Q27 -> 29410 | U27: =T27/R27 -> 0.34836066
A28: Rolling Goal | C28: =C24-C27 -> 2253 | D28: =D24-D27 -> 22371 | E28: =E24-E27 -> 39297 | F28: =F24-F27 -> -59180 | G28: =G24-G27 -> -459180 | H28: =H24-H27 -> -859180 | I28: =I24-I27 -> -1259180 | J28: =J24-J27 -> -1659180 | ... N28: =N24-N27 -> -3259181 | O28: =N28 -> -3259181 | T28: =R28-Q28 -> 0
A29: Rolling Goal | C29: Jan | D29: Feb | E29: Mar | F29: Apr | G29: May | H29: Jun | I29: Jul | J29: Aug | K29: Sept | L29: Oct | M29: Nov | N29: Dec | O29: 2019 | T29: =R29-Q29 -> 0
A30: Rolling Goal | C30: =SUMIFS(#REF!,#REF!,1,#REF!,2019,#REF!,"open") -> #REF! | D30: =SUMIFS(#REF!,#REF!,2,#REF!,2019,#REF!,"open") -> #REF! | E30: =SUMIFS(#REF!,#REF!,3,#REF!,2019,#REF!,"open") -> #REF! | F30: =SUMIFS(#REF!,#REF!,4,#REF!,2019,#REF!,"open") -> #REF! | G30: =SUMIFS(#REF!,#REF!,5,#REF!,2019,#REF!,"open") -> #REF! | H30: =SUMIFS(#REF!,#REF!,6,#REF!,2019,#REF!,"open") -> #REF! | I30: =SUMIFS(#REF!,#REF!,7,#REF!,2019,#REF!,"open") -> #REF! | J30: =SUMIFS(#REF!,#REF!,8,#REF!,2019,#REF!,"open") -> #REF! | K30: =SUMIFS(#REF!,#REF!,9,#REF!,2019,#REF!,"open") -> #REF! | L30: =SUMIFS(#REF!,#REF!,10,#REF!,2019,#REF!,"open") -> #REF! | M30: =SUMIFS(#REF!,#REF!,11,#REF!,2019,#REF!,"open") -> #REF! | N30: =SUMIFS(#REF!,#REF!,12,#REF!,2019,#REF!,"open") -> #REF! | O30: =SUM(C30:N30) -> #REF! | T30: =R30-Q30 -> 0
A31: Rolling Goal | C31: =SUMIFS(#REF!,#REF!,1,#REF!,2019,#REF!,"*",#REF!,"open") -> #REF! | D31: =SUMIFS(#REF!,#REF!,2,#REF!,2019,#REF!,"*",#REF!,"open") -> #REF! | E31: =SUMIFS(#REF!,#REF!,3,#REF!,2019,#REF!,"*",#REF!,"open") -> #REF! | F31: =SUMIFS(#REF!,#REF!,4,#REF!,2019,#REF!,"*",#REF!,"open") -> #REF! | G31: =SUMIFS(#REF!,#REF!,5,#REF!,2019,#REF!,"*",#REF!,"open") -> #REF! | H31: =SUMIFS(#REF!,#REF!,6,#REF!,2019,#REF!,"*",#REF!,"open") -> #REF! | I31: =SUMIFS(#REF!,#REF!,7,#REF!,2019,#REF!,"*",#REF!,"open") -> #REF! | J31: =SUMIFS(#REF!,#REF!,8,#REF!,2019,#REF!,"*",#REF!,"open") -> #REF! | K31: =SUMIFS(#REF!,#REF!,9,#REF!,2019,#REF!,"*",#REF!,"open") -> #REF! | L31: =SUMIFS(#REF!,#REF!,10,#REF!,2019,#REF!,"*",#REF!,"open") -> #REF! | M31: =SUMIFS(#REF!,#REF!,11,#REF!,2019,#REF!,"*",#REF!,"open") -> #REF! | N31: =SUMIFS(#REF!,#REF!,12,#REF!,2019,#REF!,"*",#REF!,"open") -> #REF! | O31: =SUM(C31:N31) -> #REF! | T31: =R31-Q31 -> 0
B32: Rolling GOAL Difference | C32: =C19-C26 -> 2253 | D32: =D19-D26+C32 -> 22371 | E32: =E19-E26+D32 -> 39297 | F32: =F19-F26+E32 -> -59180 | G32: =G19-G26+F32 -> -459180 | Q32: 6228 | R32: 9675 | S32: bunzl de mex | T32: =R32-Q32 -> 3447 | U32: =28/95 -> 0.29473684
A34: This green area does not roll into other areas. This is | B34: Project Revenue - Agreements | C34: =20000+95079 -> 115079 | D34: =20000+95079 -> 115079 | E34: =20000+95079 -> 115079 | O34: =SUM(C34:N34) -> 345237 | Q34: =SUM(Q27:Q33) -> 61242 | R34: =SUM(R27:R33) -> 94099
A35: a subset of AGREEMENT revenue. | B35: Project COGS Agreements (input) | C35: 68924 | D35: 68925 | E35: 68926 | O35: =SUM(C35:N35) -> 206775
A36: Breakdown reporting only | B36: Project Agreement Margin $ | C36: =C34-C35 -> 46155 | D36: =D34-D35 -> 46154 | E36: =E34-E35 -> 46153 | O36: =SUM(C36:N36) -> 138462 | Q36: =R34-Q34 -> 32857 | R36: =Q36/R34 -> 0.34917481
B37: Project Agreement Margin % | C37: =C36/C34 -> 0.40107231 | D37: =D36/D34 -> 0.40106362 | E37: =E36/E34 -> 0.40105493 | O37: =O36/O34 -> 0.40106362
B38: Agreement Revenue | C38: =C3 -> 294517 | D38: =D3 -> 287630 | E38: =E3 -> 296845 | F38: =F3 -> 204317 | G38: =G3 -> 0 | H38: =H3 -> 0 | I38: =I3 -> 0 | J38: =J3 -> 0 | ... N38: =N3 -> 0 | O38: =SUM(C38:N38) -> 1083309
B39: Agreement COGS (input) | C39: 102260 | D39: 99927 | E39: 106236 | F39: 46377 | O39: =SUM(C39:N39) -> 354800
B40: Agreement Margin $ | C40: =C38-C39 -> 192257 | D40: =D38-D39 -> 187703 | E40: =E38-E39 -> 190609 | F40: =F38-F39 -> 157940 | G40: =G38-G39 -> 0 | H40: =H38-H39 -> 0 | I40: =I38-I39 -> 0 | J40: =J38-J39 -> 0 | ... N40: =N38-N39 -> 0 | O40: =SUM(C40:N40) -> 728509
B41: Agreement Margin % | C41: =C40/C38 -> 0.65278745 | D41: =D40/D38 -> 0.65258492 | E41: =E40/E38 -> 0.64211626 | F41: =F40/F38 -> 0.77301448 | G41: =G40/G38 -> #DIV/0! | H41: =H40/H38 -> #DIV/0! | I41: =I40/I38 -> #DIV/0! | J41: =J40/J38 -> #DIV/0! | ... O41: =O40/O38 -> 0.67248495
B42: Standard Revenue (w Misc & CMs) | C42: 107736 | D42: 132487 | E42: 120081 | F42: 101526 | O42: =SUM(C42:N42) -> 461830
B43: Standard Misc COGS (input) | C43: 67536 | D43: 83944 | E43: 76229 | F43: 67479 | O43: =SUM(C43:N43) -> 295188
B44: Standard Margin $ | C44: =C42-C43 -> 40200 | D44: =D42-D43 -> 48543 | E44: =E42-E43 -> 43852 | F44: =F42-F43 -> 34047 | G44: =G42-G43 -> 0 | H44: =H42-H43 -> 0 | I44: =I42-I43 -> 0 | J44: =J42-J43 -> 0 | ... N44: =N42-N43 -> 0 | O44: =SUM(C44:N44) -> 166642
B45: Standard Margin % | C45: =C44/C42 -> 0.37313433 | D45: =D44/D42 -> 0.36639821 | E45: =E44/E42 -> 0.36518683 | F45: =F44/F42 -> 0.33535252 | G45: =G44/G42 -> #DIV/0! | H45: =H44/H42 -> #DIV/0! | I45: =I44/I42 -> #DIV/0! | J45: =J44/J42 -> #DIV/0! | ... O45: =O44/O42 -> 0.36082974
B46: Miscellaneous COGS (input)
B47: TOTAL Revenue | C47: =C38+C42 -> 402253 | D47: =D38+D42 -> 420117 | E47: =E38+E42 -> 416926 | F47: =F38+F42 -> 305843 | G47: =G38+G42 -> 0 | H47: =H38+H42 -> 0 | I47: =I38+I42 -> 0 | J47: =J38+J42 -> 0 | ... N47: =N38+N42 -> 0 | O47: =SUM(C47:N47) -> 1545139
B48: TOTAL COGS | C48: =C39+C43 -> 169796 | D48: =D39+D43 -> 183871 | E48: =E39+E43 -> 182465 | F48: =F39+F43 -> 113856 | G48: =G39+G43+G46 -> 0 | H48: =H39+H43+H46 -> 0 | I48: =I39+I43+I46 -> 0 | J48: =J39+J43+J46 -> 0 | K48: =K39+K43+K46 -> 0 | L48: =L39+L43+L46 -> 0 | M48: =M39+M43+M46 -> 0 | N48: =N39+N43+N46 -> 0 | O48: =SUM(C48:N48) -> 649988
B49: TOTAL [Blended] Margin $ | C49: =C47-C48 -> 232457 | D49: =D47-D48 -> 236246 | E49: =E47-E48 -> 234461 | F49: =F47-F48 -> 191987 | G49: =G47-G48 -> 0 | H49: =H47-H48 -> 0 | I49: =I47-I48 -> 0 | J49: =J47-J48 -> 0 | ... N49: =N47-N48 -> 0 | O49: =SUM(C49:N49) -> 895151
B50: TOTAL [Blended] Margin % | C50: =C49/C47 -> 0.57788755 | D50: =D49/D47 -> 0.56233383 | E50: =E49/E47 -> 0.56235639 | F50: =F49/F47 -> 0.62773057 | G50: =G49/G47 -> #DIV/0! | H50: =H49/H47 -> #DIV/0! | I50: =I49/I47 -> #DIV/0! | J50: =J49/J47 -> #DIV/0! | ... O50: =O49/O47 -> 0.57933364
B51: TARGET Minimum MARGIN (input) | C51: 223000 | D51: 223000 | E51: 223000 | F51: 200000 | G51: 200000 | H51: 200000 | I51: 200000 | J51: 200000 | K51: 200000 | L51: 200000 | M51: 200000 | N51: 200000 | O51: =SUM(C51:N51) -> 2469000
B52: $ Over TARGET MARGIN (Profit) | C52: =C49-C51 -> 9457 | D52: =D49-D51 -> 13246 | E52: =E49-E51 -> 11461 | F52: =F49-F51 -> -8013 | G52: =G49-G51 -> -200000 | H52: =H49-H51 -> -200000 | I52: =I49-I51 -> -200000 | J52: =J49-J51 -> -200000 | ... N52: =N49-N51 -> -200000 | O52: =SUM(C52:N52) -> -1573849
B53: Net Profit % | C53: =C52/C19 -> 0.023510079 | D53: =D52/D19 -> 0.031529237 | E53: =E52/E19 -> 0.027489291 | F53: =F52/F19 -> -0.026575087 | G53: =G52/G19 -> #DIV/0! | H53: =H52/H19 -> #DIV/0! | I53: =I52/I19 -> #DIV/0! | J53: =J52/J19 -> #DIV/0! | ... N53: =N52/N19 -> #DIV/0!
B55: Profit GOAL at Target 18% | C55: =C19*0.18 -> 72405.54 | D55: =D19*0.18 -> 75621.24 | E55: =E19*0.18 -> 75046.68 | F55: =F19*0.18 -> 54274.14 | G55: =G19*0.18 -> 0 | H55: =H19*0.18 -> 0 | I55: =I19*0.18 -> 0 | J55: =J19*0.18 -> 0 | ... N55: =N19*0.18 -> 0 | O55: =SUM(C55:N55) -> 277347.6 | P55: 18% Goal
A57: RECURRING SERVICES - UP/DOWN
A59: Managed Services (only) | B59: End of 2025...2026 Start… | C59: 145911 | D59: =C59 -> 145911 | E59: =D59 -> 145911 | F59: =E59 -> 145911 | G59: =F59 -> 145911 | H59: =G59 -> 145911 | I59: =H59 -> 145911 | J59: =I59 -> 145911 | K59: =J59 -> 145911 | ... N59: =M59 -> 145911 | O59: =SUM(C59:N59) -> 1750932
O60: =SUM(C60:N60) -> 0
B61: BUNZL - 2 year agreement reduction | C61: -5000 | D61: -5000 | E61: -5000 | F61: -5000 | G61: -5000 | H61: -5000 | I61: -5000 | J61: -5000 | K61: -5000 | L61: -5000 | M61: -5000 | N61: -5000 | O61: =SUM(C61:N61) -> -60000
B62: Act reduction - leaving | C62: -5730 | D62: -5730 | E62: -5730 | F62: -5730 | G62: -5730 | H62: -5730 | I62: -5730 | J62: -5730 | K62: -5730 | L62: -5730 | M62: -5730 | N62: -5730 | O62: =SUM(C62:N62) -> -68760
B63: FS Unlimited: MS Agrmt began 1/15 | C63: 302 | D63: 550 | E63: 550 | F63: 550 | G63: 550 | H63: 550 | I63: 550 | J63: 550 | K63: 550 | L63: 550 | M63: 550 | N63: 550 | O63: =SUM(C63:N63) -> 6352
B64: Amelia Newcomb Dressage: MS Agrmt began 1/19 | C64: 301.61 | D64: 850 | E64: 850 | F64: 850 | G64: 850 | H64: 850 | I64: 850 | J64: 850 | K64: 850 | L64: 850 | M64: 850 | N64: 850 | O64: =SUM(C64:N64) -> 9651.61
B65: Designated Brokers: Adtl 4 MS Tier 1 Wkstns | F65: 300 | G65: 300 | H65: 300 | I65: 300 | J65: 300 | K65: 300 | L65: 300 | M65: 300 | N65: 300 | O65: =SUM(C65:N65) -> 2700
B66: TransGo: Adtl 2 MS Tier 1 Wkstns | F66: 100 | G66: 100 | H66: 100 | I66: 100 | J66: 100 | K66: 100 | L66: 100 | M66: 100 | N66: 100 | O66: =SUM(C66:N66) -> 900
B67: Vinyl Works: Adtl 6 MS Tier 2 Wkstns | F67: 510 | G67: 510 | H67: 510 | I67: 510 | J67: 510 | K67: 510 | L67: 510 | M67: 510 | N67: 510 | O67: =SUM(C67:N67) -> 4590
B68: Realworld - increase | F68: 510 | G68: 510 | H68: 510 | I68: 510 | J68: 510 | K68: 510 | L68: 510 | M68: 510 | N68: 510 | O68: =SUM(C68:N68) -> 4590
B69: Autism Systems - increase | F69: 325 | G69: 325 | H69: 325 | I69: 325 | J69: 325 | K69: 325 | L69: 325 | M69: 325 | N69: 325 | O69: =SUM(C69:N69) -> 2925
B70: Fire Sprinkler - increase | F70: 269 | G70: 269 | H70: 269 | I70: 269 | J70: 269 | K70: 269 | L70: 269 | M70: 269 | N70: 269 | O70: =SUM(C70:N70) -> 2421
B71: Secure Money Advisors - increase | G71: 1615 | H71: 1615 | I71: 1615 | J71: 1615 | K71: 1615 | L71: 1615 | M71: 1615 | N71: 1615 | O71: =SUM(C71:N71) -> 12920
B72: FS Unlimited: Wkstn adjustment | E72: -50 | F72: -50 | G72: -50 | H72: -50 | I72: -50 | J72: -50 | K72: -50 | L72: -50 | M72: -50 | N72: -50 | O72: =SUM(C72:N72) -> -500
B73: Pelage - increase | F73: 425 | G73: 425 | H73: 425 | I73: 425 | J73: 425 | K73: 425 | L73: 425 | M73: 425 | N73: 425 | O73: =SUM(C73:N73) -> 3825
B74: Dot by Dot - increase | G74: 60 | H74: 60 | I74: 60 | J74: 60 | K74: 60 | L74: 60 | M74: 60 | N74: 60 | O74: =SUM(C74:N74) -> 480
B75: Sea Ranch - leaving | I75: -2500 | J75: -2500 | K75: -2500 | L75: -2500 | M75: -2500 | N75: -2500 | O75: =SUM(C75:N75) -> -15000
B76: CWS - increase | F76: 385 | G76: 385 | H76: 385 | I76: 385 | J76: 385 | K76: 385 | L76: 385 | M76: 385 | N76: 385 | O76: =SUM(C76:N76) -> 3465
B77: Conejo - leaving | G77: -3770 | H77: -3770 | I77: -3770 | J77: -3770 | K77: -3770 | L77: -3770 | M77: -3770 | N77: -3770 | O77: =SUM(C77:N77) -> -30160
B78: Toro Global | F78: 735 | G78: 735 | H78: 735 | I78: 735 | J78: 735 | K78: 735 | L78: 735 | M78: 735 | N78: 735 | O78: =SUM(C78:N78) -> 6615
B79: Shaina Speaks - first 5 users | F79: 280 | G79: 525 | H79: 525 | I79: 525 | J79: 525 | K79: 525 | L79: 525 | M79: 525 | N79: 525 | O79: =SUM(M79:N79) -> 1050
O80: =SUM(M80:N80) -> 0
O81: =N81 -> 0
B83: TOTAL NET | C83: =SUM(C59:C82) -> 135784.61 | D83: =SUM(D59:D82) -> 136581 | E83: =SUM(E59:E82) -> 136531 | F83: =SUM(F59:F82) -> 140370 | G83: =SUM(G59:G82) -> 138520 | H83: =SUM(H59:H82) -> 138520 | I83: =SUM(I59:I82) -> 136020 | J83: =SUM(J59:J82) -> 136020 | ... O83: =SUM(O59:O82) -> 1638996.6
B84: Increase month over month | C84: =C83-C59 -> -10126.39 | D84: =D83-C83 -> 796.39 | E84: =E83-D83 -> -50 | F84: =F83-E83 -> 3839 | G84: =G83-F83 -> -1850 | H84: =H83-G83 -> 0 | I84: =I83-H83 -> -2500 | J84: =J83-I83 -> 0 | K84: =K83-J83 -> 0 | ... N84: =N83-M83 -> 0 | O84: =SUM(C84:N84) -> -9891
B87: Rolling NET Increase over 2023 (total) | C87: =C83-C59 -> -10126.39 | D87: =D83-D59 -> -9330 | E87: =E83-E59 -> -9380 | F87: =F83-F59 -> -5541 | G87: =G83-G59 -> -7391 | H87: =H83-H59 -> -7391 | I87: =I83-I59 -> -9891 | J87: =J83-J59 -> -9891 | ... O87: =O83-O59 -> -111935.39
B89: ACTUAL MS ONLY per CW | E89: 138827
B90: Likely different based on MS revenue invoiced via Std/Misc for first month or two | E90: =E89-E83 -> 2296
E94: $187k | F94: High water mark - Dec 2024
H103: 1 | I103: 2 | J103: 3 | K103: 4 | L103: 5 | M103: 6 | N103: 7 | O103: 8 | P103: 10
G104: 2022 | H104: 2023 | I104: 2024 | J104: 2025 | K104: 2026 | L104: 2027 | M104: 2028 | N104: 2029 | O104: 2030 | P104: 2032
F106: MS Monthly | H106: 185000 | I106: =H106+50000 -> 235000 | J106: =I106+50000 -> 285000 | K106: =J106+50000 -> 335000 | L106: =K106+50000 -> 385000 | M106: =L106+50000 -> 435000 | N106: =M106+50000 -> 485000 | O106: =N106+50000 -> 535000 | P106: =#REF!+50000 -> #REF!
F108: Project Mo + Recurring Other | G108: =G106*1.5 -> 0 | H108: 130000 | I108: 400000 | J108: =J106*1.5 -> 427500 | K108: =K106*1.5 -> 502500 | L108: =L106*1.5 -> 577500 | M108: =M106*1.5 -> 652500 | N108: =N106*1.5 -> 727500 | O108: =O106*1.5 -> 802500 | P108: =P106*1.5 -> #REF!
F110: One Off Sales | H110: 100000
F112: Mo Total | G112: =SUM(G106:G111) -> 0 | H112: =SUM(H106:H111) -> 415000 | I112: =SUM(I106:I111) -> 635000 | J112: =SUM(J106:J111) -> 712500 | K112: =SUM(K106:K111) -> 837500 | L112: =SUM(L106:L111) -> 962500 | M112: =SUM(M106:M111) -> 1087500 | N112: =SUM(N106:N111) -> 1212500 | ... P112: =SUM(P106:P111) -> #REF!
F114: Annual Rev | G114: =G112*12 -> 0 | H114: =H112*12 -> 4980000 | I114: =I112*12 -> 7620000 | J114: =J112*12 -> 8550000 | K114: =K112*12 -> 10050000 | L114: =L112*12 -> 11550000 | M114: =M112*12 -> 13050000 | N114: =N112*12 -> 14550000 | ... P114: =P112*12 -> #REF!

Sheet 2025
G1: 2025
A2: Forecast | C2: Jan | D2: Feb | E2: Mar | F2: Apr | G2: May | H2: Jun | I2: Jul | J2: Aug | K2: Sept | L2: Oct | M2: Nov | N2: Dec | O2: YTD Total
A3: Recurring Sales Invoiced | B3: Agreement | C3: 322280 | D3: 321976 | E3: 328979 | F3: 382362 | G3: 381216 | H3: 364130 | I3: 316503 | J3: 320352 | K3: 316248 | L3: 310492 | M3: 315280 | N3: 318600 | O3: =SUM(C3:N3) -> 3998418 | Q3: NOTES:
B4: New Agreement in Std | O4: =SUM(C4:N4) -> 0 | Q4: Agreement invoices that are delayed until 8th of the month:
B5: ITMS | O5: =SUM(C5:N5) -> 0 | Q5: ARC - comprehensive services $84,000
B6: Licensing | O6: =SUM(F6:N6) -> 0 | Q6: Invoiced on 8th of month: BUNZL - de Mexico - invoiced this month for this month. Includes overages from last month. $9500
B7: Comprehensive Services | O7: =SUM(C7:N7) -> 0 | Q7: License Agreements = $38,000
B8: Other | O8: =SUM(C8:N8) -> 0
A10: New Sales Invoiced [INPUTS] | B10: Standard and Misc - Invoiced | C10: 40401 | D10: 103232 | E10: 59881 | F10: 142704 | G10: 144085 | H10: 62777 | I10: 58928 | J10: 244650 | K10: 73181 | L10: 108546 | M10: 90268 | N10: 111861 | O10: =SUM(C10:N10) -> 1240514
B11: Miscellaneous - Invoiced | N11: 4418 | O11: =SUM(C11:N11) -> 4418
B12: Credit Memo - Invoiced | N12: -16530 | O12: =SUM(C12:N12) -> -16530
P13: TOTAL
A14: Pending and Projected Sales | B14: Pending Project Milestones | N14: 18000 | O14: =SUM(C14:N14) -> 18000 | P14: 49235 | T14: =R20-R21-R22 -> 66787
B15: Hubspot Pipeline at 40% | O15: =SUM(C15:N15) -> 0
B16: OPPS High Forecast (inputs)
B17: OPPS Low Forecast (inputs)
A19: Total | B19: Total Revenue | C19: =C3+C6+C10 -> 362681 | D19: =D3+D6+D10 -> 425208 | E19: =E3+E6+E10 -> 388860 | F19: =F3+F6+F10 -> 525066 | G19: =G3+G6+G10 -> 525301 | H19: =H3+H6+H10 -> 426907 | I19: =I3+I6+I10 -> 375431 | J19: =J3+J6+J10 -> 565002 | ... M19: =M3+M6+M10 -> 405548 | N19: =N3+N6+N10+N11+N12 -> 418349 | O19: =SUM(C19:N19) -> 5226820 | R19: AGREEMENT | S19: Breakdown
B20: High | C20: =C3+C5+C6+C10+C11+C16+C12 -> 362681 | D20: =D3+D5+D6+D10+D11+D16+D12 -> 425208 | E20: =E3+E5+E6+E10+E11+E16+E12+E14 -> 388860 | F20: =F19+F16 -> 525066 | G20: =G3+G5+G6+G10+G11+G16+G12+G14 -> 525301 | H20: =H3+H5+H6+H10+H11+H16+H12+H14 -> 426907 | I20: =I3+I5+I6+I10+I11+I16+I12+I14 -> 375431 | J20: =J3+J5+J6+J10+J11+J16+J12+J14 -> 565002 | K20: =K3+K5+K6+K7+K8+K10+K11+K12+K14+K16 -> 389429 | L20: =L3+L5+L6+L7+L8+L10+L11+L12+L14+L16 -> 419038 | M20: =M3+M5+M6+M7+M8+M10+M11+M12+M14+M16 -> 405548 | N20: =N3+N5+N6+N7+N8+N10+N11+N12+N14+N16 -> 436349 | R20: 310492 | S20: TOTAL
B21: Low | C21: =C3+C5+C6+C10+C11+C12+C17 -> 362681 | D21: =D3+D5+D6+D10+D11+D12+D17 -> 425208 | E21: =E3+E5+E6+E10+E11+E12+E17+E14 -> 388860 | F21: =F19+F17 -> 525066 | G21: =G3+G5+G6+G10+G11+G12+G17+G14 -> 525301 | H21: =H3+H5+H6+H10+H11+H12+H17+H14 -> 426907 | I21: =I3+I5+I6+I10+I11+I12+I17+I14 -> 375431 | J21: =J3+J5+J6+J10+J11+J12+J17+J14 -> 565002 | K21: =K3+K5+K6+K7+K8+K10+K11+K12+K14+K17 -> 389429 | L21: =L3+L5+L6+L7+L8+L10+L11+L12+L14+L17 -> 419038 | M21: =M3+M5+M6+M7+M8+M10+M11+M12+M14+M17 -> 405548 | N21: =N3+N5+N6+N7+N8+N10+N11+N12+N14+N17 -> 436349 | R21: =84424+9675 -> 94099 | S21: Comp Services + Project (BUNZL de Mex)
A22: Gap (/mo) | B22: Revenue to Goal | C22: =C19-C26 -> -37319 | D22: =D19-D26 -> 25208 | E22: =E19-E26 -> -11140 | F22: =F19-F26 -> 125066 | G22: =G19-G26 -> 125301 | H22: =H19-H26 -> 26907 | I22: =I19-I26 -> -24569 | J22: =J19-J26 -> 165002 | ... N22: =N19-N26 -> 18348 | O22: =SUM(C22:N22) -> 426819 | R22: 149606 | S22: Managed Services
R23: =R20-R21-R22 -> 66787 | S23: Licensing/Server (Agreement)
A24: Rolling Actual/Forecast | B24: Actual | C24: =C19 -> 362681 | D24: =C24+D19 -> 787889 | E24: =D24+E19 -> 1176749 | F24: =E24+F19 -> 1701815 | G24: =F24+G19 -> 2227116 | H24: =G24+H19 -> 2654023 | I24: =H24+I19 -> 3029454 | J24: =I24+J19 -> 3594456 | K24: =J24+K19 -> 3983885 | ... N24: =M24+N19 -> 5226820 | O24: =N24 -> 5226820
B25: Actual ROLLING | C25: =C19 -> 362681 | D25: =C25+D19 -> 787889 | E25: =D25+E19 -> 1176749 | F25: =E25+F19 -> 1701815 | G25: =F25+G19 -> 2227116 | H25: =G25+H19 -> 2654023 | I25: =H25+I19 -> 3029454 | J25: =I25+J19 -> 3594456 | K25: =J25+K19 -> 3983885 | ... N25: =M25+N19 -> 5226820
A26: Monthly Goal | B26: Revenue GOAL | C26: 400000 | D26: 400000 | E26: 400000 | F26: 400000 | G26: 400000 | H26: 400000 | I26: 400000 | J26: 400000 | K26: 400000 | L26: 400000 | M26: 400000 | N26: 400001 | O26: =SUM(C26:N26) -> 4800001 | Q26: cogs | R26: rev
B27: Rolling GOAL | C27: =C26 -> 400000 | D27: =C27+D26 -> 800000 | E27: =D27+E26 -> 1200000 | F27: =E27+F26 -> 1600000 | G27: =F27+G26 -> 2000000 | H27: =G27+H26 -> 2400000 | I27: =H27+I26 -> 2800000 | J27: =I27+J26 -> 3200000 | K27: =J27+K26 -> 3600000 | ... N27: =M27+N26 -> 4800001 | O27: =N27 -> 4800001 | Q27: 55014 | R27: 84424 | S27: arc | T27: =R27-Q27 -> 29410 | U27: =T27/R27 -> 0.34836066
A28: Rolling Goal | C28: =C24-C27 -> -37319 | D28: =D24-D27 -> -12111 | E28: =E24-E27 -> -23251 | F28: =F24-F27 -> 101815 | G28: =G24-G27 -> 227116 | H28: =H24-H27 -> 254023 | I28: =I24-I27 -> 229454 | J28: =J24-J27 -> 394456 | ... N28: =N24-N27 -> 426819 | O28: =N28 -> 426819 | T28: =R28-Q28 -> 0
A29: Rolling Goal | C29: Jan | D29: Feb | E29: Mar | F29: Apr | G29: May | H29: Jun | I29: Jul | J29: Aug | K29: Sept | L29: Oct | M29: Nov | N29: Dec | O29: 2019 | T29: =R29-Q29 -> 0
A30: Rolling Goal | C30: =SUMIFS(#REF!,#REF!,1,#REF!,2019,#REF!,"open") -> #REF! | D30: =SUMIFS(#REF!,#REF!,2,#REF!,2019,#REF!,"open") -> #REF! | E30: =SUMIFS(#REF!,#REF!,3,#REF!,2019,#REF!,"open") -> #REF! | F30: =SUMIFS(#REF!,#REF!,4,#REF!,2019,#REF!,"open") -> #REF! | G30: =SUMIFS(#REF!,#REF!,5,#REF!,2019,#REF!,"open") -> #REF! | H30: =SUMIFS(#REF!,#REF!,6,#REF!,2019,#REF!,"open") -> #REF! | I30: =SUMIFS(#REF!,#REF!,7,#REF!,2019,#REF!,"open") -> #REF! | J30: =SUMIFS(#REF!,#REF!,8,#REF!,2019,#REF!,"open") -> #REF! | K30: =SUMIFS(#REF!,#REF!,9,#REF!,2019,#REF!,"open") -> #REF! | L30: =SUMIFS(#REF!,#REF!,10,#REF!,2019,#REF!,"open") -> #REF! | M30: =SUMIFS(#REF!,#REF!,11,#REF!,2019,#REF!,"open") -> #REF! | N30: =SUMIFS(#REF!,#REF!,12,#REF!,2019,#REF!,"open") -> #REF! | O30: =SUM(C30:N30) -> #REF! | T30: =R30-Q30 -> 0
A31: Rolling Goal | C31: =SUMIFS(#REF!,#REF!,1,#REF!,2019,#REF!,"*",#REF!,"open") -> #REF! | D31: =SUMIFS(#REF!,#REF!,2,#REF!,2019,#REF!,"*",#REF!,"open") -> #REF! | E31: =SUMIFS(#REF!,#REF!,3,#REF!,2019,#REF!,"*",#REF!,"open") -> #REF! | F31: =SUMIFS(#REF!,#REF!,4,#REF!,2019,#REF!,"*",#REF!,"open") -> #REF! | G31: =SUMIFS(#REF!,#REF!,5,#REF!,2019,#REF!,"*",#REF!,"open") -> #REF! | H31: =SUMIFS(#REF!,#REF!,6,#REF!,2019,#REF!,"*",#REF!,"open") -> #REF! | I31: =SUMIFS(#REF!,#REF!,7,#REF!,2019,#REF!,"*",#REF!,"open") -> #REF! | J31: =SUMIFS(#REF!,#REF!,8,#REF!,2019,#REF!,"*",#REF!,"open") -> #REF! | K31: =SUMIFS(#REF!,#REF!,9,#REF!,2019,#REF!,"*",#REF!,"open") -> #REF! | L31: =SUMIFS(#REF!,#REF!,10,#REF!,2019,#REF!,"*",#REF!,"open") -> #REF! | M31: =SUMIFS(#REF!,#REF!,11,#REF!,2019,#REF!,"*",#REF!,"open") -> #REF! | N31: =SUMIFS(#REF!,#REF!,12,#REF!,2019,#REF!,"*",#REF!,"open") -> #REF! | O31: =SUM(C31:N31) -> #REF! | T31: =R31-Q31 -> 0
B32: Rolling GOAL Difference | C32: =C19-C26 -> -37319 | D32: =D19-D26+C32 -> -12111 | E32: =E19-E26+D32 -> -23251 | F32: =F19-F26+E32 -> 101815 | G32: =G19-G26+F32 -> 227116 | Q32: 6228 | R32: 9675 | S32: bunzl de mex | T32: =R32-Q32 -> 3447 | U32: =28/95 -> 0.29473684
A34: This green area does not roll into other areas. This is | B34: Project Revenue - Agreements | C34: =20000+95079 -> 115079 | D34: =20000+95079 -> 115079 | E34: =20000+95079 -> 115079 | O34: =SUM(C34:N34) -> 345237 | Q34: =SUM(Q27:Q33) -> 61242 | R34: =SUM(R27:R33) -> 94099
A35: a subset of AGREEMENT revenue. | B35: Project COGS Agreements (input) | C35: 68924 | D35: 68925 | E35: 68926 | O35: =SUM(C35:N35) -> 206775
A36: Breakdown reporting only | B36: Project Agreement Margin $ | C36: =C34-C35 -> 46155 | D36: =D34-D35 -> 46154 | E36: =E34-E35 -> 46153 | O36: =SUM(C36:N36) -> 138462 | Q36: =R34-Q34 -> 32857 | R36: =Q36/R34 -> 0.34917481
B37: Project Agreement Margin % | C37: =C36/C34 -> 0.40107231 | D37: =D36/D34 -> 0.40106362 | E37: =E36/E34 -> 0.40105493 | O37: =O36/O34 -> 0.40106362
B38: Agreement Revenue | C38: =C3 -> 322280 | D38: =D3 -> 321976 | E38: =E3 -> 328979 | F38: =F3 -> 382362 | G38: =G3 -> 381216 | H38: =H3 -> 364130 | I38: =I3 -> 316503 | J38: =J3 -> 320352 | ... N38: =N3 -> 318600 | O38: =SUM(C38:N38) -> 3998418
B39: Agreement COGS (input) | C39: 102260 | D39: 99047 | E39: 118852 | F39: 145278 | G39: 142903 | H39: 135588 | I39: 110189 | J39: 111801 | K39: 110187 | L39: 107556 | M39: 110176 | N39: 110177 | O39: =SUM(C39:N39) -> 1404014
B40: Agreement Margin $ | C40: =C38-C39 -> 220020 | D40: =D38-D39 -> 222929 | E40: =E38-E39 -> 210127 | F40: =F38-F39 -> 237084 | G40: =G38-G39 -> 238313 | H40: =H38-H39 -> 228542 | I40: =I38-I39 -> 206314 | J40: =J38-J39 -> 208551 | ... N40: =N38-N39 -> 208423 | O40: =SUM(C40:N40) -> 2594404
B41: Agreement Margin % | C41: =C40/C38 -> 0.68269827 | D41: =D40/D38 -> 0.69237769 | E41: =E40/E38 -> 0.63872466 | F41: =F40/F38 -> 0.62005116 | G41: =G40/G38 -> 0.62513903 | H41: =H40/H38 -> 0.62763848 | I41: =I40/I38 -> 0.6518548 | J41: =J40/J38 -> 0.65100577 | ... O41: =O40/O38 -> 0.64885762
B42: Standard Revenue (w Misc & CMs) | C42: =C10 -> 40401 | D42: =D10 -> 103232 | E42: =E10 -> 59881 | F42: =F10 -> 142704 | G42: =G10 -> 144085 | H42: =H10 -> 62777 | I42: =I10 -> 58928 | J42: =J10 -> 244650 | ... M42: =M10 -> 90268 | N42: 99748 | O42: =SUM(C42:N42) -> 1228401
B43: Standard Misc COGS (input) | C43: 28221 | D43: 69474 | E43: 35161 | F43: 83376 | G43: 99661 | H43: 40425 | I43: 39040 | J43: 193722 | K43: 45707 | L43: 62784 | M43: 59227 | N43: 58463 | O43: =SUM(C43:N43) -> 815261
B44: Standard Margin $ | C44: =C42-C43 -> 12180 | D44: =D42-D43 -> 33758 | E44: =E42-E43 -> 24720 | F44: =F42-F43 -> 59328 | G44: =G42-G43 -> 44424 | H44: =H42-H43 -> 22352 | I44: =I42-I43 -> 19888 | J44: =J42-J43 -> 50928 | ... N44: =N42-N43 -> 41285 | O44: =SUM(C44:N44) -> 413140
B45: Standard Margin % | C45: =C44/C42 -> 0.30147769 | D45: =D44/D42 -> 0.327011 | E45: =E44/E42 -> 0.41281876 | F45: =F44/F42 -> 0.41574168 | G45: =G44/G42 -> 0.30831801 | H45: =H44/H42 -> 0.35605397 | I45: =I44/I42 -> 0.33749661 | J45: =J44/J42 -> 0.20816677 | ... O45: =O44/O42 -> 0.3363234
B46: Miscellaneous COGS (input)
B47: TOTAL Revenue | C47: =C38+C42 -> 362681 | D47: =D38+D42 -> 425208 | E47: =E38+E42 -> 388860 | F47: =F38+F42 -> 525066 | G47: =G38+G42 -> 525301 | H47: =H38+H42 -> 426907 | I47: =I38+I42 -> 375431 | J47: =J38+J42 -> 565002 | ... N47: =N38+N42 -> 418348 | O47: =SUM(C47:N47) -> 5226819
B48: TOTAL COGS | C48: =C39+C43 -> 130481 | D48: =D39+D43 -> 168521 | E48: =E39+E43 -> 154013 | F48: =F39+F43 -> 228654 | G48: =G39+G43+G46 -> 242564 | H48: =H39+H43+H46 -> 176013 | I48: =I39+I43+I46 -> 149229 | J48: =J39+J43+J46 -> 305523 | K48: =K39+K43+K46 -> 155894 | L48: =L39+L43+L46 -> 170340 | M48: =M39+M43+M46 -> 169403 | N48: =N39+N43+N46 -> 168640 | O48: =SUM(C48:N48) -> 2219275
B49: TOTAL [Blended] Margin $ | C49: =C47-C48 -> 232200 | D49: =D47-D48 -> 256687 | E49: =E47-E48 -> 234847 | F49: =F47-F48 -> 296412 | G49: =G47-G48 -> 282737 | H49: =H47-H48 -> 250894 | I49: =I47-I48 -> 226202 | J49: =J47-J48 -> 259479 | ... N49: =N47-N48 -> 249708 | O49: =SUM(C49:N49) -> 3007544
B50: TOTAL [Blended] Margin % | C50: =C49/C47 -> 0.64023205 | D50: =D49/D47 -> 0.60367397 | E50: =E49/E47 -> 0.60393715 | F50: =F49/F47 -> 0.56452332 | G50: =G49/G47 -> 0.53823808 | H50: =H49/H47 -> 0.58770177 | I50: =I49/I47 -> 0.60251285 | J50: =J49/J47 -> 0.45925324 | ... O50: =O49/O47 -> 0.57540619
B51: TARGET Minimum MARGIN (input) | C51: 235000 | D51: 218200 | E51: 210000 | F51: 204000 | G51: 204000 | H51: 204000 | I51: 204000 | J51: 204000 | K51: 204000 | L51: 204000 | M51: 204001 | N51: 204002 | O51: =SUM(C51:N51) -> 2499203
B52: $ Over TARGET MARGIN (Profit) | C52: =C49-C51 -> -2800 | D52: =D49-D51 -> 38487 | E52: =E49-E51 -> 24847 | F52: =F49-F51 -> 92412 | G52: =G49-G51 -> 78737 | H52: =H49-H51 -> 46894 | I52: =I49-I51 -> 22202 | J52: =J49-J51 -> 55479 | ... N52: =N49-N51 -> 45706 | O52: =SUM(C52:N52) -> 508341
B53: Net Profit % | C53: =C52/C19 -> -0.0077202831 | D53: =D52/D19 -> 0.090513349 | E53: =E52/E19 -> 0.063897032 | F53: =F52/F19 -> 0.17600073 | G53: =G52/G19 -> 0.1498893 | H53: =H52/H19 -> 0.10984594 | I53: =I52/I19 -> 0.059137365 | J53: =J52/J19 -> 0.098192573 | ... N53: =N52/N19 -> 0.10925328
B55: Profit GOAL at Target 18% | C55: =C19*0.18 -> 65282.58 | D55: =D19*0.18 -> 76537.44 | E55: =E19*0.18 -> 69994.8 | F55: =F19*0.18 -> 94511.88 | G55: =G19*0.18 -> 94554.18 | H55: =H19*0.18 -> 76843.26 | I55: =I19*0.18 -> 67577.58 | J55: =J19*0.18 -> 101700.36 | ... N55: =N19*0.18 -> 75302.82 | O55: =SUM(C55:N55) -> 940827.6 | P55: 18% Goal
A57: RECURRING SERVICES - UP/DOWN
A59: Managed Services (only) | B59: End of 2024 ...2025 Start… | C59: 177353 | D59: =C59 -> 177353 | E59: =D59 -> 177353 | F59: =E59 -> 177353 | G59: =F59 -> 177353 | H59: =G59 -> 177353 | I59: =H59 -> 177353 | J59: =I59 -> 177353 | K59: =J59 -> 177353 | ... N59: =M59 -> 177353 | O59: =SUM(C59:N59) -> 2128236
O60: =SUM(C60:N60) -> 0
B61: BUNZL - 2 year agreement reduction | C61: -12500 | D61: -12500 | E61: -12500 | F61: -12500 | G61: -12500 | H61: -12500 | I61: -12500 | J61: -12500 | K61: -12500 | L61: -12500 | M61: -12500 | N61: -12500 | O61: =SUM(C61:N61) -> -150000
B62: ARC - MS Reduction | E62: -4265 | F62: -4265 | G62: -4265 | H62: -4265 | I62: -4265 | J62: -4265 | K62: -4265 | L62: -4265 | M62: -4265 | N62: -4265 | O62: =SUM(C62:N62) -> -42650
B63: Southern Atlantic - MS Reduction | E63: -110 | F63: -110 | G63: -110 | H63: -110 | I63: -110 | J63: -110 | K63: -110 | L63: -110 | M63: -110 | N63: -110 | O63: =SUM(C63:N63) -> -1100
B64: AMIRI - Reduction | E64: -24750 | F64: -24750 | G64: -24750 | H64: -24750 | I64: -24750 | J64: -24750 | K64: -24750 | L64: -24750 | M64: -24750 | N64: -24750 | O64: =SUM(C64:N64) -> -247500
B65: Snap - MD Addition | D65: 640 | E65: 640 | F65: 640 | G65: 640 | H65: 640 | I65: 640 | J65: 640 | K65: 640 | L65: 640 | M65: 640 | N65: 640 | O65: =SUM(C65:N65) -> 7040
B66: Drive Wheel | D66: 510 | E66: 510 | F66: 510 | G66: 510 | H66: 510 | I66: 510 | J66: 510 | K66: 510 | L66: 510 | M66: 510 | N66: 510 | O66: =SUM(C66:N66) -> 5610
B67: Hohenstein | E67: 510 | F67: 510 | G67: 510 | H67: 510 | I67: 510 | J67: 510 | K67: 510 | L67: 510 | M67: 510 | N67: 510 | O67: =SUM(C67:N67) -> 5100
B68: Calpine - add | F68: 4755 | G68: 4755 | H68: 4755 | I68: 4755 | J68: 4755 | K68: 4755 | L68: 4755 | M68: 4755 | N68: 4755 | O68: =SUM(C68:N68) -> 42795
B69: Pacific Therapy - drop | G69: -1300 | H69: -1300 | I69: -1300 | J69: -1300 | K69: -1300 | L69: -1300 | M69: -1300 | N69: -1300 | O69: =SUM(C69:N69) -> -10400
B70: AVF - drop | G70: -1142 | H70: -1142 | I70: -1142 | J70: -1142 | K70: -1142 | L70: -1142 | M70: -1142 | N70: -1142 | O70: =SUM(C70:N70) -> -9136
B71: Vinyl Works | F71: 1350 | G71: 1350 | H71: 1350 | I71: 1350 | J71: 1350 | K71: 1350 | L71: 1350 | M71: 1350 | N71: 1350 | O71: =SUM(C71:N71) -> 12150
B72: Southern Atlantic - drop | E72: -110 | F72: -110 | G72: -110 | H72: -110 | I72: -110 | J72: -110 | K72: -110 | L72: -110 | M72: -110 | N72: -110 | O72: =SUM(C72:N72) -> -1100
B73: Alameda Structural | G73: 510 | H73: 510 | I73: 510 | J73: 510 | K73: 510 | L73: 510 | M73: 510 | N73: 510 | O73: =SUM(C73:N73) -> 4080
B74: The Pacific Center for Financial Services | G74: 1350 | H74: 1350 | I74: 1350 | J74: 1350 | K74: 1350 | L74: 1350 | M74: 1350 | N74: 1350 | O74: =SUM(C74:N74) -> 10800
B75: PHA - drop | H75: -2000 | I75: -2000 | J75: -2000 | K75: -2000 | L75: -2000 | M75: -2000 | N75: -2000 | O75: =SUM(C75:N75) -> -14000
B76: Banc Consulting Partners | I76: 1045 | J76: 1045 | K76: 1045 | L76: 1045 | M76: 1045 | N76: 1045 | O76: =SUM(C76:N76) -> 6270
B77: Virtus Financial Pertners | H77: 510 | I77: 510 | J77: 510 | K77: 510 | L77: 510 | M77: 510 | N77: 510 | O77: =SUM(G77:N77) -> 3570
B78: P&D Electric Inc | J78: 1245 | K78: 1245 | L78: 1245 | M78: 1245 | N78: 1245 | O78: =SUM(C78:N78) -> 6225
B79: Donnelly & Moore inc | K79: 605 | L79: 605 | M79: 605 | N79: 605 | O79: =SUM(C79:N79) -> 2420
B80: Pelage Pharma | L80: 595 | M80: 595 | N80: 595 | O80: =SUM(C80:N80) -> 1785
B81: Conejo - add | E81: 600 | F81: 600 | G81: 600 | H81: 600 | I81: 600 | J81: 600 | K81: 600 | L81: 600 | M81: 600 | N81: 600 | O81: =SUM(G81:N81) -> 4800
B82: SFPHF - add | L82: 510 | M82: 510 | N82: 510 | O82: =SUM(G82:N82) -> 1530
O83: =SUM(G83:N83) -> 0
O84: =SUM(G84:N84) -> 0
O85: =SUM(G85:N85) -> 0
O86: =SUM(H86:N86) -> 0
O87: =SUM(G87:N87) -> 0
O88: =SUM(H88:N88) -> 0
O89: =SUM(H89:N89) -> 0
O90: =SUM(H90:N90) -> 0
O91: =SUM(H91:N91) -> 0
O92: =SUM(I92:N92) -> 0
O93: =SUM(H93:N93) -> 0
O94: =SUM(H94:N94) -> 0
O95: =SUM(H95:N95) -> 0
O96: =SUM(H96:N96) -> 0
O97: =SUM(M97:N97) -> 0
O98: =SUM(M98:N98) -> 0
O99: =SUM(M99:N99) -> 0
O100: =N100 -> 0
B102: TOTAL NET | C102: =SUM(C59:C101) -> 164853 | D102: =SUM(D59:D101) -> 166003 | E102: =SUM(E59:E101) -> 137878 | F102: =SUM(F59:F101) -> 143983 | G102: =SUM(G59:G101) -> 143401 | H102: =SUM(H59:H101) -> 141911 | I102: =SUM(I59:I101) -> 142956 | J102: =SUM(J59:J101) -> 144201 | ... O102: =SUM(O59:O101) -> 1766525
B103: Increase month over month | C103: =C102-C59 -> -12500 | D103: =D102-C102 -> 1150 | E103: =E102-D102 -> -28125 | F103: =F102-E102 -> 6105 | G103: =G102-F102 -> -582 | H103: =H102-G102 -> -1490 | I103: =I102-H102 -> 1045 | J103: =J102-I102 -> 1245 | K103: =K102-J102 -> 605 | ... N103: =N102-M102 -> 0 | O103: =SUM(C103:N103) -> -31442
B106: Rolling NET Increase over 2023 (total) | C106: =C102-C59 -> -12500 | D106: =D102-D59 -> -11350 | E106: =E102-E59 -> -39475 | F106: =F102-F59 -> -33370 | G106: =G102-G59 -> -33952 | H106: =H102-H59 -> -35442 | I106: =I102-I59 -> -34397 | J106: =J102-J59 -> -33152 | ... O106: =O102-O59 -> -361711
B108: ACTUAL MS ONLY per CW | F108: 145413 | G108: 146766
B109: Likely different based on MS revenue invoiced via Std/Misc for first month or two | G109: =G108-C59 -> -30587
H122: 1 | I122: 2 | J122: 3 | K122: 4 | L122: 5 | M122: 6 | N122: 7 | O122: 8 | P122: 10
...

Sheet 2024
A1: Today: | B1: =TODAY() -> 46147 | G1: 2024
A2: Forecast | C2: Jan | D2: Feb | E2: Mar | F2: Apr | G2: May | H2: Jun | I2: Jul | J2: Aug | K2: Sept | L2: Oct | M2: Nov | N2: Dec | O2: YTD Total
A3: Recurring Sales Invoiced | B3: Agreement | C3: 348558 | D3: 347041 | E3: 343646 | F3: 360526 | G3: 360034 | H3: 357860 | I3: 356659 | J3: 355372 | K3: 359721 | L3: 368176 | M3: 368348 | N3: 373130 | O3: =SUM(C3:N3) -> 4299071 | Q3: NOTES:
B4: New Agreement in Std | O4: =SUM(C4:N4) -> 0 | Q4: Agreement invoices that are delayed until 8th of the month:
B5: ITMS | O5: =SUM(C5:N5) -> 0 | Q5: Amiri - emailed to client with date created, then date changed to first of next month (MS invoices)
B6: Licensing | O6: =SUM(F6:N6) -> 0 | Q6: BUNZL - path to the cloud invoiced on 8th or so of every month
B7: Comprehensive Services | O7: =SUM(C7:N7) -> 0 | Q7: License Agreement invoices (24k ish) completed on same day, first ish of the month. Once synnex auto updates.
B8: Other | O8: =SUM(C8:N8) -> 0
A10: New Sales Invoiced [INPUTS] | B10: Standard and Misc - Invoiced | C10: 142362 | D10: 229434 | E10: 86779 | F10: 77612 | G10: 126216 | H10: 56715 | I10: 95800 | J10: 81425 | K10: 133285 | L10: 151749 | M10: 54579 | N10: 65199 | O10: =SUM(C10:N10) -> 1301155
B11: Miscellaneous - Invoiced | O11: =SUM(C11:N11) -> 0
B12: Credit Memo - Invoiced | O12: =SUM(C12:N12) -> 0
Q13: revenue | R13: 387307
A14: Pending and Projected Sales | B14: Pending Project Milestones | N14: =3600+7200 -> 10800 | O14: =SUM(C14:N14) -> 10800 | P14: move to 1/31/25 | Q14: margin | R14: 175674 | S14: =R14/R13 -> 0.45357817
B15: Hubspot Pipeline at 40% | O15: =SUM(C15:N15) -> 0 | R15: =R14/12 -> 14639.5
B16: OPPS High Forecast (inputs)
B17: OPPS Low Forecast (inputs)
A19: Total | B19: Total Revenue | C19: =C3+C6+C10 -> 490920 | D19: =D3+D6+D10 -> 576475 | E19: =E3+E6+E10 -> 430425 | F19: =F3+F6+F10 -> 438138 | G19: =G3+G6+G10 -> 486250 | H19: =H3+H6+H10 -> 414575 | I19: =I3+I6+I10 -> 452459 | J19: =J3+J6+J10 -> 436797 | ... N19: =N3+N6+N10 -> 438329 | O19: =SUM(C19:N19) -> 5600226 | R19: AGREEMENT | S19: Breakdown
B20: High | C20: =C3+C5+C6+C10+C11+C16+C12 -> 490920 | D20: =D3+D5+D6+D10+D11+D16+D12 -> 576475 | E20: =E3+E5+E6+E10+E11+E16+E12+E14 -> 430425 | F20: =F19+F16 -> 438138 | G20: =G3+G5+G6+G10+G11+G16+G12+G14 -> 486250 | H20: =H3+H5+H6+H10+H11+H16+H12+H14 -> 414575 | I20: =I3+I5+I6+I10+I11+I16+I12+I14 -> 452459 | J20: =J3+J5+J6+J10+J11+J16+J12+J14 -> 436797 | K20: =K3+K5+K6+K7+K8+K10+K11+K12+K14+K16 -> 493006 | L20: =L3+L5+L6+L7+L8+L10+L11+L12+L14+L16 -> 519925 | M20: =M3+M5+M6+M7+M8+M10+M11+M12+M14+M16 -> 422927 | N20: =N3+N5+N6+N7+N8+N10+N11+N12+N14+N16 -> 449129 | R20: 368176 | S20: TOTAL
B21: Low | C21: =C3+C5+C6+C10+C11+C12+C17 -> 490920 | D21: =D3+D5+D6+D10+D11+D12+D17 -> 576475 | E21: =E3+E5+E6+E10+E11+E12+E17+E14 -> 430425 | F21: =F19+F17 -> 438138 | G21: =G3+G5+G6+G10+G11+G12+G17+G14 -> 486250 | H21: =H3+H5+H6+H10+H11+H12+H17+H14 -> 414575 | I21: =I3+I5+I6+I10+I11+I12+I17+I14 -> 452459 | J21: =J3+J5+J6+J10+J11+J12+J17+J14 -> 436797 | K21: =K3+K5+K6+K7+K8+K10+K11+K12+K14+K17 -> 493006 | L21: =L3+L5+L6+L7+L8+L10+L11+L12+L14+L17 -> 519925 | M21: =M3+M5+M6+M7+M8+M10+M11+M12+M14+M17 -> 422927 | N21: =N3+N5+N6+N7+N8+N10+N11+N12+N14+N17 -> 449129 | R21: 135079 | S21: Project
A22: Gap (/mo) | B22: Revenue to Goal | C22: =C19-C26 -> 40920 | D22: =D19-D26 -> 126475 | E22: C | F22: =F19-F26 -> -36862 | G22: =G19-G26 -> 11250 | H22: =H19-H26 -> -60425 | I22: =I19-I26 -> -22541 | J22: =J19-J26 -> -38203 | K22: =K19-K26 -> 18006 | O22: =SUM(C22:N22) -> 38620 | R22: 175685 | S22: Managed Services
R23: =R20-R21-R22 -> 57412 | S23: Licensing (Agreement)
A24: Rolling Actual/Forecast | B24: Actual | C24: =C19 -> 490920 | D24: =C24+D19 -> 1067395 | E24: =D24+E19 -> 1497820 | F24: =E24+F19 -> 1935958 | G24: =F24+G19 -> 2422208 | H24: =G24+H19 -> 2836783 | I24: =H24+I19 -> 3289242 | J24: =I24+J19 -> 3726039 | K24: =J24+K19 -> 4219045 | ... N24: =M24+N19 -> 5600226 | O24: =N24 -> 5600226
B25: Actual ROLLING | C25: =C19 -> 490920 | D25: =C25+D19 -> 1067395 | E25: =D25+E19 -> 1497820 | F25: =E25+F19 -> 1935958 | G25: =F25+G19 -> 2422208 | H25: =G25+H19 -> 2836783 | I25: =H25+I19 -> 3289242 | J25: =I25+J19 -> 3726039 | K25: =J25+K19 -> 4219045 | ... N25: =M25+N19 -> 5600226
A26: Monthly Goal | B26: Revenue GOAL | C26: 450000 | D26: 450000 | E26: 450000 | F26: 475000 | G26: 475000 | H26: 475000 | I26: 475000 | J26: 475000 | K26: 475000 | L26: 475000 | M26: 475000 | N26: 475000 | O26: =SUM(C26:N26) -> 5625000 | Q26: cogs | R26: rev
B27: Rolling GOAL | C27: =C26 -> 450000 | D27: =C27+D26 -> 900000 | E27: =D27+E26 -> 1350000 | F27: =E27+F26 -> 1825000 | G27: =F27+G26 -> 2300000 | H27: =G27+H26 -> 2775000 | I27: =H27+I26 -> 3250000 | J27: =I27+J26 -> 3725000 | K27: =J27+K26 -> 4200000 | ... N27: =M27+N26 -> 5625000 | O27: =N27 -> 5625000 | Q27: 58924 | R27: 95079 | S27: arc | T27: =R27-Q27 -> 36155 | U27: =T27/R27 -> 0.38026273
A28: Rolling Goal | C28: =C24-C27 -> 40920 | D28: =D24-D27 -> 167395 | E28: =E24-E27 -> 147820 | F28: =F24-F27 -> 110958 | G28: =G24-G27 -> 122208 | H28: =H24-H27 -> 61783 | I28: =I24-I27 -> 39242 | J28: =J24-J27 -> 1039 | ... N28: =N24-N27 -> -24774 | O28: =N28 -> -24774
A29: Rolling Goal | C29: Jan | D29: Feb | E29: Mar | F29: Apr | G29: May | H29: Jun | I29: Jul | J29: Aug | K29: Sept | L29: Oct | M29: Nov | N29: Dec | O29: 2019
A30: Rolling Goal | C30: =SUMIFS(#REF!,#REF!,1,#REF!,2019,#REF!,"open") -> #REF! | D30: =SUMIFS(#REF!,#REF!,2,#REF!,2019,#REF!,"open") -> #REF! | E30: =SUMIFS(#REF!,#REF!,3,#REF!,2019,#REF!,"open") -> #REF! | F30: =SUMIFS(#REF!,#REF!,4,#REF!,2019,#REF!,"open") -> #REF! | G30: =SUMIFS(#REF!,#REF!,5,#REF!,2019,#REF!,"open") -> #REF! | H30: =SUMIFS(#REF!,#REF!,6,#REF!,2019,#REF!,"open") -> #REF! | I30: =SUMIFS(#REF!,#REF!,7,#REF!,2019,#REF!,"open") -> #REF! | J30: =SUMIFS(#REF!,#REF!,8,#REF!,2019,#REF!,"open") -> #REF! | K30: =SUMIFS(#REF!,#REF!,9,#REF!,2019,#REF!,"open") -> #REF! | L30: =SUMIFS(#REF!,#REF!,10,#REF!,2019,#REF!,"open") -> #REF! | M30: =SUMIFS(#REF!,#REF!,11,#REF!,2019,#REF!,"open") -> #REF! | N30: =SUMIFS(#REF!,#REF!,12,#REF!,2019,#REF!,"open") -> #REF! | O30: =SUM(C30:N30) -> #REF!
A31: Rolling Goal | C31: =SUMIFS(#REF!,#REF!,1,#REF!,2019,#REF!,"*",#REF!,"open") -> #REF! | D31: =SUMIFS(#REF!,#REF!,2,#REF!,2019,#REF!,"*",#REF!,"open") -> #REF! | E31: =SUMIFS(#REF!,#REF!,3,#REF!,2019,#REF!,"*",#REF!,"open") -> #REF! | F31: =SUMIFS(#REF!,#REF!,4,#REF!,2019,#REF!,"*",#REF!,"open") -> #REF! | G31: =SUMIFS(#REF!,#REF!,5,#REF!,2019,#REF!,"*",#REF!,"open") -> #REF! | H31: =SUMIFS(#REF!,#REF!,6,#REF!,2019,#REF!,"*",#REF!,"open") -> #REF! | I31: =SUMIFS(#REF!,#REF!,7,#REF!,2019,#REF!,"*",#REF!,"open") -> #REF! | J31: =SUMIFS(#REF!,#REF!,8,#REF!,2019,#REF!,"*",#REF!,"open") -> #REF! | K31: =SUMIFS(#REF!,#REF!,9,#REF!,2019,#REF!,"*",#REF!,"open") -> #REF! | L31: =SUMIFS(#REF!,#REF!,10,#REF!,2019,#REF!,"*",#REF!,"open") -> #REF! | M31: =SUMIFS(#REF!,#REF!,11,#REF!,2019,#REF!,"*",#REF!,"open") -> #REF! | N31: =SUMIFS(#REF!,#REF!,12,#REF!,2019,#REF!,"*",#REF!,"open") -> #REF! | O31: =SUM(C31:N31) -> #REF!
B32: Rolling GOAL Difference | C32: =C19-C26 -> 40920 | D32: =D19-D26+C32 -> 167395 | E32: =E19-E26+D32 -> 147820 | F32: =F19-F26+E32 -> 110958 | G32: =G19-G26+F32 -> 122208 | Q32: 20000 | R32: 40000 | S32: bunzl | T32: =87-59 -> 28 | U32: =28/95 -> 0.29473684
A34: This green area does not roll into other areas. This is | B34: Project Revenue - Agreements | C34: =7000+30000+87402 -> 124402 | D34: =40000+87402 -> 127402 | E34: =40000+87402 -> 127402 | F34: =40000+87402 -> 127402 | G34: =40000+87402 -> 127402 | H34: =40000+87402 -> 127402 | I34: =40000+87402 -> 127402 | J34: =40000+87402 -> 127402 | K34: =40000+87402 -> 127402 | L34: 135079 | M34: 135079 | N34: 135079 | O34: =SUM(C34:N34) -> 1548855
A35: a subset of AGREEMENT revenue. | B35: Project COGS Agreements (input) | C35: 75924 | D35: 78924 | E35: 78925 | F35: 78926 | G35: 78927 | H35: 78928 | I35: 78929 | J35: 78930 | K35: 78931 | L35: 78924 | M35: 78924 | N35: 78924 | O35: =SUM(C35:N35) -> 944116 | Q35: =SUM(Q27:Q33) -> 78924 | R35: =SUM(R27:R33) -> 135079
A36: Breakdown reporting only | B36: Project Agreement Margin $ | C36: =C34-C35 -> 48478 | D36: =D34-D35 -> 48478 | E36: =E34-E35 -> 48477 | F36: =F34-F35 -> 48476 | G36: =G34-G35 -> 48475 | H36: =H34-H35 -> 48474 | I36: =I34-I35 -> 48473 | J36: =J34-J35 -> 48472 | ... N36: =N34-N35 -> 56155 | O36: =SUM(C36:N36) -> 604739
B37: Project Agreement Margin % | C37: =C36/C34 -> 0.38968827 | D37: =D36/D34 -> 0.38051208 | E37: =E36/E34 -> 0.38050423 | F37: =F36/F34 -> 0.38049638 | G37: =G36/G34 -> 0.38048853 | H37: =H36/H34 -> 0.38048068 | I37: =I36/I34 -> 0.38047283 | J37: =J36/J34 -> 0.38046498 | ... O37: =O36/O34 -> 0.39044262 | Q37: =R35-Q35 -> 56155 | R37: =Q37/R35 -> 0.41571969
B38: Agreement Revenue | C38: =C3 -> 348558 | D38: =D3 -> 347041 | E38: =E3 -> 343646 | F38: =F3 -> 360526 | G38: =G3 -> 360034 | H38: =H3 -> 357860 | I38: =I3 -> 356659 | J38: =J3 -> 355372 | ... N38: =N3 -> 373130 | O38: =SUM(C38:N38) -> 4299071
B39: Agreement COGS (input) | C39: 113922 | D39: 125890 | E39: 115839 | F39: 115682 | G39: 117134 | H39: 117998 | I39: 119399 | J39: 117184 | K39: 118167 | L39: 122089 | M39: 122089 | N39: 123350 | O39: =SUM(C39:N39) -> 1428743
B40: Agreement Margin $ | C40: =C38-C39 -> 234636 | D40: =D38-D39 -> 221151 | E40: =E38-E39 -> 227807 | F40: =F38-F39 -> 244844 | G40: =G38-G39 -> 242900 | H40: =H38-H39 -> 239862 | I40: =I38-I39 -> 237260 | J40: =J38-J39 -> 238188 | ... N40: =N38-N39 -> 249780 | O40: =SUM(C40:N40) -> 2870328
B41: Agreement Margin % | C41: =C40/C38 -> 0.673162 | D41: =D40/D38 -> 0.63724747 | E41: =E40/E38 -> 0.66291183 | F41: =F40/F38 -> 0.67912994 | G41: =G40/G38 -> 0.6746585 | H41: =H40/H38 -> 0.6702677 | I41: =I40/I38 -> 0.66522925 | J41: =J40/J38 -> 0.67024977 | ... O41: =O40/O38 -> 0.66766239
B42: Standard Revenue (w Misc & CMs) | C42: =C10 -> 142362 | D42: =D10 -> 229434 | E42: =E10 -> 86779 | F42: =F10 -> 77612 | G42: =G10 -> 126216 | H42: =H10 -> 56715 | I42: =I10 -> 95800 | J42: =J10 -> 81425 | ... N42: =N10 -> 65199 | O42: =SUM(C42:N42) -> 1301155
B43: Standard Misc COGS (input) | C43: 108489 | D43: 126181 | E43: 28767 | F43: 42209 | G43: 76947 | H43: 37489 | I43: 52584 | J43: 55020 | K43: 96780 | L43: 87705 | M43: 31928 | N43: 39707 | O43: =SUM(C43:N43) -> 783806
B44: Standard Margin $ | C44: =C42-C43 -> 33873 | D44: =D42-D43 -> 103253 | E44: =E42-E43 -> 58012 | F44: 34671 | G44: =G42-G43 -> 49269 | H44: =H42-H43 -> 19226 | I44: =I42-I43 -> 43216 | J44: =J42-J43 -> 26405 | K44: =K42-K43 -> 36505 | L44: =L42-L43 -> 64044 | M44: =M42-M43 -> 22651 | N44: =N42-N43 -> 25492 | O44: =SUM(C44:N44) -> 516617
B45: Standard Margin % | C45: =C44/C42 -> 0.23793569 | D45: =D44/D42 -> 0.45003356 | E45: =E44/E42 -> 0.66850275 | F45: =F44/F42 -> 0.44672216 | G45: =G44/G42 -> 0.39035463 | H45: =H44/H42 -> 0.33899321 | I45: =I44/I42 -> 0.45110647 | J45: =J44/J42 -> 0.32428615 | ... O45: =O44/O42 -> 0.39704493
B46: Miscellaneous COGS (input)
B47: TOTAL Revenue | C47: =C38+C42 -> 490920 | D47: =D38+D42 -> 576475 | E47: =E38+E42 -> 430425 | F47: =F38+F42 -> 438138 | G47: =G38+G42 -> 486250 | H47: =H38+H42 -> 414575 | I47: =I38+I42 -> 452459 | J47: =J38+J42 -> 436797 | ... N47: =N38+N42 -> 438329 | O47: =SUM(C47:N47) -> 5600226
B48: TOTAL COGS | C48: =C39+C43 -> 222411 | D48: =D39+D43 -> 252071 | E48: =E39+E43 -> 144606 | F48: =F39+F43 -> 157891 | G48: =G39+G43+G46 -> 194081 | H48: =H39+H43+H46 -> 155487 | I48: =I39+I43+I46 -> 171983 | J48: =J39+J43+J46 -> 172204 | K48: =K39+K43+K46 -> 214947 | L48: =L39+L43+L46 -> 209794 | M48: =M39+M43+M46 -> 154017 | N48: =N39+N43+N46 -> 163057 | O48: =SUM(C48:N48) -> 2212549 | Q48: 5
B49: TOTAL [Blended] Margin $ | C49: =C47-C48 -> 268509 | D49: =D47-D48 -> 324404 | E49: =E47-E48 -> 285819 | F49: =F47-F48 -> 280247 | G49: =G47-G48 -> 292169 | H49: =H47-H48 -> 259088 | I49: =I47-I48 -> 280476 | J49: =J47-J48 -> 264593 | ... N49: =N47-N48 -> 275272 | O49: =SUM(C49:N49) -> 3387677
B50: TOTAL [Blended] Margin % | C50: =C49/C47 -> 0.54695062 | D50: =D49/D47 -> 0.56273733 | E50: =E49/E47 -> 0.66403903 | F50: =F49/F47 -> 0.63963181 | G50: =G49/G47 -> 0.6008617 | H50: =H49/H47 -> 0.62494844 | I50: =I49/I47 -> 0.61989263 | J50: =J49/J47 -> 0.60575737 | ... O50: =O49/O47 -> 0.60491791
B51: TARGET Minimum MARGIN (input) | C51: 240000 | D51: 240000 | E51: 240000 | F51: 240000 | G51: 240000 | H51: 240000 | I51: 240000 | J51: 240000 | K51: 240000 | L51: 245000 | M51: 245000 | N51: 245000 | O51: =SUM(C51:N51) -> 2895000
B52: $ Over TARGET MARGIN | C52: =C49-C51 -> 28509 | D52: =D49-D51 -> 84404 | E52: =E49-E51 -> 45819 | F52: =F49-F51 -> 40247 | G52: =G49-G51 -> 52169 | H52: =H49-H51 -> 19088 | I52: =I49-I51 -> 40476 | J52: =J49-J51 -> 24593 | ... N52: =N49-N51 -> 30272 | O52: =SUM(C52:N52) -> 492677
B53: QUICKBOOKS GM
B55: Profitability Line for GM | C55: 240000 | D55: 240000 | E55: 240000 | F55: 240000 | G55: 240000 | H55: 240000 | I55: 240000 | J55: 240000 | K55: 240000 | L55: 240000 | M55: 240000 | N55: 240000
B56: Projected NET Profit | C56: =C49-C55 -> 28509 | D56: =D49-D55 -> 84404 | E56: =E49-E55 -> 45819 | F56: =F49-F55 -> 40247 | G56: =G49-G55 -> 52169 | H56: =H49-H55 -> 19088 | I56: =I49-I55 -> 40476 | J56: =J49-J55 -> 24593 | ... N56: =N49-N55 -> 35272 | O56: =SUM(C56:N56) -> 507677
B57: Projected NET Profit % | C57: =C56/C47 -> 0.058072598 | D57: =D56/D47 -> 0.14641398 | E57: =E56/E47 -> 0.1064506 | F57: =F56/F47 -> 0.091859186 | G57: =G56/G47 -> 0.10728843 | H57: =H56/H47 -> 0.046042333 | I57: =I56/I47 -> 0.089457829 | J57: =J56/J47 -> 0.056303042 | ... N57: =N56/N47 -> 0.080469237
B58: Profit GOAL at Target 18% | C58: =C19*0.18 -> 88365.6 | D58: =D19*0.18 -> 103765.5 | E58: =E19*0.18 -> 77476.5 | F58: =F19*0.18 -> 78864.84 | G58: =G19*0.18 -> 87525 | H58: =H19*0.18 -> 74623.5 | I58: =I19*0.18 -> 81442.62 | J58: =J19*0.18 -> 78623.46 | ... N58: =N19*0.18 -> 78899.22 | O58: =SUM(C58:N58) -> 1008040.7 | P58: 18% Goal
A60: RECURRING SERVICES - UP/DOWN
A62: Managed Services (only) | B62: 2024 Starting | C62: 177853 | D62: 177853 | E62: 177853 | F62: 177853 | G62: 177853 | H62: 177853 | I62: 177853 | J62: 177853 | K62: 177853 | L62: 177853 | M62: 177853 | N62: 177853 | O62: =SUM(C62:N62) -> 2134236
B63: Upstream Intl (full month) | C63: 1694 | D63: 3905 | E63: 3905 | F63: 3905 | G63: 3905 | H63: 3905 | I63: 3905 | J63: 3905 | K63: 3905 | L63: 3905 | M63: 3905 | N63: 3905 | O63: =SUM(C63:N63) -> 44649
B64: Recarbon | C64: -3905 | D64: -3905 | E64: -3905 | F64: -3905 | G64: -3905 | H64: -3905 | I64: -3905 | J64: -3905 | K64: -3905 | L64: -3905 | M64: -3905 | N64: -3905 | O64: =SUM(C64:N64) -> -46860
B65: Afranie | C65: -6945 | D65: -6945 | E65: -6945 | F65: -6945 | G65: -6945 | H65: -6945 | I65: -6945 | J65: -6945 | K65: -6945 | L65: -6945 | M65: -6945 | N65: -6945 | O65: =SUM(C65:N65) -> -83340
B66: Teddy Bear Cancer | D66: 1050 | E66: 1050 | F66: 1050 | G66: 1050 | H66: 1050 | I66: 1050 | J66: 1050 | K66: 1050 | L66: 1050 | M66: 1050 | N66: 1050 | O66: =SUM(C66:N66) -> 11550
B67: Marsh Industries | D67: -150 | E67: -150 | F67: -150 | G67: -150 | H67: -150 | I67: -150 | J67: -150 | K67: -150 | L67: -150 | M67: -150 | N67: -150 | O67: =SUM(C67:N67) -> -1650
B68: LocalRoof (user add) | D68: 100 | E68: 175 | F68: 175 | G68: 175 | H68: 175 | I68: 175 | J68: 175 | K68: 175 | L68: 175 | M68: 175 | N68: 175 | O68: =SUM(C68:N68) -> 1850
B69: San Fran Public Health (SFPH) | D69: 318.61 | E69: 660 | F69: 660 | G69: 660 | H69: 660 | I69: 660 | J69: 660 | K69: 660 | L69: 660 | M69: 660 | N69: 660 | O69: =SUM(C69:N69) -> 6918.61
B70: Organic Certifiers | E70: -2281 | F70: -3290 | G70: -3290 | H70: -3290 | I70: -3290 | J70: -3290 | K70: -3290 | L70: -3290 | M70: -3290 | N70: -3290 | O70: =SUM(C70:N70) -> -31891
B71: Amiri - Milan, ITALY | E71: 7400 | F71: 7400 | G71: 7400 | H71: 7400 | I71: 7400 | J71: 7400 | K71: 7400 | L71: 7400 | M71: 7400 | N71: 7400 | O71: =SUM(C71:N71) -> 74000
B72: Upstream Intl (full month) | E72: -2665 | F72: -3905 | G72: -3905 | H72: -3905 | I72: -3905 | J72: -3905 | K72: -3905 | L72: -3905 | M72: -3905 | N72: -3905 | O72: =SUM(C72:N72) -> -37810
B73: MCR - Bunzl | E73: 3387 | F73: 15000 | G73: 15000 | H73: 15000 | I73: 15000 | J73: 15000 | K73: 15000 | L73: 15000 | M73: 15000 | N73: 15000 | O73: =SUM(C73:N73) -> 138387
B74: Calpine - reduction | E74: -4600 | F74: -11400 | G74: -11400 | H74: -11400 | I74: -11400 | J74: -11400 | K74: -11400 | L74: -11400 | M74: -11400 | N74: -11400 | O74: =SUM(C74:N74) -> -107200
B75: Pacific Blue Engineering | F75: 1445 | G75: 1445 | H75: 1445 | I75: 1445 | J75: 1445 | K75: 1445 | L75: 1445 | M75: 1445 | N75: 1445 | O75: =SUM(C75:N75) -> 13005
B76: Applied Powdercoast - Afranie | F76: 370 | G76: 740 | H76: 740 | I76: 740 | J76: 740 | K76: 740 | L76: 740 | M76: 740 | N76: 740 | O76: =SUM(C76:N76) -> 6290
B77: Vintage Marina | H77: -600 | I77: -600 | J77: -600 | K77: -600 | L77: -600 | M77: -600 | N77: -600 | O77: =SUM(C77:N77) -> -4200
B78: Reality Church | I78: -2025 | J78: -2025 | K78: -2025 | L78: -2025 | M78: -2025 | N78: -2025 | O78: =SUM(C78:N78) -> -12150
B79: RevMax | I79: -2150 | J79: -2150 | K79: -2150 | L79: -2150 | M79: -2150 | N79: -2150 | O79: =SUM(C79:N79) -> -12900
B80: Ditec | H80: -400 | I80: -400 | J80: -400 | K80: -400 | L80: -400 | M80: -400 | N80: -400 | O80: =SUM(C80:N80) -> -2800
B81: Autism Systems - MDM reduction | H81: 1100 | I81: 1100 | J81: 1100 | K81: 1100 | L81: 1100 | M81: 1100 | N81: 1100 | O81: =SUM(C81:N81) -> 7700
B82: SFPH - increase | F82: 240 | G82: 240 | H82: 325 | I82: 325 | J82: 325 | K82: 325 | L82: 325 | M82: 325 | N82: 325 | O82: =SUM(G82:N82) -> 2515
B83: Southern Atlantic | G83: 243 | H83: 685 | I83: 685 | J83: 685 | K83: 685 | L83: 685 | M83: 685 | N83: 685 | O83: =SUM(G83:N83) -> 5038
B84: Cordova Bunzl (Increase) | H84: 2350 | I84: 2350 | J84: 2350 | K84: 2350 | L84: 2350 | M84: 2350 | N84: 2350 | O84: =SUM(G84:N84) -> 16450
B85: TSI | I85: -1225 | J85: -1225 | K85: -1225 | L85: -1225 | M85: -1225 | N85: -1225 | O85: =SUM(G85:N85) -> -7350
B86: LocalRoof (user add) | I86: 1050 | J86: 1050 | K86: 1050 | L86: 1050 | M86: 1050 | N86: 1050 | O86: =SUM(G86:N86) -> 6300
B87: Pacific Therapy - Managed Server Reduction | J87: -200 | K87: -200 | L87: -200 | M87: -200 | N87: -200 | O87: =SUM(G87:N87) -> -1000
B88: CWS (workstation change to Tier 1) | K88: -290 | L88: -290 | M88: -290 | N88: -290 | O88: =SUM(H88:N88) -> -1160
B89: Southern Atlantic (change to Tier 1) | K89: -185 | L89: -185 | M89: -185 | N89: -185 | O89: =SUM(G89:N89) -> -740
B90: Blue Ocean Barns (MS Increase) | K90: 955 | L90: 955 | M90: 955 | N90: 955 | O90: =SUM(H90:N90) -> 3820
B91: Secure Money | K91: 2410 | L91: 2410 | M91: 2410 | N91: 2410 | O91: =SUM(H91:N91) -> 9640
B92: AVF (MS Reduction) | O92: =SUM(H92:N92) -> 0
B93: Bunzl (Tinlgey) | L93: 3775 | M93: 7550 | N93: 7550 | O93: =SUM(H93:N93) -> 18875
B94: Bible Fellowship - Server Reduction | N94: -159 | O94: =SUM(I94:N94) -> -159
B95: Sea Ranch - Workstation reduction | N95: -450 | O95: =SUM(H95:N95) -> -450
O96: =SUM(H96:N96) -> 0
O97: =SUM(H97:N97) -> 0
O98: =SUM(H98:N98) -> 0
O99: =SUM(M99:N99) -> 0
O100: =SUM(M100:N100) -> 0
O101: =SUM(M101:N101) -> 0
O102: =N102 -> 0
B104: TOTAL NET | C104: =SUM(C62:C103) -> 168697 | D104: =SUM(D62:D103) -> 172226.61 | E104: =SUM(E62:E103) -> 173884 | F104: =SUM(F62:F103) -> 178503 | G104: =SUM(G62:G103) -> 179116 | H104: =SUM(H62:H103) -> 182093 | I104: =SUM(I62:I103) -> 177743 | J104: =SUM(J62:J103) -> 177543 | ... O104: =SUM(O62:O103) -> 2149563.6
B105: Increase month over month | C105: =C104-C62 -> -9156 | D105: =D104-C104 -> 3529.61 | E105: =E104-D104 -> 1657.39 | F105: =F104-E104 -> 4619 | G105: =G104-F104 -> 613 | H105: =H104-G104 -> 2977 | I105: =I104-H104 -> -4350 | J105: =J104-I104 -> -200 | K105: =K104-J104 -> 2890 | ... N105: =N104-M104 -> -609 | O105: =SUM(C105:N105) -> 9521
B108: Rolling NET Increase over 2023 (total) | C108: =C104-C62 -> -9156 | D108: =D104-D62 -> -5626.39 | E108: =E104-E62 -> -3969 | F108: =F104-F62 -> 650 | G108: =G104-G62 -> 1263 | H108: =H104-H62 -> 4240 | I108: =I104-I62 -> -110 | J108: =J104-J62 -> -310 | ... O108: =O104-O62 -> 15327.61
B110: ACTUAL MS ONLY per CW | C110: 171512 | D110: 168168 | E110: 165944 | F110: 175914 | G110: 174779 | H110: 174811 | K110: 175119 | L110: 175685 | M110: 181702 | N110: 181229
...

Sheet 2023
A1: Today | B1: =TODAY() -> 46147 | G1: 2023
A2: Forecast | C2: Jan | D2: Feb | E2: Mar | F2: Apr | G2: May | H2: Jun | I2: Jul | J2: Aug | K2: Sept | L2: Oct | M2: Nov | N2: Dec | O2: YTD Total
A3: Recurring Sales Invoiced | B3: Agreement | C3: 218082 | D3: 216803 | E3: 231863 | F3: =233751+875 -> 234626 | G3: 252748 | H3: 275590 | I3: 303985 | J3: 304741 | K3: 324458 | L3: 371084 | M3: 373068 | N3: 338390 | O3: =SUM(C3:N3) -> 3445438
B4: Staff Aug Agreement | O4: =SUM(C4:N4) -> 0
B5: ITMS | O5: =SUM(C5:N5) -> 0
B6: Licensing | O6: =SUM(F6:N6) -> 0
B7: Staffing | O7: =SUM(C7:N7) -> 0
B8: Other | O8: =SUM(C8:N8) -> 0
A10: New Sales Invoiced [INPUTS] | B10: Standard - Invoiced | C10: 62639 | D10: 70350 | E10: =87494-10000 -> 77494 | F10: 51947 | G10: 140324 | H10: 165632 | I10: 72989 | J10: 150257 | K10: 103384 | L10: 93118 | M10: 64906 | N10: 59113 | O10: =SUM(C10:N10) -> 1112153
B11: Miscellaneous - Invoiced | D11: 656 | E11: 421 | F11: 1727 | G11: 2594 | H11: 625 | I11: 16128 | O11: =SUM(C11:N11) -> 22151
B12: Credit Memo - Invoiced | C12: -1183 | D12: -10069 | E12: -692 | G12: -12593 | H12: -2420 | O12: =SUM(C12:N12) -> -26957
A14: Pending and Projected Sales | B14: Pending Project Milestones | N14: 13143 | O14: =SUM(C14:N14) -> 13143
B15: Other Revenue | O15: =SUM(C15:N15) -> 0
B16: OPPS High Forecast (inputs)
B17: OPPS Low Forecast (inputs)
A19: Total | B19: Total Revenue | C19: =C3+C5+C6+C7+C8+C10+C11+C12+C14+C15 -> 279538 | D19: =D3+D5+D6+D7+D8+D10+D11+D12+D14+D15 -> 277740 | E19: =E3+E5+E6+E7+E8+E10+E11+E12+E14+E15 -> 309086 | F19: =F3+F4+F5+F6+F7+F8+F10+F11+F12+F14+F15 -> 288300 | G19: =G46 -> 383073 | H19: =H46 -> 439427 | I19: =I46 -> 393102 | J19: =J46 -> 454998 | K19: =K46 -> 427842 | L19: =L46 -> 464202 | M19: =M46 -> 437974 | N19: =N46 -> 397503 | O19: =SUM(C19:N19) -> 4552785 | R19: AGREEMENT
B20: High | C20: =C3+C5+C6+C10+C11+C16+C12 -> 279538 | D20: =D3+D5+D6+D10+D11+D16+D12 -> 277740 | E20: =E3+E5+E6+E10+E11+E16+E12+E14 -> 309086 | F20: =F19+F16 -> 288300 | G20: =G3+G5+G6+G10+G11+G16+G12+G14 -> 383073 | H20: =H3+H5+H6+H10+H11+H16+H12+H14 -> 439427 | I20: =I3+I5+I6+I10+I11+I16+I12+I14 -> 393102 | J20: =J3+J5+J6+J10+J11+J16+J12+J14 -> 454998 | K20: =K3+K5+K6+K7+K8+K10+K11+K12+K14+K16 -> 427842 | L20: =L3+L5+L6+L7+L8+L10+L11+L12+L14+L16 -> 464202 | M20: =M3+M5+M6+M7+M8+M10+M11+M12+M14+M16 -> 437974 | N20: =N3+N5+N6+N7+N8+N10+N11+N12+N14+N16 -> 410646 | R20: 373082 | S20: total
B21: Low | C21: =C3+C5+C6+C10+C11+C12+C17 -> 279538 | D21: =D3+D5+D6+D10+D11+D12+D17 -> 277740 | E21: =E3+E5+E6+E10+E11+E12+E17+E14 -> 309086 | F21: =F19+F17 -> 288300 | G21: =G3+G5+G6+G10+G11+G12+G17+G14 -> 383073 | H21: =H3+H5+H6+H10+H11+H12+H17+H14 -> 439427 | I21: =I3+I5+I6+I10+I11+I12+I17+I14 -> 393102 | J21: =J3+J5+J6+J10+J11+J12+J17+J14 -> 454998 | K21: =K3+K5+K6+K7+K8+K10+K11+K12+K14+K17 -> 427842 | L21: =L3+L5+L6+L7+L8+L10+L11+L12+L14+L17 -> 464202 | M21: =M3+M5+M6+M7+M8+M10+M11+M12+M14+M17 -> 437974 | N21: =N3+N5+N6+N7+N8+N10+N11+N12+N14+N17 -> 410646 | R21: 147395
A22: Gap (/mo) | B22: Revenue to Goal | C22: =C19-C25 -> -20462 | D22: =D19-D25 -> -32260 | E22: =E19-E25 -> -5914 | F22: =F19-F25 -> -31700 | G22: =G19-G25 -> 63073 | H22: =H19-H25 -> 84427 | I22: =I19-I25 -> 28102 | J22: =J19-J25 -> 54998 | ... N22: =N19-N25 -> -52497 | O22: =SUM(C22:N22) -> 117785 | R22: 176078
R23: =R20-R21-R22 -> 49609 | S23: Licensing
A24: Rolling Actual/Forecast | B24: Actual | C24: =C19 -> 279538 | D24: =C24+D19 -> 557278 | E24: =D24+E19 -> 866364 | F24: =E24+F19 -> 1154664 | G24: =F24+G19 -> 1537737 | H24: =G24+H19 -> 1977164 | I24: =H24+I19 -> 2370266 | J24: =I24+J19 -> 2825264 | K24: =J24+K19 -> 3253106 | ... N24: =M24+N19 -> 4552785 | O24: =N24 -> 4552785
A25: Monthly Goal | B25: Revenue GOAL | C25: 300000 | D25: 310000 | E25: 315000 | F25: 320000 | G25: 320000 | H25: 355000 | I25: 365000 | J25: 400000 | K25: 400000 | L25: 450000 | M25: 450000 | N25: 450000 | O25: =SUM(C25:N25) -> 4435000 | Q25: cogs | R25: rev
B26: Rolling GOAL | C26: =C25 -> 300000 | D26: =C26+D25 -> 610000 | E26: =D26+E25 -> 925000 | F26: =E26+F25 -> 1245000 | G26: =F26+G25 -> 1565000 | H26: =G26+H25 -> 1920000 | I26: =H26+I25 -> 2285000 | J26: =I26+J25 -> 2685000 | K26: =J26+K25 -> 3085000 | ... N26: =M26+N25 -> 4435000 | O26: =N26 -> 4435000 | Q26: 76493 | R26: 125395 | S26: arc
A27: Rolling Goal | C27: =C24-C26 -> -20462 | D27: =D24-D26 -> -52722 | E27: =E24-E26 -> -58636 | F27: =F24-F26 -> -90336 | G27: =G24-G26 -> -27263 | H27: =H24-H26 -> 57164 | I27: =I24-I26 -> 85266 | J27: =J24-J26 -> 140264 | ... N27: =N24-N26 -> 117785 | O27: =N27 -> 117785
A28: Rolling Goal | C28: Jan | D28: Feb | E28: Mar | F28: Apr | G28: May | H28: Jun | I28: Jul | J28: Aug | K28: Sept | L28: Oct | M28: Nov | N28: Dec | O28: 2019
A29: Rolling Goal | C29: =SUMIFS(#REF!,#REF!,1,#REF!,2019,#REF!,"open") -> #REF! | D29: =SUMIFS(#REF!,#REF!,2,#REF!,2019,#REF!,"open") -> #REF! | E29: =SUMIFS(#REF!,#REF!,3,#REF!,2019,#REF!,"open") -> #REF! | F29: =SUMIFS(#REF!,#REF!,4,#REF!,2019,#REF!,"open") -> #REF! | G29: =SUMIFS(#REF!,#REF!,5,#REF!,2019,#REF!,"open") -> #REF! | H29: =SUMIFS(#REF!,#REF!,6,#REF!,2019,#REF!,"open") -> #REF! | I29: =SUMIFS(#REF!,#REF!,7,#REF!,2019,#REF!,"open") -> #REF! | J29: =SUMIFS(#REF!,#REF!,8,#REF!,2019,#REF!,"open") -> #REF! | K29: =SUMIFS(#REF!,#REF!,9,#REF!,2019,#REF!,"open") -> #REF! | L29: =SUMIFS(#REF!,#REF!,10,#REF!,2019,#REF!,"open") -> #REF! | M29: =SUMIFS(#REF!,#REF!,11,#REF!,2019,#REF!,"open") -> #REF! | N29: =SUMIFS(#REF!,#REF!,12,#REF!,2019,#REF!,"open") -> #REF! | O29: =SUM(C29:N29) -> #REF!
A30: Rolling Goal | C30: =SUMIFS(#REF!,#REF!,1,#REF!,2019,#REF!,"*",#REF!,"open") -> #REF! | D30: =SUMIFS(#REF!,#REF!,2,#REF!,2019,#REF!,"*",#REF!,"open") -> #REF! | E30: =SUMIFS(#REF!,#REF!,3,#REF!,2019,#REF!,"*",#REF!,"open") -> #REF! | F30: =SUMIFS(#REF!,#REF!,4,#REF!,2019,#REF!,"*",#REF!,"open") -> #REF! | G30: =SUMIFS(#REF!,#REF!,5,#REF!,2019,#REF!,"*",#REF!,"open") -> #REF! | H30: =SUMIFS(#REF!,#REF!,6,#REF!,2019,#REF!,"*",#REF!,"open") -> #REF! | I30: =SUMIFS(#REF!,#REF!,7,#REF!,2019,#REF!,"*",#REF!,"open") -> #REF! | J30: =SUMIFS(#REF!,#REF!,8,#REF!,2019,#REF!,"*",#REF!,"open") -> #REF! | K30: =SUMIFS(#REF!,#REF!,9,#REF!,2019,#REF!,"*",#REF!,"open") -> #REF! | L30: =SUMIFS(#REF!,#REF!,10,#REF!,2019,#REF!,"*",#REF!,"open") -> #REF! | M30: =SUMIFS(#REF!,#REF!,11,#REF!,2019,#REF!,"*",#REF!,"open") -> #REF! | N30: =SUMIFS(#REF!,#REF!,12,#REF!,2019,#REF!,"*",#REF!,"open") -> #REF! | O30: =SUM(C30:N30) -> #REF!
B31: Rolling GOAL Difference | C31: =C24-C25 -> -20462 | D31: =D24-D26 -> -52722 | E31: =E24-E26 -> -58636 | F31: =F24-F26 -> -90336 | G31: =G24-G26 -> -27263 | H31: =H24-H26 -> 57164 | I31: =I24-I26 -> 85266 | J31: =J24-J26 -> 140264 | Q31: 7500 | R31: 15000 | S31: bunzl
Q32: 2000 | R32: 7000 | S32: rwb
A33: This green area does not roll into other areas. This is | B33: Project Revenue - Agreements | C33: 68800 | D33: 68800 | E33: 68800 | F33: 68800 | G33: 73645 | H33: =73645+7000 -> 80645 | I33: =73645+7000 -> 80645 | J33: =73645+7000 -> 80645 | K33: =73645+7000+20000 -> 100645 | L33: =125395+7000+15000 -> 147395 | M33: 147395 | N33: =87401+7000+15000 -> 109401 | O33: =SUM(C33:N33) -> 1095616
A34: a subset of AGREEMENT revenue. | B34: Project COGS Agreements (input) | C34: 41300 | D34: 41300 | E34: 41300 | F34: 41300 | G34: 49040 | H34: =41813+2200 -> 44013 | I34: =41813+2200 -> 44013 | J34: =41813+2200 -> 44013 | K34: 54000 | L34: 85993 | M34: 85993 | O34: =SUM(C34:N34) -> 572265 | Q34: =SUM(Q26:Q32) -> 85993 | R34: =SUM(R26:R32) -> 147395
A35: Breakdown reporting only | B35: Project Agreement Margin $ | C35: =C33-C34 -> 27500 | D35: =D33-D34 -> 27500 | E35: =E33-E34 -> 27500 | F35: =F33-F34 -> 27500 | G35: =G33-G34 -> 24605 | H35: =H33-H34 -> 36632 | I35: =I33-I34 -> 36632 | J35: =J33-J34 -> 36632 | ... N35: =N33-N34 -> 109401 | O35: =SUM(C35:N35) -> 523351
B36: Project Agreement Margin % | C36: =C35/C33 -> 0.3997093 | D36: =D35/D33 -> 0.3997093 | E36: =E35/E33 -> 0.3997093 | F36: =F35/F33 -> 0.3997093 | G36: =G35/G33 -> 0.33410279 | H36: =H35/H33 -> 0.45423771 | I36: =I35/I33 -> 0.45423771 | J36: =J35/J33 -> 0.45423771 | ... O36: =O35/O33 -> 0.4776774
B37: Agreement Revenue | C37: 221093 | D37: 220309 | E37: 235382 | F37: =F3 -> 234626 | G37: =G3 -> 252748 | H37: =H3 -> 275590 | I37: =I3 -> 303985 | J37: =J3 -> 304741 | K37: =K3 -> 324458 | L37: =L3 -> 371084 | M37: =M3 -> 373068 | N37: =N3 -> 338390 | O37: =SUM(C37:N37) -> 3455474 | R37: =125-87 -> 38
B38: Agreement COGS (input) | C38: 72816 | D38: 72895 | E38: 72704 | F38: 71598 | G38: 86053 | H38: 81568 | I38: 82196 | J38: 77141 | K38: 86887 | L38: 120216 | M38: 122384 | N38: 106649 | O38: =SUM(C38:N38) -> 1053107 | R38: =373-38 -> 335
B39: Agreement Margin $ | C39: =C37-C38 -> 148277 | D39: =D37-D38 -> 147414 | E39: =E37-E38 -> 162678 | F39: =F37-F38 -> 163028 | G39: =G37-G38 -> 166695 | H39: =H37-H38 -> 194022 | I39: =I37-I38 -> 221789 | J39: =J37-J38 -> 227600 | ... N39: =N37-N38 -> 231741 | O39: =SUM(C39:N39) -> 2402367
B40: Agreement Margin % | C40: =C39/C37 -> 0.67065443 | D40: =D39/D37 -> 0.66912382 | E40: =E39/E37 -> 0.69112337 | F40: =F39/F37 -> 0.694842 | G40: =G39/G37 -> 0.65953044 | H40: =H39/H37 -> 0.70402409 | I40: =I39/I37 -> 0.72960508 | J40: =J39/J37 -> 0.74686373 | ... O40: =O39/O37 -> 0.69523515
B41: Standard Revenue (w Misc & CMs) | C41: 57730 | D41: 59574 | E41: =97840-10000 -> 87840 | F41: =F10+F11+F12 -> 53674 | G41: =G10+G11+G12 -> 130325 | H41: =H10+H11+H12 -> 163837 | I41: =I10+I11+I12 -> 89117 | J41: =J10+J11+J12 -> 150257 | K41: =K10+K11+K12 -> 103384 | L41: =L10+L11+L12 -> 93118 | M41: =M10+M11+M12 -> 64906 | N41: =N10+N11+N12 -> 59113 | O41: =SUM(C41:N41) -> 1112875
B42: Standard Misc COGS (input) | C42: 47875 | D42: 40516 | E42: 68203 | F42: 24058 | G42: 82000 | H42: 100066 | I42: 47879 | J42: 107591 | K42: 72313 | L42: 50352 | M42: 33945 | N42: 41728 | O42: =SUM(C42:N42) -> 716526
B43: Standard Margin $ | C43: =C41-C42 -> 9855 | D43: =D41-D42 -> 19058 | E43: =E41-E42 -> 19637 | F43: =F41-F42 -> 29616 | G43: =G41-G42 -> 48325 | H43: =H41-H42 -> 63771 | I43: =I41-I42 -> 41238 | J43: =J41-J42 -> 42666 | ... N43: =N41-N42 -> 17385 | O43: =SUM(C43:N43) -> 396349
B44: Standard Margin % | C44: =C43/C41 -> 0.17070847 | D44: =D43/D41 -> 0.31990466 | E44: =E43/E41 -> 0.22355419 | F44: =F43/F41 -> 0.55177553 | G44: =G43/G41 -> 0.37080376 | H44: =H43/H41 -> 0.38923442 | I44: =I43/I41 -> 0.46273999 | J44: =J43/J41 -> 0.28395349 | ... O44: =O43/O41 -> 0.35614871
B45: Miscellaneous COGS (input) | G45: 2187 | H45: 0 | I45: 9237
B46: TOTAL Revenue | C46: =C37+C41 -> 278823 | D46: =D37+D41 -> 279883 | E46: =E37+E41 -> 323222 | F46: =F37+F41 -> 288300 | G46: =G37+G41 -> 383073 | H46: =H37+H41 -> 439427 | I46: =I37+I41 -> 393102 | J46: =J37+J41 -> 454998 | ... N46: =N37+N41 -> 397503 | O46: =SUM(C46:N46) -> 4568349
B47: TOTAL COGS | C47: =C38+C42 -> 120691 | D47: =D38+D42 -> 113411 | E47: =E38+E42 -> 140907 | F47: =F38+F42 -> 95656 | G47: =G38+G42+G45 -> 170240 | H47: =H38+H42+H45 -> 181634 | I47: =I38+I42+I45 -> 139312 | J47: =J38+J42+J45 -> 184732 | K47: =K38+K42+K45 -> 159200 | L47: =L38+L42+L45 -> 170568 | M47: =M38+M42+M45 -> 156329 | N47: =N38+N42+N45 -> 148377 | O47: =SUM(C47:N47) -> 1781057
B48: TOTAL [Blended] Margin $ | C48: =C46-C47 -> 158132 | D48: =D46-D47 -> 166472 | E48: =E46-E47 -> 182315 | F48: =F46-F47 -> 192644 | G48: =G46-G47 -> 212833 | H48: =H46-H47 -> 257793 | I48: =I46-I47 -> 253790 | J48: =J46-J47 -> 270266 | ... N48: =N46-N47 -> 249126 | O48: =SUM(C48:N48) -> 2787292
B49: TOTAL [Blended] Margin % | C49: =C48/C46 -> 0.56714116 | D49: =D48/D46 -> 0.59479139 | E49: =E48/E46 -> 0.56405505 | F49: =F48/F46 -> 0.66820673 | G49: =G48/G46 -> 0.55559384 | H49: =H48/H46 -> 0.58665717 | I49: =I48/I46 -> 0.64560852 | J49: =J48/J46 -> 0.59399382 | ... O49: =O48/O46 -> 0.61013114
B50: TARGET Minimum MARGIN (input) | C50: 190000 | D50: 190000 | E50: 195000 | F50: 195000 | G50: 200000 | H50: 215000 | I50: 225000 | J50: 235000 | K50: 235000 | L50: 235000 | M50: 235000 | N50: 235000 | O50: =SUM(C50:N50) -> 2585000
B51: $ Over TARGET MARGIN | C51: =C48-C50 -> -31868 | D51: =D48-D50 -> -23528 | E51: =E48-E50 -> -12685 | F51: =F48-F50 -> -2356 | G51: =G48-G50 -> 12833 | H51: =H48-H50 -> 42793 | I51: =I48-I50 -> 28790 | J51: =J48-J50 -> 35266 | ... N51: =N48-N50 -> 14126 | O51: =SUM(C51:N51) -> 202292
B52: QUICKBOOKS GM
B54: Profitability Line for GM | C54: 200000 | D54: 200000 | E54: 200000 | F54: 215000 | G54: 225000 | H54: 245000 | I54: 235000 | J54: 235000 | K54: 235000 | L54: 235000 | M54: 235000 | N54: 235000
B55: Projected NET Profit | C55: =C48-C54 -> -41868 | D55: =D48-D54 -> -33528 | E55: =E48-E54 -> -17685 | F55: =F48-F54 -> -22356 | G55: =G48-G54 -> -12167 | H55: =H48-H54 -> 12793 | I55: =I48-I54 -> 18790 | J55: =J48-J54 -> 35266 | ... N55: =N48-N54 -> 14126 | O55: =SUM(C55:N55) -> 92292
B56: Projected NET Profit % | C56: =C55/C46 -> -0.15015978 | D56: =D55/D46 -> -0.11979291 | E56: =E55/E46 -> -0.054714716 | F56: =F55/F46 -> -0.077544225 | G56: =G55/G46 -> -0.03176157 | H56: =H55/H46 -> 0.029112913 | I56: =I55/I46 -> 0.047799299 | J56: =J55/J46 -> 0.077508033 | ... N56: =N55/N46 -> 0.035536839
B57: Profit GOAL 18% | C57: =C19*0.18 -> 50316.84 | D57: =D19*0.18 -> 49993.2 | E57: =E19*0.18 -> 55635.48 | F57: =F19*0.18 -> 51894 | G57: =G19*0.18 -> 68953.14 | H57: =H19*0.18 -> 79096.86 | I57: =I19*0.18 -> 70758.36 | J57: =J19*0.18 -> 81899.64 | ... N57: =N19*0.18 -> 71550.54 | O57: =SUM(C57:N57) -> 819501.3 | P57: 18% Goal
B58: Rolling | C58: =C57 -> 50316.84 | D58: =C58+D57 -> 100310.04 | E58: =D58+E57 -> 155945.52 | F58: =E58+F57 -> 207839.52 | G58: =F58+G57 -> 276792.66 | H58: =G58+H57 -> 355889.52 | I58: =H58+I57 -> 426647.88 | J58: =I58+J57 -> 508547.52 | K58: =J58+K57 -> 585559.08 | ... N58: =M58+N57 -> 819501.3 | O58: =N58 -> 819501.3
A60: RECURRING SERVICES - UP/DOWN
A62: Managed Services (only) | B62: 2023 Starting | C62: 102371 | D62: 102371 | E62: 102371 | F62: 102371 | G62: 102371 | H62: 102371 | I62: 102371 | J62: 102371 | K62: 102371 | L62: 102371 | M62: 102371 | N62: 102371 | O62: =SUM(C62:N62) -> 1228452
B63: Autism Systems - Saginaw addition | C63: 300 | D63: 300 | E63: 300 | F63: 300 | G63: 300 | H63: 300 | I63: 300 | J63: 300 | K63: 300 | L63: 300 | M63: 300 | N63: 300 | O63: =SUM(C63:N63) -> 3600
B64: PHA | C64: 500 | D64: 500 | E64: 500 | F64: 500 | G64: 500 | H64: 500 | I64: 500 | J64: 500 | K64: 500 | L64: 500 | M64: 500 | N64: 500 | O64: =SUM(C64:N64) -> 6000
B65: Recarbon | C65: 450 | D65: 450 | E65: 450 | F65: 450 | G65: 450 | H65: 450 | I65: 450 | J65: 450 | K65: 450 | L65: 450 | M65: 450 | N65: 450 | O65: =SUM(C65:N65) -> 5400
B66: SV Labs - departure -9k | D66: -9000 | E66: -9000 | F66: -9000 | G66: -9000 | H66: -9000 | I66: -9000 | J66: -9000 | K66: -9000 | L66: -9000 | M66: -9000 | N66: -9000 | O66: =SUM(C66:N66) -> -99000
B67: NOBU (Redacted) - departure - 4k | D67: -4000 | E67: -4000 | F67: -4000 | G67: -4000 | H67: -4000 | I67: -4000 | J67: -4000 | K67: -4000 | L67: -4000 | M67: -4000 | N67: -4000 | O67: =SUM(C67:N67) -> -44000
A68: Assessment Started and near completion | B68: iTrac | D68: -1060 | E68: -1060 | F68: -1060 | G68: -1060 | H68: -1060 | I68: -1060 | J68: -1060 | K68: -1060 | L68: -1060 | M68: -1060 | N68: -1060 | O68: =SUM(C68:N68) -> -11660
A69: Decision maker is engaged | B69: Clear Construction | D69: -1800 | E69: -1800 | F69: -1800 | G69: -1800 | H69: -1800 | I69: -1800 | J69: -1800 | K69: -1800 | L69: -1800 | M69: -1800 | N69: -1800 | O69: =SUM(C69:N69) -> -19800
A70: Verbaly expressed wanting to get started | B70: CWS Investments | D70: 750 | E70: 750 | F70: 750 | G70: 750 | H70: 750 | I70: 750 | J70: 750 | K70: 750 | L70: 750 | M70: 750 | N70: 750 | O70: =SUM(C70:N70) -> 8250
A71: Good feeling | B71: Cool-Pak Increase | D71: 7767 | E71: 7767 | F71: 7767 | G71: 7767 | H71: 7767 | I71: 7767 | J71: 7767 | K71: 7767 | L71: 7767 | M71: 7767 | N71: 7767 | O71: =SUM(C71:N71) -> 85437
A72: Agreement and pricing reviewed | B72: Local Roofs | D72: 750 | E72: 750 | F72: 750 | G72: 750 | H72: 750 | I72: 750 | J72: 750 | K72: 750 | L72: 750 | M72: 750 | N72: 750 | O72: =SUM(C72:N72) -> 8250
B73: Autism Systems - Macombe/Warren addition | D73: 300 | E73: 300 | F73: 300 | G73: 300 | H73: 300 | I73: 300 | J73: 300 | K73: 300 | L73: 300 | M73: 300 | N73: 300 | O73: =SUM(C73:N73) -> 3300
B74: Amiri | E74: 17700 | F74: 17700 | G74: 17700 | H74: 17700 | I74: 17700 | J74: 17700 | K74: 17700 | L74: 17700 | M74: 17700 | N74: 17700 | O74: =SUM(C74:N74) -> 177000
B75: Local Roofs Increase | E75: 200 | F75: 200 | G75: 200 | H75: 200 | I75: 200 | J75: 200 | K75: 200 | L75: 200 | M75: 200 | N75: 200 | O75: =SUM(C75:N75) -> 2000
B76: Recarbon Increase | E76: 300 | F76: 300 | G76: 300 | H76: 300 | I76: 300 | J76: 300 | K76: 300 | L76: 300 | M76: 300 | N76: 300 | O76: =SUM(C76:N76) -> 3000
B77: Calpine | E77: 2941.92 | F77: 7600 | G77: 7600 | H77: 7600 | I77: 7600 | J77: 7600 | K77: 7600 | L77: 7600 | M77: 7600 | N77: 7600 | O77: =SUM(C77:N77) -> 71341.92
B78: Manduka | F78: -6000 | G78: -6000 | H78: -6000 | I78: -6000 | J78: -6000 | K78: -6000 | L78: -6000 | M78: -6000 | N78: -6000 | O78: =SUM(C78:N78) -> -54000
B79: Infinity Q | F79: -600 | G79: -600 | H79: -600 | I79: -600 | J79: -600 | K79: -600 | L79: -600 | M79: -600 | N79: -600 | O79: =SUM(C79:N79) -> -5400
B80: Shoreline Group | F80: -3000 | G80: -3000 | H80: -3000 | I80: -3000 | J80: -3000 | K80: -3000 | L80: -3000 | M80: -3000 | N80: -3000 | O80: =SUM(C80:N80) -> -27000
B81: Recarbon | F81: -150 | G81: -150 | H81: -150 | I81: -150 | J81: -150 | K81: -150 | L81: -150 | M81: -150 | N81: -150 | O81: =SUM(C81:N81) -> -1350
B82: Organic Certifiers | G82: -218.62 | H82: -218.62 | I82: -218.62 | J82: -218.62 | K82: -218.62 | L82: -218.62 | M82: -218.62 | N82: -218.62 | O82: =SUM(C82:N82) -> -1748.96
B83: Afranie | D83: 5950 | E83: 5950 | F83: 5950 | O83: =SUM(C83:N83) -> 17850
B84: Aero Technical Metal Finishing (Afranie) | G84: 1750 | H84: 1750 | I84: 1750 | J84: 1750 | K84: 1750 | L84: 1750 | M84: 1750 | N84: 1750 | O84: =SUM(G84:N84) -> 14000
B85: Alard Engineering (Afranie) | G85: 2900 | H85: 2900 | I85: 2900 | J85: 2900 | K85: 2900 | L85: 2900 | M85: 2900 | N85: 2900 | O85: =SUM(G85:N85) -> 23200
B86: Applied Powder Coat (Afranie) | G86: 1225 | H86: 1225 | I86: 1225 | J86: 1225 | K86: 1225 | L86: 1225 | M86: 1225 | N86: 1225 | O86: =SUM(G86:N86) -> 9800
B87: Max Industries (Afranie) | G87: 875 | H87: 875 | I87: 875 | J87: 875 | K87: 875 | L87: 875 | M87: 875 | N87: 875 | O87: =SUM(G87:N87) -> 7000
B88: Sea Ranch Lodge | G88: 2475 | H88: 2475 | I88: 2475 | J88: 2475 | K88: 2475 | L88: 2475 | M88: 2475 | N88: 2475 | O88: =SUM(G88:N88) -> 19800
B89: Local Roofs - Increase | G89: 80 | H89: 80 | I89: 80 | J89: 80 | K89: 80 | L89: 80 | M89: 80 | N89: 80 | O89: =SUM(G89:N89) -> 640
B90: Bible Fellowship - increase | G90: 200 | H90: 200 | I90: 200 | J90: 200 | K90: 200 | L90: 200 | M90: 200 | N90: 200 | O90: =SUM(G90:N90) -> 1600
B91: Calpine - Increase | G91: 3950 | H91: 3950 | I91: 3950 | J91: 3950 | K91: 3950 | L91: 3950 | M91: 3950 | N91: 3950 | O91: =SUM(H91:N91) -> 27650
B92: Bunzl Companies added Phase 1 a | H92: 34925 | I92: 34925 | J92: 34925 | K92: 34925 | L92: 34925 | M92: 34925 | N92: 34925 | O92: =SUM(G92:N92) -> 244475
B93: Pacific Therapy - reduction to tier 1 | H93: -1050 | I93: -1050 | J93: -1050 | K93: -1050 | L93: -1050 | M93: -1050 | N93: -1050 | O93: =SUM(H93:N93) -> -7350
B94: Local Roofs - Increase | H94: 40 | I94: 40 | J94: 40 | K94: 40 | L94: 40 | M94: 40 | N94: 40 | O94: =SUM(H94:N94) -> 280
B95: Race Winning Brands - after hours | H95: 7000 | O95: =SUM(H95:N95) -> 7000 | P95: remove from MS and place in project agreement with
B96: Bunzl Companies added Phase 1 b | I96: 11575 | J96: 11575 | K96: 11575 | L96: 11575 | M96: 11575 | N96: 11575 | O96: =SUM(H96:N96) -> 69450 | P96: BUNZL, ARC, RWB
B97: Advanced Chiropractic | I97: =-650 -> -650 | J97: =-650 -> -650 | K97: =-650 -> -650 | L97: =-650 -> -650 | M97: =-650 -> -650 | N97: =-650 -> -650 | O97: =SUM(I97:N97) -> -3900
B98: Millworks | I98: 3527 | J98: 4050 | K98: 4050 | L98: 4050 | M98: 4050 | N98: 4050 | O98: =SUM(H98:N98) -> 23777
B99: Blue Ocean Barns | I99: 2125 | J99: 2550 | K99: 2550 | L99: 2550 | M99: 2550 | N99: 2550 | O99: =SUM(H99:N99) -> 14875
B100: Sea Ranch Lodge | L100: 500 | M100: 500 | N100: 500 | O100: =SUM(H100:N100) -> 1500
B101: Millworks - reduction to Tier 0 | L101: -1720 | M101: -1720 | N101: -1720 | O101: =SUM(H101:N101) -> -5160
B102: Local Roofs - Increase | M102: 40 | N102: 40 | O102: =SUM(M102:N102) -> 80
B103: People Powered - offboarding | M103: -350 | N103: -350 | O103: =SUM(M103:N103) -> -700
B104: CVG - removed 1 firewall | M104: -75 | N104: -75 | O104: =SUM(M104:N104) -> -150
B105: Upstream Intl | N105: 1461 | O105: =N105 -> 1461 | P105: will be $2665 starting 1/1/24
B107: TOTAL NET | C107: =SUM(C62:C106) -> 103621 | D107: =SUM(D62:D106) -> 103278 | E107: =SUM(E62:E106) -> 124419.92 | F107: =SUM(F62:F106) -> 119328 | G107: =SUM(G62:G106) -> 126614.38 | H107: =SUM(H62:H106) -> 167529.38 | I107: =SUM(I62:I106) -> 177106.38 | J107: =SUM(J62:J106) -> 178054.38 | ... O107: =SUM(O62:O106) -> 1805250
...

Sheet Categories
C1: Closed | D1: Forecast
A2: Service Name | B2: Type | D2: Jan | E2: Feb | F2: Mar | G2: Apr | H2: May | I2: Jun | J2: Jul | K2: Aug | L2: Sept | M2: Oct | N2: Nov | O2: Dec
A3: OLD BUSINESS
A4: ITMS Reoccurring (Help Desk, ITM) | B4: Monthly
A5: Hardware/Software Reoccurring (Amazon, SSaS) | B5: Monthly
A6: Service Management aaS (PM, SM) | B6: Monthly
A7: Pro Services (Staffed Reoccurring) | B7: Monthly
A8: Pro Services (Staffed Projects/Transactional) | B8: Transactional
A9: Pro Services (Outsourced Staffing) | B9: Transactional
A10: Pro Services (3rd Party) | B10: Transactional
A11: Hardware/Software Transactional | B11: Transactional
A12: HeroTech ITMS
A13: HeroTech Licenses
A14: HeroTech PM | B14: Monthly
A15: Other Services Income (RR, CareSight) | B15: Monthly
A17: NEW BUSINESS
A18: PC Refresh (POTS installed base) | C18: =SUMIFS(#REF!,#REF!,"POTS - PC Refresh 2019",#REF!,"won",#REF!,"<>Hero Tech") -> #REF! | D18: =SUMIFS(#REF!,#REF!,"POTS - PC Refresh 2019",#REF!,"open",#REF!,"1",#REF!,"<>Hero Tech") -> #REF! | E18: =SUMIFS(#REF!,#REF!,"POTS - PC Refresh 2019",#REF!,"open",#REF!,"2",#REF!,"<>Hero Tech") -> #REF! | F18: =SUMIFS(#REF!,#REF!,"POTS - PC Refresh 2019",#REF!,"open",#REF!,"3",#REF!,"<>Hero Tech") -> #REF! | G18: =SUMIFS(#REF!,#REF!,"POTS - PC Refresh 2019",#REF!,"open",#REF!,"4",#REF!,"<>Hero Tech") -> #REF! | H18: =SUMIFS(#REF!,#REF!,"POTS - PC Refresh 2019",#REF!,"open",#REF!,"5",#REF!,"<>Hero Tech") -> #REF! | I18: =SUMIFS(#REF!,#REF!,"POTS - PC Refresh 2019",#REF!,"open",#REF!,"6",#REF!,"<>Hero Tech") -> #REF! | J18: =SUMIFS(#REF!,#REF!,"POTS - PC Refresh 2019",#REF!,"open",#REF!,"7",#REF!,"<>Hero Tech") -> #REF! | K18: =SUMIFS(#REF!,#REF!,"POTS - PC Refresh 2019",#REF!,"open",#REF!,"8",#REF!,"<>Hero Tech") -> #REF! | L18: =SUMIFS(#REF!,#REF!,"POTS - PC Refresh 2019",#REF!,"open",#REF!,"9",#REF!,"<>Hero Tech") -> #REF! | M18: =SUMIFS(#REF!,#REF!,"POTS - PC Refresh 2019",#REF!,"open",#REF!,"10",#REF!,"<>Hero Tech") -> #REF! | N18: =SUMIFS(#REF!,#REF!,"POTS - PC Refresh 2019",#REF!,"open",#REF!,"11",#REF!,"<>Hero Tech") -> #REF! | O18: =SUMIFS(#REF!,#REF!,"POTS - PC Refresh 2019",#REF!,"open",#REF!,"12",#REF!,"<>Hero Tech") -> #REF!
A19: PC Refresh (HT installed base) | C19: =SUMIFS(#REF!,#REF!,"POTS - PC Refresh 2019",#REF!,"won",#REF!,"Hero Tech") -> #REF! | D19: =SUMIFS(#REF!,#REF!,"POTS - PC Refresh 2019",#REF!,"open",#REF!,"1",#REF!,"Hero Tech") -> #REF! | E19: =SUMIFS(#REF!,#REF!,"POTS - PC Refresh 2019",#REF!,"open",#REF!,"2",#REF!,"Hero Tech") -> #REF! | F19: =SUMIFS(#REF!,#REF!,"POTS - PC Refresh 2019",#REF!,"open",#REF!,"3",#REF!,"Hero Tech") -> #REF! | G19: =SUMIFS(#REF!,#REF!,"POTS - PC Refresh 2019",#REF!,"open",#REF!,"4",#REF!,"Hero Tech") -> #REF! | H19: =SUMIFS(#REF!,#REF!,"POTS - PC Refresh 2019",#REF!,"open",#REF!,"5",#REF!,"Hero Tech") -> #REF! | I19: =SUMIFS(#REF!,#REF!,"POTS - PC Refresh 2019",#REF!,"open",#REF!,"6",#REF!,"Hero Tech") -> #REF! | J19: =SUMIFS(#REF!,#REF!,"POTS - PC Refresh 2019",#REF!,"open",#REF!,"7",#REF!,"Hero Tech") -> #REF! | K19: =SUMIFS(#REF!,#REF!,"POTS - PC Refresh 2019",#REF!,"open",#REF!,"8",#REF!,"Hero Tech") -> #REF! | L19: =SUMIFS(#REF!,#REF!,"POTS - PC Refresh 2019",#REF!,"open",#REF!,"9",#REF!,"Hero Tech") -> #REF! | M19: =SUMIFS(#REF!,#REF!,"POTS - PC Refresh 2019",#REF!,"open",#REF!,"10",#REF!,"Hero Tech") -> #REF! | N19: =SUMIFS(#REF!,#REF!,"POTS - PC Refresh 2019",#REF!,"open",#REF!,"11",#REF!,"Hero Tech") -> #REF! | O19: =SUMIFS(#REF!,#REF!,"POTS - PC Refresh 2019",#REF!,"open",#REF!,"12",#REF!,"Hero Tech") -> #REF!
A20: POTS VoIP
A21: New ITMS Clients
A22: Other Campaigns (SQL, SBS, MS licenses)
D27: =D29/C29 -> 1.3639528 | E27: =E29/D29 -> 1.1955803 | F27: =F29/E29 -> 1.3087744 | G27: =G29/F29 -> 1.255967 | H27: =H29/G29 -> 1.1487822 | I27: =I29/H29 -> 0.84595948 | J27: =J29/I29 -> 1.1778695 | K27: =K29/J29 -> 1.1331328
C28: 2010 | D28: 2011 | E28: 2012 | F28: 2013 | G28: 2014 | H28: 2015 | I28: 2016 | J28: 2017 | K28: 2018
B29: POB | C29: 530937 | D29: 724173 | E29: 865807 | F29: 1133146 | G29: 1423194 | H29: 1634940 | I29: 1383093 | J29: 1629103 | K29: 1845990
B30: POTS | K30: 1696000
B31: Other | K31: =K29-K30 -> 149990

Sheet 5.1.18
G1: Yes | H1: Maybe | I1: No | J1: Notes
F2: May | G2: 45546.57 | H2: 45787.1 | I2: 70543.97 | J2: 91333.67
A4: Row Labels | B4: Opportunity Summary | C4: Years | D4: Stage | E4: Count of Company | F4: Sum of Revenue
A5: A Change in Trajectory (ACT) | B5: POTS PC Refresh | C5: 2019 | E5: 1 | F5: 22000
C6: Aug | E6: 1 | F6: 22000
C7: 31-Aug | D7: 5 - Solution Development | E7: 1 | F7: 22000 | J7: Update Amount, and update close date - past may
B8: POTS sonicwall renewal | C8: 2019 | E8: 2 | F8: 2000
C9: Feb | E9: 1 | F9: 400 | J9: Update Amount, and update close date - past may
C10: 20-Feb | D10: 13 - Needs Invoice | E10: 1 | F10: 400 | J10: Ask Amy if we can close this. Or move to 2017 close date
C11: Mar | E11: 1 | F11: 1600
C12: 13-Mar | D12: 13 - Needs Invoice | E12: 1 | F12: 1600 | G12: =GETPIVOTDATA("Sum of Revenue",$A$4,"Close Date",152,"Company","A Change in Trajectory (ACT)","Opportunity Summary","P1 Downtown location","Months",5) -> #REF! | J12: This week :)
B13: POTS Forever Social Cabling | C13: 2019 | E13: 1 | F13: 0 | G13: =GETPIVOTDATA("Sum of Revenue",$A$4,"Close Date",152,"Company","Advanced Chiropractic","Opportunity Summary","P1 Sonicwall License Renewal","Months",5) -> #REF! | J13: Need to invoice, update status of opp and ticket to needs invoice
C14: Feb | E14: 1 | F14: 0 | G14: =GETPIVOTDATA("Sum of Revenue",$A$4,"Close Date",125,"Company","Autism Behavioral Health (ABH)","Opportunity Summary","P1 snipping tool","Months",5) -> #REF!
C15: 28-Feb | D15: 90 - Lost | E15: 1 | F15: 0 | H15: =GETPIVOTDATA("Sum of Revenue",$A$4,"Close Date",152,"Company","CAPS MEDIA","Opportunity Summary","P1 PC Refresh - Win7 1 of 1","Months",5) -> #REF! | J15: Wait from info from client - internal challenge with their tech - need to f/u this week
B16: POTS Hive manager renewal | C16: 2019 | E16: 1 | F16: 525 | I16: =GETPIVOTDATA("Sum of Revenue",$A$4,"Close Date",152,"Company","Cool Pak","Opportunity Summary","P1 AWS - MS","Months",5) -> #REF! | J16: Update close date
C17: Feb | E17: 1 | F17: 525 | G17: =GETPIVOTDATA("Sum of Revenue",$A$4,"Close Date",125,"Company","DITEC Manufacturing","Opportunity Summary","P1 PC Refresh 1 of 6","Stage","Awaiting Client Approval","Months",5) -> #REF! | J17: need final client approval - Chad to call
C18: 18-Feb | D18: 13 - Needs Invoice | E18: 1 | F18: 525 | G18: =GETPIVOTDATA("Sum of Revenue",$A$4,"Close Date",142,"Company","DITEC Manufacturing","Opportunity Summary","P1 PC Refresh 2 of 6","Stage","New Opportunity","Months",5) -> #REF! | J18: need final client approval - Chad to call
B19: POTS Van Nuys Cable Add'l | C19: 2019 | E19: 1 | F19: 404.57 | I19: =GETPIVOTDATA("Sum of Revenue",$A$4,"Close Date",125,"Company","G and R Concrete","Opportunity Summary","P1 PC Refresh","Stage","New Opportunity","Months",5) -> #REF! | J19: update close date - confirm if "real"
C20: Jan | E20: 1 | F20: 404.57 | I20: =GETPIVOTDATA("Sum of Revenue",$A$4,"Close Date",152,"Company","Hod Dunbar","Opportunity Summary","P1 WiFI","Stage","New Opportunity","Months",5) -> #REF! | J20: June
C21: 21-Jan | D21: 13 - Needs Invoice | E21: 1 | F21: 404.57 | I21: =GETPIVOTDATA("Sum of Revenue",$A$4,"Close Date",152,"Company","House of Ruth","Opportunity Summary","P1 Laptop","Stage","New Opportunity","Months",5) -> #REF! | J21: Need to close opp, no sale
B22: POTS dual monitor | C22: 2019 | E22: 1 | F22: 132.97 | H22: =GETPIVOTDATA("Sum of Revenue",$A$4,"Close Date",125,"Company","House of Ruth","Opportunity Summary","P1 New Printer","Stage","New Opportunity","Months",5) -> #REF! | J22: Need to look into - call customer
C23: Mar | E23: 1 | F23: 132.97 | H23: =GETPIVOTDATA("Sum of Revenue",$A$4,"Close Date",152,"Company","House of Ruth","Opportunity Summary","P1 replace all computers HDD","Stage","Awaiting Client Approval","Months",5) -> #REF! | J23: Maybe for May - only 1 of these will come in. F/u with customer
C24: 31-Mar | D24: 13 - Needs Invoice | E24: 1 | F24: 132.97 | I24: =GETPIVOTDATA("Sum of Revenue",$A$4,"Close Date",152,"Company","House of Ruth","Opportunity Summary","P1 replace all computers SSD","Stage","Awaiting Client Approval","Months",5) -> #REF!
B25: POTS Adobe Acrobat DC licenses 32 exp 3/22 | C25: 2019 | E25: 1 | F25: 5660.9 | H25: =GETPIVOTDATA("Sum of Revenue",$A$4,"Close Date",125,"Company","Instrument Control Services","Opportunity Summary","P1 VoIP Proposal","Stage","New Opportunity","Months",5) -> #REF! | J25: Emo. Chad to follow up
C26: Mar | E26: 1 | F26: 5660.9 | I26: =GETPIVOTDATA("Sum of Revenue",$A$4,"Close Date",152,"Company","Jack Built","Opportunity Summary","P1 MS","Stage","Qualifying","Months",5) -> #REF! | J26: owner is going dark - potential new client
C27: 13-Mar | D27: 13 - Needs Invoice | E27: 1 | F27: 5660.9 | I27: =GETPIVOTDATA("Sum of Revenue",$A$4,"Close Date",152,"Company","Notes for Notes","Opportunity Summary","P1 iMac Hard Drive","Stage","On Hold","Months",5) -> #REF! | J27: Chad to f/u
B28: POTS Riverside Computers | C28: 2019 | E28: 1 | F28: 1739.66 | H28: =GETPIVOTDATA("Sum of Revenue",$A$4,"Close Date",152,"Company","Ojai Oil Company","Opportunity Summary","P1 AWS - test server","Stage","Awaiting Client Approval","Months",5) -> #REF! | J28: Testing thin client. Need to get someone onsite to set it up - sch this week
C29: Mar | E29: 1 | F29: 1739.66 | I29: =GETPIVOTDATA("Sum of Revenue",$A$4,"Close Date",152,"Company","Organic Certifiers","Opportunity Summary","P1 AWS Migration","Stage","Awaiting Client Approval","Months",5) -> #REF! | J29: need to follow up
C30: 31-Mar | D30: 13 - Needs Invoice | E30: 1 | F30: 1739.66 | I30: =GETPIVOTDATA("Sum of Revenue",$A$4,"Close Date",152,"Company","Passport to Adaptive Living","Opportunity Summary","P1 ABAS-3 server setup","Stage","New Opportunity","Months",5) -> #REF! | J30: No - need to close
B31: POTS Fresno Computers | C31: 2019 | E31: 1 | F31: 1787.24 | H31: =GETPIVOTDATA("Sum of Revenue",$A$4,"Close Date",152,"Company","Pilot Automotive","Opportunity Summary","P1 Wi-Fi (Aerohive)","Stage","Awaiting Client Approval","Months",5) -> #REF! | J31: Need client approval - buy something that smells good?
C32: Mar | E32: 1 | F32: 1787.24 | I32: =GETPIVOTDATA("Sum of Revenue",$A$4,"Close Date",152,"Company","Project Sister Family Services","Opportunity Summary","P1 CURV server renewal Serial HHMQ082 ","Stage","Needs Invoice","Months",5) -> #REF! | J32: warranty renewal - give to them to get through 2018 - quote for 13 mo
C33: 31-Mar | D33: 13 - Needs Invoice | E33: 1 | F33: 1787.24 | I33: =GETPIVOTDATA("Sum of Revenue",$A$4,"Close Date",145,"Company","Ransom Seed Laboratory","Opportunity Summary","P1 8x8","Stage","Qualifying","Months",5) -> #REF! | J33: Update close date
B34: POTS Van Nuys computers | C34: 2019 | E34: 1 | F34: 2680.86 | I34: =GETPIVOTDATA("Sum of Revenue",$A$4,"Close Date",152,"Company","Smile Shapers","Opportunity Summary","P1 Server","Stage","New Opportunity","Months",5) -> #REF! | J34: one of the 3 will come in - 3 quotes
C35: Mar | E35: 1 | F35: 2680.86 | I35: =GETPIVOTDATA("Sum of Revenue",$A$4,"Close Date",122,"Company","Smile Shapers","Opportunity Summary","P1 Server (low)","Stage","New Opportunity","Months",5) -> #REF!
C36: 31-Mar | D36: 13 - Needs Invoice | E36: 1 | F36: 2680.86 | G36: =GETPIVOTDATA("Sum of Revenue",$A$4,"Close Date",152,"Company","Smile Shapers","Opportunity Summary","P1 Sodo Server","Stage","New Opportunity","Months",5) -> #REF!
B37: POTS San Diego Office - New | C37: 2019 | E37: 1 | F37: 6643.04 | H37: =GETPIVOTDATA("Sum of Revenue",$A$4,"Close Date",152,"Company","Ventura Harley","Opportunity Summary","P1 MS","Stage","New Opportunity","Months",5) -> #REF! | J37: follow up
C38: May | E38: 1 | F38: 6643.04 | H38: =GETPIVOTDATA("Sum of Revenue",$A$4,"Close Date",152,"Company","ZNS","Opportunity Summary","P1 Office365 Migratin","Stage","New Opportunity","Months",5) -> #REF!
C39: 31-May | D39: 5 - Solution Development | E39: 1 | F39: 6643.04 | G39: =GETPIVOTDATA("Sum of Revenue",$A$4,"Close Date",125,"Company","ZNS","Opportunity Summary","P1 Server Option 1","Stage","New Opportunity","Months",5) -> #REF!
B40: POTS clone AWS | C40: 2019 | E40: 1 | F40: 0 | I40: =GETPIVOTDATA("Sum of Revenue",$A$4,"Close Date",125,"Company","ZNS","Opportunity Summary","P1 Server option 2","Stage","New Opportunity","Months",5) -> #REF!
C41: May | E41: 1 | F41: 0 | G41: =GETPIVOTDATA("Sum of Revenue",$A$4,"Close Date",137,"Company","ZNS","Opportunity Summary","P1 Site location setup","Stage","New Opportunity","Months",5) -> #REF!
C42: 31-May | D42: 1 - New Opportunity | E42: 1 | F42: 0
B43: POTS Adobe license addition | C43: 2019 | E43: 1 | F43: 321.08 | G43: =GETPIVOTDATA("Sum of Revenue",$A$4,"Close Date",179,"Company","Autism Response Team (ART)","Opportunity Summary","P1 Raise AWS amount they pay","Stage","New Opportunity","Months",6) -> #REF!
C44: May | E44: 1 | F44: 321.08 | H44: =GETPIVOTDATA("Sum of Revenue",$A$4,"Close Date",167,"Company","DITEC Manufacturing","Opportunity Summary","P1 DYNAMICS Migration Project","Stage","On Hold","Months",6) -> #REF! | J44: $25K to book in June, $15K sept, dec
C45: 1-May | D45: 13 - Needs Invoice | E45: 1 | F45: 321.08 | G45: =GETPIVOTDATA("Sum of Revenue",$A$4,"Close Date",170,"Company","DITEC Manufacturing","Opportunity Summary","P1 PC Refresh 3 of 6","Stage","New Opportunity","Months",6) -> #REF!
B46: POTS remove ZNS icons | C46: 2019 | E46: 1 | F46: 0
C47: May | E47: 1 | F47: 0
C48: 31-May | D48: 5 - Solution Development | E48: 1 | F48: 0
B49: POTS Wyse Thin Client Management Suite | C49: 2019 | E49: 1 | F49: 0
C50: May | E50: 1 | F50: 0
C51: 31-May | D51: 5 - Solution Development | E51: 1 | F51: 0
A52: ABEDI | B52: POTS PC refresh | C52: 2019 | E52: 1 | F52: 9000
C53: Sep | E53: 1 | F53: 9000
C54: 20-Sep | D54: 5 - Solution Development | E54: 1 | F54: 9000
B55: POTS sonicwall renewal | C55: 2019 | E55: 1 | F55: 539
C56: Apr | E56: 1 | F56: 539
C57: 29-Apr | D57: 13 - Needs Invoice | E57: 1 | F57: 539
B58: POTS 2-in-1 laptop | C58: 2019 | E58: 1 | F58: 0
C59: Jan | E59: 1 | F59: 0
C60: 31-Jan | D60: 90 - Lost | E60: 1 | F60: 0
B61: POTS on-site tech | C61: 2019 | E61: 1 | F61: 620
C62: May | E62: 1 | F62: 620
C63: 1-May | D63: 5 - Solution Development | E63: 1 | F63: 620
A64: Advanced Chiropractic | B64: POTS Refurb Desktop | C64: 2019 | E64: 1 | F64: 1065.34
C65: Jan | E65: 1 | F65: 1065.34
C66: 7-Jan | D66: 13 - Needs Invoice | E66: 1 | F66: 1065.34
B67: POTS MS Office 2019 | C67: 2019 | E67: 1 | F67: 249
C68: Jan | E68: 1 | F68: 249
C69: 9-Jan | D69: 13 - Needs Invoice | E69: 1 | F69: 249
B70: POTS PC Refresh (remaining 8 comps) | C70: 2019 | E70: 1 | F70: 7376.8
C71: Jan | E71: 1 | F71: 7376.8
C72: 24-Jan | D72: 13 - Needs Invoice | E72: 1 | F72: 7376.8
A73: Autism Behavioral Health (ABH) | B73: POTS sonicwall renewal | C73: 2019 | E73: 1 | F73: 600
C74: Mar | E74: 1 | F74: 600
C75: 13-Mar | D75: 13 - Needs Invoice | E75: 1 | F75: 600
B76: POTS refurb laptop | C76: 2019 | E76: 1 | F76: 617.99
C77: Jan | E77: 1 | F77: 617.99
C78: 12-Jan | D78: 13 - Needs Invoice | E78: 1 | F78: 617.99
A79: Autism Response Team (ART) | B79: POTS aerohive | C79: 2019 | E79: 1 | F79: 686.5
C80: Apr | E80: 1 | F80: 686.5
C81: 30-Apr | D81: 13 - Needs Invoice | E81: 1 | F81: 686.5
B82: POTS sonicwall renewal | C82: 2019 | E82: 1 | F82: 539
C83: May | E83: 1 | F83: 539
C84: 1-May | D84: 13 - Needs Invoice | E84: 1 | F84: 539
B85: POTS Hive manager renewal | C85: 2019 | E85: 1 | F85: 350
C86: Feb | E86: 1 | F86: 350
C87: 18-Feb | D87: 13 - Needs Invoice | E87: 1 | F87: 350
A88: AVF Group Incorporated | B88: POTS PC Refresh | C88: 2019 | E88: 1 | F88: 6000
C89: Aug | E89: 1 | F89: 6000
C90: 31-Aug | D90: 5 - Solution Development | E90: 1 | F90: 6000
B91: POTS sonicwall renewal | C91: 2019 | E91: 1 | F91: 539
C92: Mar | E92: 1 | F92: 539
C93: 13-Mar | D93: 13 - Needs Invoice | E93: 1 | F93: 539
B94: POTS server renewal | C94: 2019 | E94: 1 | F94: 212.64
C95: Apr | E95: 1 | F95: 212.64
C96: 8-Apr | D96: 13 - Needs Invoice | E96: 1 | F96: 212.64
B97: POTS laptop | C97: 2019 | E97: 1 | F97: 2268.77
C98: Feb | E98: 1 | F98: 2268.77
C99: 28-Feb | D99: 13 - Needs Invoice | E99: 1 | F99: 2268.77
A100: CAPS MEDIA | B100: POTS sonicwall renewal | C100: 2019 | E100: 1 | F100: 539
C101: Jan | E101: 1 | F101: 539
...

Sheet 5.1.18-2
A1: Jan | G1: Yes | H1: Maybe | I1: No | J1: Notes
A2: Turning Point Foundation | B2: P1 Computer Refresh | C2: 31-Jan | D2: Quoting | E2: 1 | F2: 24000 | J2: Update Amount, and update close date - past may
A3: Feb | E3: 2 | F3: 7013.21
A4: Turning Point Foundation | B4: P1 Office365 Migration | C4: 28-Feb | D4: Qualifying | E4: 1 | F4: 7000 | J4: Update Amount, and update close date - past may
A5: XYZ Test Company | B5: TEST OPPORTUNITY | C5: 20-Feb | D5: New Opportunity | E5: 1 | F5: 13.21 | J5: Ask Amy if we can close this. Or move to 2017 close date
A6: May | E6: 30 | F6: 161877.64
A7: A Change in Trajectory (ACT) | B7: P1 Downtown location | C7: 31-May | D7: New Opportunity | E7: 1 | F7: 24992.23 | G7: 24992.23 | J7: This week :)
A8: Advanced Chiropractic | B8: P1 Sonicwall License Renewal | C8: 31-May | D8: On Hold | E8: 1 | F8: 249 | G8: 249 | J8: Need to invoice, update status of opp and ticket to needs invoice
A9: Autism Behavioral Health (ABH) | B9: P1 snipping tool | C9: 4-May | D9: New Opportunity | E9: 1 | F9: 310 | G9: 310
A10: CAPS MEDIA | B10: P1 PC Refresh - Win7 1 of 1 | C10: 31-May | D10: Awaiting Client Approval | E10: 1 | F10: 1858.9 | H10: 1858.9 | J10: Wait from info from client - internal challenge with their tech - need to f/u this week
A11: Cool Pak | B11: P1 AWS - MS | C11: 31-May | D11: Quoting | E11: 1 | F11: 985 | I11: 985 | J11: Update close date
A12: DITEC Manufacturing | B12: P1 PC Refresh 1 of 6 | C12: 4-May | D12: Awaiting Client Approval | E12: 1 | F12: 2010 | G12: 2010 | J12: need final client approval - Chad to call
B13: P1 PC Refresh 2 of 6 | C13: 21-May | D13: New Opportunity | E13: 1 | F13: 2010 | G13: 2010 | J13: need final client approval - Chad to call
A14: G and R Concrete | B14: P1 PC Refresh | C14: 4-May | D14: New Opportunity | E14: 1 | F14: 1000 | I14: 1000 | J14: update close date - confirm if "real"
A15: Hod Dunbar | B15: P1 WiFI | C15: 31-May | D15: New Opportunity | E15: 1 | F15: 1013 | I15: 1013 | J15: June
A16: House of Ruth | B16: P1 Laptop | C16: 31-May | D16: New Opportunity | E16: 1 | F16: 627.49 | I16: 627.49 | J16: Need to close opp, no sale
B17: P1 New Printer | C17: 4-May | D17: New Opportunity | E17: 1 | F17: 839.99 | H17: 839.99 | J17: Need to look into - call customer
B18: P1 replace all computers HDD | C18: 31-May | D18: Awaiting Client Approval | E18: 1 | F18: 25507.21 | H18: 25507.21 | J18: Maybe for May - only 1 of these will come in. F/u with customer
B19: P1 replace all computers SSD | C19: 31-May | D19: Awaiting Client Approval | E19: 1 | F19: 29945.99 | I19: 29945.99
A20: Instrument Control Services | B20: P1 VoIP Proposal | C20: 4-May | D20: New Opportunity | E20: 1 | F20: 2800 | H20: 2800 | J20: Emo. Chad to follow up
A21: Jack Built | B21: P1 MS | C21: 31-May | D21: Qualifying | E21: 1 | F21: 1000 | I21: 1000 | J21: owner is going dark - potential new client
A22: Notes for Notes | B22: P1 iMac Hard Drive | C22: 31-May | D22: On Hold | E22: 1 | F22: 265.79 | I22: 265.79 | J22: Chad to f/u
A23: Ojai Oil Company | B23: P1 AWS - test server | C23: 31-May | D23: Awaiting Client Approval | E23: 1 | F23: 6000 | H23: 6000 | J23: Testing thin client. Need to get someone onsite to set it up - sch this week
A24: Organic Certifiers | B24: P1 AWS Migration | C24: 31-May | D24: Awaiting Client Approval | E24: 1 | F24: 3100 | I24: 3100 | J24: need to follow up
A25: Passport to Adaptive Living | B25: P1 ABAS-3 server setup | C25: 31-May | D25: New Opportunity | E25: 1 | F25: 310 | I25: 310 | J25: No - need to close
A26: Pilot Automotive | B26: P1 Wi-Fi (Aerohive) | C26: 31-May | D26: Awaiting Client Approval | E26: 1 | F26: 3564 | H26: 3564 | J26: Need client approval - buy something that smells good?
A27: Project Sister Family Services | B27: P1 CURV server renewal Serial HHMQ082 | C27: 31-May | D27: Needs Invoice | E27: 1 | F27: 50 | I27: 50 | J27: warranty renewal - give to them to get through 2018 - quote for 13 mo
A28: Ransom Seed Laboratory | B28: P1 8x8 | C28: 24-May | D28: Qualifying | E28: 1 | F28: 1550 | I28: 1550 | J28: Update close date
A29: Smile Shapers | B29: P1 Server | C29: 31-May | D29: New Opportunity | E29: 1 | F29: 10895.86 | I29: 10895.86 | J29: one of the 3 will come in - 3 quotes
B30: P1 Server (low) | C30: 1-May | D30: New Opportunity | E30: 1 | F30: 9527.88 | I30: 9527.88
B31: P1 Sodo Server | C31: 31-May | D31: New Opportunity | E31: 1 | F31: 3803.94 | G31: 3803.94
A32: Ventura Harley | B32: P1 MS | C32: 31-May | D32: New Opportunity | E32: 1 | F32: 567 | H32: 567 | J32: follow up
A33: ZNS | B33: P1 Office365 Migratin | C33: 31-May | D33: New Opportunity | E33: 1 | F33: 4650 | H33: 4650
B34: P1 Server Option 1 | C34: 4-May | D34: New Opportunity | E34: 1 | F34: 11171.4 | G34: 11171.4
B35: P1 Server option 2 | C35: 4-May | D35: New Opportunity | E35: 1 | F35: 10272.96 | I35: 10272.96
B36: P1 Site location setup | C36: 16-May | D36: New Opportunity | E36: 1 | F36: 1000 | G36: 1000
A37: Jun | E37: 3 | F37: 55918
A38: Autism Response Team (ART) | B38: P1 Raise AWS amount they pay | C38: 27-Jun | D38: New Opportunity | E38: 1 | F38: 300 | G38: 300
A39: DITEC Manufacturing | B39: P1 DYNAMICS Migration Project | C39: 15-Jun | D39: On Hold | E39: 1 | F39: 53430 | H39: 53430 | J39: $25K to book in June, $15K sept, dec
B40: P1 PC Refresh 3 of 6 | C40: 18-Jun | D40: New Opportunity | E40: 1 | F40: 2188 | G40: 2188

Sheet 5.9.18
F1: Yes | G1: Maybe | H1: No | I1: Notes
E2: =SUM(F2:G2) -> #REF! | F2: =SUM(F6:F28) -> #REF! | G2: =SUM(G6:G28) -> #REF! | H2: =SUM(H6:H28) -> #REF!
A3: Row Labels | B3: Opportunity Summary | C3: Years | D3: Stage | E3: Sum of Revenue
A4: A Change in Trajectory (ACT) | B4: POTS PC Refresh | C4: 2019 | E4: 22000
C5: Aug | E5: 22000
C6: 31-Aug | D6: 5 - Solution Development | E6: 22000 | F6: =GETPIVOTDATA("Revenue",$A$3,"Close Date",152,"Company","A Change in Trajectory (ACT)","Opportunity Summary","P1 Downtown location","Stage","New Opportunity","Months",5) -> #REF! | I6: 99% sure will come in by EOM
B7: POTS sonicwall renewal | C7: 2019 | E7: 2000 | H7: =GETPIVOTDATA("Revenue",$A$3,"Close Date",152,"Company","Cool Pak","Opportunity Summary","P1 AWS - MS","Stage","Quoting","Months",5) -> #REF! | I7: Recurring - move to June. Deciding this month to start June 1 - Chad to call
C8: Feb | E8: 400 | G8: =GETPIVOTDATA("Revenue",$A$3,"Close Date",152,"Company","Hod Dunbar","Opportunity Summary","P1 WiFI","Stage","New Opportunity","Months",5) -> #REF! | I8: Charlie to f/u
C9: 20-Feb | D9: 13 - Needs Invoice | E9: 400 | G9: =GETPIVOTDATA("Revenue",$A$3,"Close Date",152,"Company","House of Ruth","Opportunity Summary","P1 replace all computers HDD","Stage","Awaiting Client Approval","Months",5) -> #REF! | I9: Will get 1 of 2 - customer has become unresponsive. Required to buy new computer. Pricing not issue. Need to find out - when is the grant due? Chad to call customer
C10: Mar | E10: 1600 | H10: =GETPIVOTDATA("Revenue",$A$3,"Close Date",152,"Company","House of Ruth","Opportunity Summary","P1 replace all computers SSD","Stage","Awaiting Client Approval","Months",5) -> #REF! | I10: Will get 1 of 2
C11: 13-Mar | D11: 13 - Needs Invoice | E11: 1600 | F11: =GETPIVOTDATA("Revenue",$A$3,"Close Date",152,"Company","Inland Valley Hope Partners","Opportunity Summary","P1 Refurbished Desktop ","Stage","Quote in review","Months",5) -> #REF! | I11: Approved. Waiting for invoice. f/u if don’t receive by 5/14
B12: POTS Forever Social Cabling | C12: 2019 | E12: 0 | H12: =GETPIVOTDATA("Revenue",$A$3,"Close Date",152,"Company","Jack Built","Opportunity Summary","P1 MS","Stage","Qualifying","Months",5) -> #REF! | I12: Chad get this off list - Add to/create drip list?
C13: Feb | E13: 0 | F13: =GETPIVOTDATA("Revenue",$A$3,"Close Date",130,"Company","Mission Oaks Tax and Accounting","Opportunity Summary","P1 Battery Backup - Server Grade","Stage","New Opportunity","Months",5) -> #REF!
C14: 28-Feb | D14: 90 - Lost | E14: 0 | F14: =GETPIVOTDATA("Revenue",$A$3,"Close Date",152,"Company","Ojai Oil Company","Opportunity Summary","P1 AWS - test server","Stage","Awaiting Client Approval","Months",5) -> #REF! | I14: Setting up thin client today. Will have answer this week how it work. F/u if don’t hear back by 5/14. How can we make more money from them!!!! :)
B15: POTS Hive manager renewal | C15: 2019 | E15: 525 | H15: =GETPIVOTDATA("Revenue",$A$3,"Close Date",152,"Company","Organic Certifiers","Opportunity Summary","P1 AWS Migration","Stage","Awaiting Client Approval","Months",5) -> #REF! | I15: Close
C16: Feb | E16: 525 | H16: =GETPIVOTDATA("Revenue",$A$3,"Close Date",152,"Company","Passport to Adaptive Living","Opportunity Summary","P1 ABAS-3 server setup","Stage","New Opportunity","Months",5) -> #REF! | I16: Close
C17: 18-Feb | D17: 13 - Needs Invoice | E17: 525 | H17: =GETPIVOTDATA("Revenue",$A$3,"Close Date",152,"Company","Pilot Automotive","Opportunity Summary","P1 Wi-Fi (Aerohive)","Stage","Awaiting Client Approval","Months",5) -> #REF! | I17: Want it, no pressing need. IT wants - eventually will come in. Move close date? Adnana meeting with them 5/10
B18: POTS Van Nuys Cable Add'l | C18: 2019 | E18: 404.57 | F18: =GETPIVOTDATA("Revenue",$A$3,"Close Date",152,"Company","Pilot Automotive","Opportunity Summary","P1 MS increase","Stage","New Opportunity","Months",5) -> #REF!
C19: Jan | E19: 404.57 | H19: =GETPIVOTDATA("Revenue",$A$3,"Close Date",152,"Company","Project Sister Family Services","Opportunity Summary","P1 CURV server renewal Serial HHMQ082 ","Stage","Needs Invoice","Months",5) -> #REF! | I19: Move to purchasing board - add notes as to what we are doing!
C20: 21-Jan | D20: 13 - Needs Invoice | E20: 404.57 | G20: =GETPIVOTDATA("Revenue",$A$3,"Close Date",152,"Company","Ransom Seed Laboratory","Opportunity Summary","P1 8x8","Stage","Qualifying","Months",5) -> #REF! | I20: Chad to call this week - will know definite yes or no
B21: POTS dual monitor | C21: 2019 | E21: 132.97 | F21: =GETPIVOTDATA("Revenue",$A$3,"Close Date",152,"Company","Smile Shapers","Opportunity Summary","P1 Server (low)","Stage","New Opportunity","Months",5) -> #REF! | I21: Will get 1 of 2 - agreed for 2 PC refreshes/mo. F/u by 5/14
C22: Mar | E22: 132.97 | H22: =GETPIVOTDATA("Revenue",$A$3,"Close Date",152,"Company","Smile Shapers","Opportunity Summary","P1 Sodo Server","Stage","New Opportunity","Months",5) -> #REF! | I22: Will get 1 of 2
C23: 31-Mar | D23: 13 - Needs Invoice | E23: 132.97 | F23: =GETPIVOTDATA("Revenue",$A$3,"Close Date",152,"Company","Studio Designs","Opportunity Summary","P1 MS increase","Stage","New Opportunity","Months",5) -> #REF! | I23: Adnan meeting with them - will know yes v no
B24: POTS Adobe Acrobat DC licenses 32 exp 3/22 | C24: 2019 | E24: 5660.9 | G24: =GETPIVOTDATA("Revenue",$A$3,"Close Date",152,"Company","Turning Point Foundation","Opportunity Summary","P1 AWS MS","Stage","Awaiting Client Approval","Months",5) -> #REF! | I24: recurring - has to happen, forced to upgrade. F/u try to get meeting with CEO
C25: Mar | E25: 5660.9 | H25: =GETPIVOTDATA("Revenue",$A$3,"Close Date",152,"Company","Ventura Harley","Opportunity Summary","P1 MS","Stage","New Opportunity","Months",5) -> #REF! | I25: Move to June
C26: 13-Mar | D26: 13 - Needs Invoice | E26: 5660.9 | H26: =GETPIVOTDATA("Revenue",$A$3,"Close Date",152,"Company","ZNS","Opportunity Summary","P1 Office365 Migratin","Stage","New Opportunity","Months",5) -> #REF! | I26: Remove
B27: POTS Riverside Computers | C27: 2019 | E27: 1739.66 | F27: =GETPIVOTDATA("Revenue",$A$3,"Close Date",152,"Company","ZNS","Opportunity Summary","P1 o365","Stage","New Opportunity","Months",5) -> #REF!
C28: Mar | E28: 1739.66
C29: 31-Mar | D29: 13 - Needs Invoice | E29: 1739.66
B30: POTS Fresno Computers | C30: 2019 | E30: 1787.24
C31: Mar | E31: 1787.24
C32: 31-Mar | D32: 13 - Needs Invoice | E32: 1787.24
B33: POTS Van Nuys computers | C33: 2019 | E33: 2680.86
C34: Mar | E34: 2680.86
C35: 31-Mar | D35: 13 - Needs Invoice | E35: 2680.86
B36: POTS San Diego Office - New | C36: 2019 | E36: 6643.04
C37: May | E37: 6643.04
C38: 31-May | D38: 5 - Solution Development | E38: 6643.04
B39: POTS clone AWS | C39: 2019 | E39: 0
C40: May | E40: 0
C41: 31-May | D41: 1 - New Opportunity | E41: 0
B42: POTS Adobe license addition | C42: 2019 | E42: 321.08
C43: May | E43: 321.08
C44: 1-May | D44: 13 - Needs Invoice | E44: 321.08
B45: POTS remove ZNS icons | C45: 2019 | E45: 0
C46: May | E46: 0
C47: 31-May | D47: 5 - Solution Development | E47: 0
B48: POTS Wyse Thin Client Management Suite | C48: 2019 | E48: 0
C49: May | E49: 0
C50: 31-May | D50: 5 - Solution Development | E50: 0
A51: ABEDI | B51: POTS PC refresh | C51: 2019 | E51: 9000
C52: Sep | E52: 9000
C53: 20-Sep | D53: 5 - Solution Development | E53: 9000
B54: POTS sonicwall renewal | C54: 2019 | E54: 539
C55: Apr | E55: 539
C56: 29-Apr | D56: 13 - Needs Invoice | E56: 539
B57: POTS 2-in-1 laptop | C57: 2019 | E57: 0
C58: Jan | E58: 0
C59: 31-Jan | D59: 90 - Lost | E59: 0
B60: POTS on-site tech | C60: 2019 | E60: 620
C61: May | E61: 620
C62: 1-May | D62: 5 - Solution Development | E62: 620
A63: Advanced Chiropractic | B63: POTS Refurb Desktop | C63: 2019 | E63: 1065.34
C64: Jan | E64: 1065.34
C65: 7-Jan | D65: 13 - Needs Invoice | E65: 1065.34
B66: POTS MS Office 2019 | C66: 2019 | E66: 249
C67: Jan | E67: 249
C68: 9-Jan | D68: 13 - Needs Invoice | E68: 249
B69: POTS PC Refresh (remaining 8 comps) | C69: 2019 | E69: 7376.8
C70: Jan | E70: 7376.8
C71: 24-Jan | D71: 13 - Needs Invoice | E71: 7376.8
A72: Autism Behavioral Health (ABH) | B72: POTS sonicwall renewal | C72: 2019 | E72: 600
C73: Mar | E73: 600
C74: 13-Mar | D74: 13 - Needs Invoice | E74: 600
B75: POTS refurb laptop | C75: 2019 | E75: 617.99
C76: Jan | E76: 617.99
C77: 12-Jan | D77: 13 - Needs Invoice | E77: 617.99
A78: Autism Response Team (ART) | B78: POTS aerohive | C78: 2019 | E78: 686.5
C79: Apr | E79: 686.5
C80: 30-Apr | D80: 13 - Needs Invoice | E80: 686.5
B81: POTS sonicwall renewal | C81: 2019 | E81: 539
C82: May | E82: 539
C83: 1-May | D83: 13 - Needs Invoice | E83: 539
B84: POTS Hive manager renewal | C84: 2019 | E84: 350
C85: Feb | E85: 350
C86: 18-Feb | D86: 13 - Needs Invoice | E86: 350
A87: AVF Group Incorporated | B87: POTS PC Refresh | C87: 2019 | E87: 6000
C88: Aug | E88: 6000
C89: 31-Aug | D89: 5 - Solution Development | E89: 6000
B90: POTS sonicwall renewal | C90: 2019 | E90: 539
C91: Mar | E91: 539
C92: 13-Mar | D92: 13 - Needs Invoice | E92: 539
B93: POTS server renewal | C93: 2019 | E93: 212.64
C94: Apr | E94: 212.64
C95: 8-Apr | D95: 13 - Needs Invoice | E95: 212.64
B96: POTS laptop | C96: 2019 | E96: 2268.77
C97: Feb | E97: 2268.77
C98: 28-Feb | D98: 13 - Needs Invoice | E98: 2268.77
A99: CAPS MEDIA | B99: POTS sonicwall renewal | C99: 2019 | E99: 539
C100: Jan | E100: 539
...

Sheet 5.22.18 v2
F1: Yes | G1: Maybe | H1: No | I1: Notes
E2: 2172.9 | F2: 2172.9 | G2: 0 | H2: 115444.7
A3: Row Labels | B3: Opportunity Summary | C3: Stage | D3: Close Date | E3: Sum of Revenue
A4: <5/18/2018
A5: May
A6: Autism Response Team (ART) | B6: POTS refurbished laptops (3) | C6: New Opportunity | D6: 18-May | E6: 1459.65 | F6: 1459.65 | I6: Waiting client approval - change stage
A7: Hod Dunbar | B7: POTS WiFI | C7: New Opportunity | D7: 31-May | E7: 1013 | H7: 1013 | I7: Remove
A8: House of Ruth | B8: POTS replace all computers HDD | C8: Awaiting Client Approval | D8: 31-May | E8: 25507.21 | H8: 25507.21 | I8: Move close date out of May - CSAT. Need to have an in person meeting with Adnan and Chad
B9: POTS replace all computers SSD | C9: Awaiting Client Approval | D9: 31-May | E9: 29945.99 | H9: 29945.99 | I9: same as above
A10: Ojai Oil Company | B10: POTS AWS - test server | C10: Awaiting Client Approval | D10: 31-May | E10: 6000 | H10: 6000 | I10: Move Close date to June?
A11: Project Sister Family Services | B11: POTS monitors (3) | C11: New Opportunity | D11: 18-May | E11: 713.25 | F11: 713.25 | I11: Invoiced this week - waiting client approval
A12: Turning Point Foundation | B12: POTS AWS MS | C12: Awaiting Client Approval | D12: 31-May | E12: 2411.5 | H12: 2411.5 | I12: Move to June
A13: Ventura Harley | B13: POTS MS | C13: New Opportunity | D13: 31-May | E13: 567 | H13: 567 | I13: Move to June
A14: ZNS | B14: POTS o365 | C14: New Opportunity | D14: 31-May | E14: 50000 | H14: 50000 | I14: Making decision on 5/29 (Tues)
A15: Jun | F15: 58978.5
A16: Autism Response Team (ART) | B16: POTS Raise AWS amount they pay | C16: New Opportunity | D16: 27-Jun | E16: 300 | F16: 300
A17: California Center for Public Health Advocacy | B17: POTS monthly website maintenance | C17: New Opportunity | D17: 4-Jun | E17: 0 | F17: 100 | I17: Need to update Revenue $$ - website maintenance monthly fee
A18: Cool Pak | B18: POTS AWS - MS | C18: Quoting | D18: 30-Jun | E18: 1879 | G18: 1879
A19: DITEC Manufacturing | B19: POTS DYNAMICS Migration Project | C19: On Hold | D19: 15-Jun | E19: 53430 | G19: 25000 | I19: need to f.u
B20: POTS PC Refresh 1 of 6 | C20: Awaiting Client Approval | D20: 30-Jun | E20: 2010 | F20: 2010
B21: POTS PC Refresh 2 of 6 | C21: Awaiting Client Approval | D21: 30-Jun | E21: 2010 | H21: 2010
A22: Instrument Control Services | B22: POTS VoIP Proposal | C22: New Opportunity | D22: 30-Jun | E22: 2800 | G22: 2800 | I22: need to f/u
A23: Manduka | B23: POTS server environment upgrade | C23: New Opportunity | D23: 30-Jun | E23: 0 | I23: Need to update Revenue $$, update close month
A24: Notes for Notes | B24: POTS iMac Hard Drive | C24: On Hold | D24: 30-Jun | E24: 265.79 | F24: 265.79 | I24: invoiced?
A25: Pilot Automotive | B25: POTS Wi-Fi (Aerohive) | C25: Awaiting Client Approval | D25: 30-Jun | E25: 3564 | G25: 3564 | I25: Adnan to intro Chad and make sure proper "hand over"
A26: ZNS | B26: POTS Site location setup | C26: New Opportunity | D26: 30-Jun | E26: 1000 | F26: 1000 | I26: New site
A27: Jul | E27: 23958.85 | F27: 10000 | I27: ACT - cabling for DT LA Office
A28: Aug | E28: 539 | F28: 72654.29

Sheet Sales Campaign Pivot
A1: Company | B1: (Multiple Items)
A2: Opportunity Summary | B2: (All)
A3: Stage | B3: (Multiple Items)
A4: Close Date | B4: (Multiple Items)
A5: Years | B5: 2019
A7: Row Labels | B7: Campaign | C7: Sum of Revenue
A8: Dec | B8: POTS-Server Replacement | C8: 10000
A9: Dec Total | C9: 10000
A10: Grand Total | C10: 10000

Sheet Sales Campaign Overview
A1: Sales Campaign Forecast | B1: Total | D1: January | F1: February | H1: March | J1: April | L1: May | N1: June | P1: July | R1: August | T1: September | V1: October | X1: November | Z1: December
A2: POTS - 2011 Small Business Server | B2: =COUNTIFS(#REF!,'Sales Campaign Overview'!$A2,#REF!,"open") -> #REF! | C2: =SUMIFS(#REF!,#REF!,'Sales Campaign Overview'!$A2,#REF!,"open") -> #REF! | D2: =COUNTIFS(#REF!,'Sales Campaign Overview'!$A2,#REF!,"open",#REF!,"1") -> #REF! | E2: =SUMIFS(#REF!,#REF!,'Sales Campaign Overview'!$A2,#REF!,"open",#REF!,"1") -> #REF! | F2: =COUNTIFS(#REF!,'Sales Campaign Overview'!$A2,#REF!,"open",#REF!,"2") -> #REF! | G2: =SUMIFS(#REF!,#REF!,'Sales Campaign Overview'!$A2,#REF!,"open",#REF!,"2") -> #REF! | H2: =COUNTIFS(#REF!,'Sales Campaign Overview'!$A2,#REF!,"open",#REF!,"3") -> #REF! | I2: =SUMIFS(#REF!,#REF!,'Sales Campaign Overview'!$A2,#REF!,"open",#REF!,"3") -> #REF! | J2: =COUNTIFS(#REF!,'Sales Campaign Overview'!$A2,#REF!,"open",#REF!,"4") -> #REF! | K2: =SUMIFS(#REF!,#REF!,'Sales Campaign Overview'!$A2,#REF!,"open",#REF!,"4") -> #REF! | L2: =COUNTIFS(#REF!,'Sales Campaign Overview'!$A2,#REF!,"open",#REF!,"5") -> #REF! | M2: =SUMIFS(#REF!,#REF!,'Sales Campaign Overview'!$A2,#REF!,"open",#REF!,"5") -> #REF! | N2: =COUNTIFS(#REF!,'Sales Campaign Overview'!$A2,#REF!,"open",#REF!,"6") -> #REF! | O2: =SUMIFS(#REF!,#REF!,'Sales Campaign Overview'!$A2,#REF!,"open",#REF!,"6") -> #REF! | P2: =COUNTIFS(#REF!,'Sales Campaign Overview'!$A2,#REF!,"open",#REF!,"7") -> #REF! | Q2: =SUMIFS(#REF!,#REF!,'Sales Campaign Overview'!$A2,#REF!,"open",#REF!,"7") -> #REF! | R2: =COUNTIFS(#REF!,'Sales Campaign Overview'!$A2,#REF!,"open",#REF!,"8") -> #REF! | S2: =SUMIFS(#REF!,#REF!,'Sales Campaign Overview'!$A2,#REF!,"open",#REF!,"8") -> #REF! | T2: =COUNTIFS(#REF!,'Sales Campaign Overview'!$A2,#REF!,"open",#REF!,"9") -> #REF! | U2: =SUMIFS(#REF!,#REF!,'Sales Campaign Overview'!$A2,#REF!,"open",#REF!,"9") -> #REF! | V2: =COUNTIFS(#REF!,'Sales Campaign Overview'!$A2,#REF!,"open",#REF!,"10") -> #REF! | W2: =SUMIFS(#REF!,#REF!,'Sales Campaign Overview'!$A2,#REF!,"open",#REF!,"10") -> #REF! | X2: =COUNTIFS(#REF!,'Sales Campaign Overview'!$A2,#REF!,"open",#REF!,"11") -> #REF! | Y2: =SUMIFS(#REF!,#REF!,'Sales Campaign Overview'!$A2,#REF!,"open",#REF!,"11") -> #REF! | Z2: =COUNTIFS(#REF!,'Sales Campaign Overview'!$A2,#REF!,"open",#REF!,"12") -> #REF! | AA2: =SUMIFS(#REF!,#REF!,'Sales Campaign Overview'!$A2,#REF!,"open",#REF!,"12") -> #REF!
A3: POTS - Aerohive Renewal | B3: =COUNTIFS(#REF!,'Sales Campaign Overview'!$A3,#REF!,"open") -> #REF! | C3: =SUMIFS(#REF!,#REF!,'Sales Campaign Overview'!$A3,#REF!,"open") -> #REF! | D3: =COUNTIFS(#REF!,'Sales Campaign Overview'!$A3,#REF!,"open",#REF!,"1") -> #REF! | E3: =SUMIFS(#REF!,#REF!,'Sales Campaign Overview'!$A3,#REF!,"open",#REF!,"1") -> #REF! | F3: =COUNTIFS(#REF!,'Sales Campaign Overview'!$A3,#REF!,"open",#REF!,"2") -> #REF! | G3: =SUMIFS(#REF!,#REF!,'Sales Campaign Overview'!$A3,#REF!,"open",#REF!,"2") -> #REF! | H3: =COUNTIFS(#REF!,'Sales Campaign Overview'!$A3,#REF!,"open",#REF!,"3") -> #REF! | I3: =SUMIFS(#REF!,#REF!,'Sales Campaign Overview'!$A3,#REF!,"open",#REF!,"3") -> #REF! | J3: =COUNTIFS(#REF!,'Sales Campaign Overview'!$A3,#REF!,"open",#REF!,"4") -> #REF! | K3: =SUMIFS(#REF!,#REF!,'Sales Campaign Overview'!$A3,#REF!,"open",#REF!,"4") -> #REF! | L3: =COUNTIFS(#REF!,'Sales Campaign Overview'!$A3,#REF!,"open",#REF!,"5") -> #REF! | M3: =SUMIFS(#REF!,#REF!,'Sales Campaign Overview'!$A3,#REF!,"open",#REF!,"5") -> #REF! | N3: =COUNTIFS(#REF!,'Sales Campaign Overview'!$A3,#REF!,"open",#REF!,"6") -> #REF! | O3: =SUMIFS(#REF!,#REF!,'Sales Campaign Overview'!$A3,#REF!,"open",#REF!,"6") -> #REF! | P3: =COUNTIFS(#REF!,'Sales Campaign Overview'!$A3,#REF!,"open",#REF!,"7") -> #REF! | Q3: =SUMIFS(#REF!,#REF!,'Sales Campaign Overview'!$A3,#REF!,"open",#REF!,"7") -> #REF! | R3: =COUNTIFS(#REF!,'Sales Campaign Overview'!$A3,#REF!,"open",#REF!,"8") -> #REF! | S3: =SUMIFS(#REF!,#REF!,'Sales Campaign Overview'!$A3,#REF!,"open",#REF!,"8") -> #REF! | T3: =COUNTIFS(#REF!,'Sales Campaign Overview'!$A3,#REF!,"open",#REF!,"9") -> #REF! | U3: =SUMIFS(#REF!,#REF!,'Sales Campaign Overview'!$A3,#REF!,"open",#REF!,"9") -> #REF! | V3: =COUNTIFS(#REF!,'Sales Campaign Overview'!$A3,#REF!,"open",#REF!,"10") -> #REF! | W3: =SUMIFS(#REF!,#REF!,'Sales Campaign Overview'!$A3,#REF!,"open",#REF!,"10") -> #REF! | X3: =COUNTIFS(#REF!,'Sales Campaign Overview'!$A3,#REF!,"open",#REF!,"11") -> #REF! | Y3: =SUMIFS(#REF!,#REF!,'Sales Campaign Overview'!$A3,#REF!,"open",#REF!,"11") -> #REF! | Z3: =COUNTIFS(#REF!,'Sales Campaign Overview'!$A3,#REF!,"open",#REF!,"12") -> #REF! | AA3: =SUMIFS(#REF!,#REF!,'Sales Campaign Overview'!$A3,#REF!,"open",#REF!,"12") -> #REF!
A4: POTS - MSFT License Migration | B4: =COUNTIFS(#REF!,'Sales Campaign Overview'!$A4,#REF!,"open") -> #REF! | C4: =SUMIFS(#REF!,#REF!,'Sales Campaign Overview'!$A4,#REF!,"open") -> #REF! | D4: =COUNTIFS(#REF!,'Sales Campaign Overview'!$A4,#REF!,"open",#REF!,"1") -> #REF! | E4: =SUMIFS(#REF!,#REF!,'Sales Campaign Overview'!$A4,#REF!,"open",#REF!,"1") -> #REF! | F4: =COUNTIFS(#REF!,'Sales Campaign Overview'!$A4,#REF!,"open",#REF!,"2") -> #REF! | G4: =SUMIFS(#REF!,#REF!,'Sales Campaign Overview'!$A4,#REF!,"open",#REF!,"2") -> #REF! | H4: =COUNTIFS(#REF!,'Sales Campaign Overview'!$A4,#REF!,"open",#REF!,"3") -> #REF! | I4: =SUMIFS(#REF!,#REF!,'Sales Campaign Overview'!$A4,#REF!,"open",#REF!,"3") -> #REF! | J4: =COUNTIFS(#REF!,'Sales Campaign Overview'!$A4,#REF!,"open",#REF!,"4") -> #REF! | K4: =SUMIFS(#REF!,#REF!,'Sales Campaign Overview'!$A4,#REF!,"open",#REF!,"4") -> #REF! | L4: =COUNTIFS(#REF!,'Sales Campaign Overview'!$A4,#REF!,"open",#REF!,"5") -> #REF! | M4: =SUMIFS(#REF!,#REF!,'Sales Campaign Overview'!$A4,#REF!,"open",#REF!,"5") -> #REF! | N4: =COUNTIFS(#REF!,'Sales Campaign Overview'!$A4,#REF!,"open",#REF!,"6") -> #REF! | O4: =SUMIFS(#REF!,#REF!,'Sales Campaign Overview'!$A4,#REF!,"open",#REF!,"6") -> #REF! | P4: =COUNTIFS(#REF!,'Sales Campaign Overview'!$A4,#REF!,"open",#REF!,"7") -> #REF! | Q4: =SUMIFS(#REF!,#REF!,'Sales Campaign Overview'!$A4,#REF!,"open",#REF!,"7") -> #REF! | R4: =COUNTIFS(#REF!,'Sales Campaign Overview'!$A4,#REF!,"open",#REF!,"8") -> #REF! | S4: =SUMIFS(#REF!,#REF!,'Sales Campaign Overview'!$A4,#REF!,"open",#REF!,"8") -> #REF! | T4: =COUNTIFS(#REF!,'Sales Campaign Overview'!$A4,#REF!,"open",#REF!,"9") -> #REF! | U4: =SUMIFS(#REF!,#REF!,'Sales Campaign Overview'!$A4,#REF!,"open",#REF!,"9") -> #REF! | V4: =COUNTIFS(#REF!,'Sales Campaign Overview'!$A4,#REF!,"open",#REF!,"10") -> #REF! | W4: =SUMIFS(#REF!,#REF!,'Sales Campaign Overview'!$A4,#REF!,"open",#REF!,"10") -> #REF! | X4: =COUNTIFS(#REF!,'Sales Campaign Overview'!$A4,#REF!,"open",#REF!,"11") -> #REF! | Y4: =SUMIFS(#REF!,#REF!,'Sales Campaign Overview'!$A4,#REF!,"open",#REF!,"11") -> #REF! | Z4: =COUNTIFS(#REF!,'Sales Campaign Overview'!$A4,#REF!,"open",#REF!,"12") -> #REF! | AA4: =SUMIFS(#REF!,#REF!,'Sales Campaign Overview'!$A4,#REF!,"open",#REF!,"12") -> #REF!
A5: POTS - PC Refresh 2019 | B5: =COUNTIFS(#REF!,'Sales Campaign Overview'!$A5,#REF!,"open") -> #REF! | C5: =SUMIFS(#REF!,#REF!,'Sales Campaign Overview'!$A5,#REF!,"open") -> #REF! | D5: =COUNTIFS(#REF!,'Sales Campaign Overview'!$A5,#REF!,"open",#REF!,"1") -> #REF! | E5: =SUMIFS(#REF!,#REF!,'Sales Campaign Overview'!$A5,#REF!,"open",#REF!,"1") -> #REF! | F5: =COUNTIFS(#REF!,'Sales Campaign Overview'!$A5,#REF!,"open",#REF!,"2") -> #REF! | G5: =SUMIFS(#REF!,#REF!,'Sales Campaign Overview'!$A5,#REF!,"open",#REF!,"2") -> #REF! | H5: =COUNTIFS(#REF!,'Sales Campaign Overview'!$A5,#REF!,"open",#REF!,"3") -> #REF! | I5: =SUMIFS(#REF!,#REF!,'Sales Campaign Overview'!$A5,#REF!,"open",#REF!,"3") -> #REF! | J5: =COUNTIFS(#REF!,'Sales Campaign Overview'!$A5,#REF!,"open",#REF!,"4") -> #REF! | K5: =SUMIFS(#REF!,#REF!,'Sales Campaign Overview'!$A5,#REF!,"open",#REF!,"4") -> #REF! | L5: =COUNTIFS(#REF!,'Sales Campaign Overview'!$A5,#REF!,"open",#REF!,"5") -> #REF! | M5: =SUMIFS(#REF!,#REF!,'Sales Campaign Overview'!$A5,#REF!,"open",#REF!,"5") -> #REF! | N5: =COUNTIFS(#REF!,'Sales Campaign Overview'!$A5,#REF!,"open",#REF!,"6") -> #REF! | O5: =SUMIFS(#REF!,#REF!,'Sales Campaign Overview'!$A5,#REF!,"open",#REF!,"6") -> #REF! | P5: =COUNTIFS(#REF!,'Sales Campaign Overview'!$A5,#REF!,"open",#REF!,"7") -> #REF! | Q5: =SUMIFS(#REF!,#REF!,'Sales Campaign Overview'!$A5,#REF!,"open",#REF!,"7") -> #REF! | R5: =COUNTIFS(#REF!,'Sales Campaign Overview'!$A5,#REF!,"open",#REF!,"8") -> #REF! | S5: =SUMIFS(#REF!,#REF!,'Sales Campaign Overview'!$A5,#REF!,"open",#REF!,"8") -> #REF! | T5: =COUNTIFS(#REF!,'Sales Campaign Overview'!$A5,#REF!,"open",#REF!,"9") -> #REF! | U5: =SUMIFS(#REF!,#REF!,'Sales Campaign Overview'!$A5,#REF!,"open",#REF!,"9") -> #REF! | V5: =COUNTIFS(#REF!,'Sales Campaign Overview'!$A5,#REF!,"open",#REF!,"10") -> #REF! | W5: =SUMIFS(#REF!,#REF!,'Sales Campaign Overview'!$A5,#REF!,"open",#REF!,"10") -> #REF! | X5: =COUNTIFS(#REF!,'Sales Campaign Overview'!$A5,#REF!,"open",#REF!,"11") -> #REF! | Y5: =SUMIFS(#REF!,#REF!,'Sales Campaign Overview'!$A5,#REF!,"open",#REF!,"11") -> #REF! | Z5: =COUNTIFS(#REF!,'Sales Campaign Overview'!$A5,#REF!,"open",#REF!,"12") -> #REF! | AA5: =SUMIFS(#REF!,#REF!,'Sales Campaign Overview'!$A5,#REF!,"open",#REF!,"12") -> #REF!
A6: POTS - Server 2008 EOL | B6: =COUNTIFS(#REF!,'Sales Campaign Overview'!$A6,#REF!,"open") -> #REF! | C6: =SUMIFS(#REF!,#REF!,'Sales Campaign Overview'!$A6,#REF!,"open") -> #REF! | D6: =COUNTIFS(#REF!,'Sales Campaign Overview'!$A6,#REF!,"open",#REF!,"1") -> #REF! | E6: =SUMIFS(#REF!,#REF!,'Sales Campaign Overview'!$A6,#REF!,"open",#REF!,"1") -> #REF! | F6: =COUNTIFS(#REF!,'Sales Campaign Overview'!$A6,#REF!,"open",#REF!,"2") -> #REF! | G6: =SUMIFS(#REF!,#REF!,'Sales Campaign Overview'!$A6,#REF!,"open",#REF!,"2") -> #REF! | H6: =COUNTIFS(#REF!,'Sales Campaign Overview'!$A6,#REF!,"open",#REF!,"3") -> #REF! | I6: =SUMIFS(#REF!,#REF!,'Sales Campaign Overview'!$A6,#REF!,"open",#REF!,"3") -> #REF! | J6: =COUNTIFS(#REF!,'Sales Campaign Overview'!$A6,#REF!,"open",#REF!,"4") -> #REF! | K6: =SUMIFS(#REF!,#REF!,'Sales Campaign Overview'!$A6,#REF!,"open",#REF!,"4") -> #REF! | L6: =COUNTIFS(#REF!,'Sales Campaign Overview'!$A6,#REF!,"open",#REF!,"5") -> #REF! | M6: =SUMIFS(#REF!,#REF!,'Sales Campaign Overview'!$A6,#REF!,"open",#REF!,"5") -> #REF! | N6: =COUNTIFS(#REF!,'Sales Campaign Overview'!$A6,#REF!,"open",#REF!,"6") -> #REF! | O6: =SUMIFS(#REF!,#REF!,'Sales Campaign Overview'!$A6,#REF!,"open",#REF!,"6") -> #REF! | P6: =COUNTIFS(#REF!,'Sales Campaign Overview'!$A6,#REF!,"open",#REF!,"7") -> #REF! | Q6: =SUMIFS(#REF!,#REF!,'Sales Campaign Overview'!$A6,#REF!,"open",#REF!,"7") -> #REF! | R6: =COUNTIFS(#REF!,'Sales Campaign Overview'!$A6,#REF!,"open",#REF!,"8") -> #REF! | S6: =SUMIFS(#REF!,#REF!,'Sales Campaign Overview'!$A6,#REF!,"open",#REF!,"8") -> #REF! | T6: =COUNTIFS(#REF!,'Sales Campaign Overview'!$A6,#REF!,"open",#REF!,"9") -> #REF! | U6: =SUMIFS(#REF!,#REF!,'Sales Campaign Overview'!$A6,#REF!,"open",#REF!,"9") -> #REF! | V6: =COUNTIFS(#REF!,'Sales Campaign Overview'!$A6,#REF!,"open",#REF!,"10") -> #REF! | W6: =SUMIFS(#REF!,#REF!,'Sales Campaign Overview'!$A6,#REF!,"open",#REF!,"10") -> #REF! | X6: =COUNTIFS(#REF!,'Sales Campaign Overview'!$A6,#REF!,"open",#REF!,"11") -> #REF! | Y6: =SUMIFS(#REF!,#REF!,'Sales Campaign Overview'!$A6,#REF!,"open",#REF!,"11") -> #REF! | Z6: =COUNTIFS(#REF!,'Sales Campaign Overview'!$A6,#REF!,"open",#REF!,"12") -> #REF! | AA6: =SUMIFS(#REF!,#REF!,'Sales Campaign Overview'!$A6,#REF!,"open",#REF!,"12") -> #REF!
A7: POTS - Server Renewal | B7: =COUNTIFS(#REF!,'Sales Campaign Overview'!$A7,#REF!,"open") -> #REF! | C7: =SUMIFS(#REF!,#REF!,'Sales Campaign Overview'!$A7,#REF!,"open") -> #REF! | D7: =COUNTIFS(#REF!,'Sales Campaign Overview'!$A7,#REF!,"open",#REF!,"1") -> #REF! | E7: =SUMIFS(#REF!,#REF!,'Sales Campaign Overview'!$A7,#REF!,"open",#REF!,"1") -> #REF! | F7: =COUNTIFS(#REF!,'Sales Campaign Overview'!#REF!,#REF!,"open",#REF!,"2") -> #REF! | G7: =SUMIFS(#REF!,#REF!,'Sales Campaign Overview'!$A7,#REF!,"open",#REF!,"2") -> #REF! | H7: =COUNTIFS(#REF!,'Sales Campaign Overview'!$A7,#REF!,"open",#REF!,"3") -> #REF! | I7: =SUMIFS(#REF!,#REF!,'Sales Campaign Overview'!$A7,#REF!,"open",#REF!,"3") -> #REF! | J7: =COUNTIFS(#REF!,'Sales Campaign Overview'!$A7,#REF!,"open",#REF!,"4") -> #REF! | K7: =SUMIFS(#REF!,#REF!,'Sales Campaign Overview'!$A7,#REF!,"open",#REF!,"4") -> #REF! | L7: =COUNTIFS(#REF!,'Sales Campaign Overview'!$A7,#REF!,"open",#REF!,"5") -> #REF! | M7: =SUMIFS(#REF!,#REF!,'Sales Campaign Overview'!$A7,#REF!,"open",#REF!,"5") -> #REF! | N7: =COUNTIFS(#REF!,'Sales Campaign Overview'!$A7,#REF!,"open",#REF!,"6") -> #REF! | O7: =SUMIFS(#REF!,#REF!,'Sales Campaign Overview'!$A7,#REF!,"open",#REF!,"6") -> #REF! | P7: =COUNTIFS(#REF!,'Sales Campaign Overview'!$A7,#REF!,"open",#REF!,"7") -> #REF! | Q7: =SUMIFS(#REF!,#REF!,'Sales Campaign Overview'!$A7,#REF!,"open",#REF!,"7") -> #REF! | R7: =COUNTIFS(#REF!,'Sales Campaign Overview'!$A7,#REF!,"open",#REF!,"8") -> #REF! | S7: =SUMIFS(#REF!,#REF!,'Sales Campaign Overview'!$A7,#REF!,"open",#REF!,"8") -> #REF! | T7: =COUNTIFS(#REF!,'Sales Campaign Overview'!$A7,#REF!,"open",#REF!,"9") -> #REF! | U7: =SUMIFS(#REF!,#REF!,'Sales Campaign Overview'!$A7,#REF!,"open",#REF!,"9") -> #REF! | V7: =COUNTIFS(#REF!,'Sales Campaign Overview'!$A7,#REF!,"open",#REF!,"10") -> #REF! | W7: =SUMIFS(#REF!,#REF!,'Sales Campaign Overview'!$A7,#REF!,"open",#REF!,"10") -> #REF! | X7: =COUNTIFS(#REF!,'Sales Campaign Overview'!$A7,#REF!,"open",#REF!,"11") -> #REF! | Y7: =SUMIFS(#REF!,#REF!,'Sales Campaign Overview'!$A7,#REF!,"open",#REF!,"11") -> #REF! | Z7: =COUNTIFS(#REF!,'Sales Campaign Overview'!$A7,#REF!,"open",#REF!,"12") -> #REF! | AA7: =SUMIFS(#REF!,#REF!,'Sales Campaign Overview'!$A7,#REF!,"open",#REF!,"12") -> #REF!
A8: POTS - Sonicwall Renewal | B8: =COUNTIFS(#REF!,'Sales Campaign Overview'!$A8,#REF!,"open") -> #REF! | C8: =SUMIFS(#REF!,#REF!,'Sales Campaign Overview'!$A8,#REF!,"open") -> #REF! | D8: =COUNTIFS(#REF!,'Sales Campaign Overview'!$A8,#REF!,"open",#REF!,"1") -> #REF! | E8: =SUMIFS(#REF!,#REF!,'Sales Campaign Overview'!$A8,#REF!,"open",#REF!,"1") -> #REF! | F8: =COUNTIFS(#REF!,'Sales Campaign Overview'!$A8,#REF!,"open",#REF!,"2") -> #REF! | G8: =SUMIFS(#REF!,#REF!,'Sales Campaign Overview'!$A8,#REF!,"open",#REF!,"2") -> #REF! | H8: =COUNTIFS(#REF!,'Sales Campaign Overview'!$A8,#REF!,"open",#REF!,"3") -> #REF! | I8: =SUMIFS(#REF!,#REF!,'Sales Campaign Overview'!$A8,#REF!,"open",#REF!,"3") -> #REF! | J8: =COUNTIFS(#REF!,'Sales Campaign Overview'!$A8,#REF!,"open",#REF!,"4") -> #REF! | K8: =SUMIFS(#REF!,#REF!,'Sales Campaign Overview'!$A8,#REF!,"open",#REF!,"4") -> #REF! | L8: =COUNTIFS(#REF!,'Sales Campaign Overview'!$A8,#REF!,"open",#REF!,"5") -> #REF! | M8: =SUMIFS(#REF!,#REF!,'Sales Campaign Overview'!$A8,#REF!,"open",#REF!,"5") -> #REF! | N8: =COUNTIFS(#REF!,'Sales Campaign Overview'!$A8,#REF!,"open",#REF!,"6") -> #REF! | O8: =SUMIFS(#REF!,#REF!,'Sales Campaign Overview'!$A8,#REF!,"open",#REF!,"6") -> #REF! | P8: =COUNTIFS(#REF!,'Sales Campaign Overview'!$A8,#REF!,"open",#REF!,"7") -> #REF! | Q8: =SUMIFS(#REF!,#REF!,'Sales Campaign Overview'!$A8,#REF!,"open",#REF!,"7") -> #REF! | R8: =COUNTIFS(#REF!,'Sales Campaign Overview'!$A8,#REF!,"open",#REF!,"8") -> #REF! | S8: =SUMIFS(#REF!,#REF!,'Sales Campaign Overview'!$A8,#REF!,"open",#REF!,"8") -> #REF! | T8: =COUNTIFS(#REF!,'Sales Campaign Overview'!$A8,#REF!,"open",#REF!,"9") -> #REF! | U8: =SUMIFS(#REF!,#REF!,'Sales Campaign Overview'!$A8,#REF!,"open",#REF!,"9") -> #REF! | V8: =COUNTIFS(#REF!,'Sales Campaign Overview'!$A8,#REF!,"open",#REF!,"10") -> #REF! | W8: =SUMIFS(#REF!,#REF!,'Sales Campaign Overview'!$A8,#REF!,"open",#REF!,"10") -> #REF! | X8: =COUNTIFS(#REF!,'Sales Campaign Overview'!$A8,#REF!,"open",#REF!,"11") -> #REF! | Y8: =SUMIFS(#REF!,#REF!,'Sales Campaign Overview'!$A8,#REF!,"open",#REF!,"11") -> #REF! | Z8: =COUNTIFS(#REF!,'Sales Campaign Overview'!$A8,#REF!,"open",#REF!,"12") -> #REF! | AA8: =SUMIFS(#REF!,#REF!,'Sales Campaign Overview'!$A8,#REF!,"open",#REF!,"12") -> #REF!
A9: POTS - VoIP Migration | B9: =COUNTIFS(#REF!,'Sales Campaign Overview'!$A9,#REF!,"open") -> #REF! | C9: =SUMIFS(#REF!,#REF!,'Sales Campaign Overview'!$A9,#REF!,"open") -> #REF! | D9: =COUNTIFS(#REF!,'Sales Campaign Overview'!$A9,#REF!,"open",#REF!,"1") -> #REF! | E9: =SUMIFS(#REF!,#REF!,'Sales Campaign Overview'!$A9,#REF!,"open",#REF!,"1") -> #REF! | F9: =COUNTIFS(#REF!,'Sales Campaign Overview'!$A9,#REF!,"open",#REF!,"2") -> #REF! | G9: =SUMIFS(#REF!,#REF!,'Sales Campaign Overview'!$A9,#REF!,"open",#REF!,"2") -> #REF! | H9: =COUNTIFS(#REF!,'Sales Campaign Overview'!$A9,#REF!,"open",#REF!,"3") -> #REF! | I9: =SUMIFS(#REF!,#REF!,'Sales Campaign Overview'!$A9,#REF!,"open",#REF!,"3") -> #REF! | J9: =COUNTIFS(#REF!,'Sales Campaign Overview'!$A9,#REF!,"open",#REF!,"4") -> #REF! | K9: =SUMIFS(#REF!,#REF!,'Sales Campaign Overview'!$A9,#REF!,"open",#REF!,"4") -> #REF! | L9: =COUNTIFS(#REF!,'Sales Campaign Overview'!$A9,#REF!,"open",#REF!,"5") -> #REF! | M9: =SUMIFS(#REF!,#REF!,'Sales Campaign Overview'!$A9,#REF!,"open",#REF!,"5") -> #REF! | N9: =COUNTIFS(#REF!,'Sales Campaign Overview'!$A9,#REF!,"open",#REF!,"6") -> #REF! | O9: =SUMIFS(#REF!,#REF!,'Sales Campaign Overview'!$A9,#REF!,"open",#REF!,"6") -> #REF! | P9: =COUNTIFS(#REF!,'Sales Campaign Overview'!$A9,#REF!,"open",#REF!,"7") -> #REF! | Q9: =SUMIFS(#REF!,#REF!,'Sales Campaign Overview'!$A9,#REF!,"open",#REF!,"7") -> #REF! | R9: =COUNTIFS(#REF!,'Sales Campaign Overview'!$A9,#REF!,"open",#REF!,"8") -> #REF! | S9: =SUMIFS(#REF!,#REF!,'Sales Campaign Overview'!$A9,#REF!,"open",#REF!,"8") -> #REF! | T9: =COUNTIFS(#REF!,'Sales Campaign Overview'!$A9,#REF!,"open",#REF!,"9") -> #REF! | U9: =SUMIFS(#REF!,#REF!,'Sales Campaign Overview'!$A9,#REF!,"open",#REF!,"9") -> #REF! | V9: =COUNTIFS(#REF!,'Sales Campaign Overview'!$A9,#REF!,"open",#REF!,"10") -> #REF! | W9: =SUMIFS(#REF!,#REF!,'Sales Campaign Overview'!$A9,#REF!,"open",#REF!,"10") -> #REF! | X9: =COUNTIFS(#REF!,'Sales Campaign Overview'!$A9,#REF!,"open",#REF!,"11") -> #REF! | Y9: =SUMIFS(#REF!,#REF!,'Sales Campaign Overview'!$A9,#REF!,"open",#REF!,"11") -> #REF! | Z9: =COUNTIFS(#REF!,'Sales Campaign Overview'!$A9,#REF!,"open",#REF!,"12") -> #REF! | AA9: =SUMIFS(#REF!,#REF!,'Sales Campaign Overview'!$A9,#REF!,"open",#REF!,"12") -> #REF!
A10: POTS-Server Replacement | B10: =COUNTIFS(#REF!,'Sales Campaign Overview'!$A10,#REF!,"open") -> #REF! | C10: =SUMIFS(#REF!,#REF!,'Sales Campaign Overview'!$A10,#REF!,"open") -> #REF! | D10: =COUNTIFS(#REF!,'Sales Campaign Overview'!$A10,#REF!,"open",#REF!,"1") -> #REF! | E10: =SUMIFS(#REF!,#REF!,'Sales Campaign Overview'!$A10,#REF!,"open",#REF!,"1") -> #REF! | F10: =COUNTIFS(#REF!,'Sales Campaign Overview'!$A10,#REF!,"open",#REF!,"2") -> #REF! | G10: =SUMIFS(#REF!,#REF!,'Sales Campaign Overview'!$A10,#REF!,"open",#REF!,"2") -> #REF! | H10: =COUNTIFS(#REF!,'Sales Campaign Overview'!$A10,#REF!,"open",#REF!,"3") -> #REF! | I10: =SUMIFS(#REF!,#REF!,'Sales Campaign Overview'!$A10,#REF!,"open",#REF!,"3") -> #REF! | J10: =COUNTIFS(#REF!,'Sales Campaign Overview'!$A10,#REF!,"open",#REF!,"4") -> #REF! | K10: =SUMIFS(#REF!,#REF!,'Sales Campaign Overview'!$A10,#REF!,"open",#REF!,"4") -> #REF! | L10: =COUNTIFS(#REF!,'Sales Campaign Overview'!$A10,#REF!,"open",#REF!,"5") -> #REF! | M10: =SUMIFS(#REF!,#REF!,'Sales Campaign Overview'!$A10,#REF!,"open",#REF!,"5") -> #REF! | N10: =COUNTIFS(#REF!,'Sales Campaign Overview'!$A10,#REF!,"open",#REF!,"6") -> #REF! | O10: =SUMIFS(#REF!,#REF!,'Sales Campaign Overview'!$A10,#REF!,"open",#REF!,"6") -> #REF! | P10: =COUNTIFS(#REF!,'Sales Campaign Overview'!$A10,#REF!,"open",#REF!,"7") -> #REF! | Q10: =SUMIFS(#REF!,#REF!,'Sales Campaign Overview'!$A10,#REF!,"open",#REF!,"7") -> #REF! | R10: =COUNTIFS(#REF!,'Sales Campaign Overview'!$A10,#REF!,"open",#REF!,"8") -> #REF! | S10: =SUMIFS(#REF!,#REF!,'Sales Campaign Overview'!$A10,#REF!,"open",#REF!,"8") -> #REF! | T10: =COUNTIFS(#REF!,'Sales Campaign Overview'!$A10,#REF!,"open",#REF!,"9") -> #REF! | U10: =SUMIFS(#REF!,#REF!,'Sales Campaign Overview'!$A10,#REF!,"open",#REF!,"9") -> #REF! | V10: =COUNTIFS(#REF!,'Sales Campaign Overview'!$A10,#REF!,"open",#REF!,"10") -> #REF! | W10: =SUMIFS(#REF!,#REF!,'Sales Campaign Overview'!$A10,#REF!,"open",#REF!,"10") -> #REF! | X10: =COUNTIFS(#REF!,'Sales Campaign Overview'!$A10,#REF!,"open",#REF!,"11") -> #REF! | Y10: =SUMIFS(#REF!,#REF!,'Sales Campaign Overview'!$A10,#REF!,"open",#REF!,"11") -> #REF! | Z10: =COUNTIFS(#REF!,'Sales Campaign Overview'!$A10,#REF!,"open",#REF!,"12") -> #REF! | AA10: =SUMIFS(#REF!,#REF!,'Sales Campaign Overview'!$A10,#REF!,"open",#REF!,"12") -> #REF!
A11: POTS-SSL Renewal | B11: =COUNTIFS(#REF!,'Sales Campaign Overview'!$A11,#REF!,"open") -> #REF! | C11: =SUMIFS(#REF!,#REF!,'Sales Campaign Overview'!$A11,#REF!,"open") -> #REF! | D11: =COUNTIFS(#REF!,'Sales Campaign Overview'!$A11,#REF!,"open",#REF!,"1") -> #REF! | E11: =SUMIFS(#REF!,#REF!,'Sales Campaign Overview'!$A11,#REF!,"open",#REF!,"1") -> #REF! | F11: =COUNTIFS(#REF!,'Sales Campaign Overview'!$A11,#REF!,"open",#REF!,"2") -> #REF! | G11: =SUMIFS(#REF!,#REF!,'Sales Campaign Overview'!$A11,#REF!,"open",#REF!,"2") -> #REF! | H11: =COUNTIFS(#REF!,'Sales Campaign Overview'!$A11,#REF!,"open",#REF!,"3") -> #REF! | I11: =SUMIFS(#REF!,#REF!,'Sales Campaign Overview'!$A11,#REF!,"open",#REF!,"3") -> #REF! | J11: =COUNTIFS(#REF!,'Sales Campaign Overview'!$A11,#REF!,"open",#REF!,"4") -> #REF! | K11: =SUMIFS(#REF!,#REF!,'Sales Campaign Overview'!$A11,#REF!,"open",#REF!,"4") -> #REF! | L11: =COUNTIFS(#REF!,'Sales Campaign Overview'!$A11,#REF!,"open",#REF!,"5") -> #REF! | M11: =SUMIFS(#REF!,#REF!,'Sales Campaign Overview'!$A11,#REF!,"open",#REF!,"5") -> #REF! | N11: =COUNTIFS(#REF!,'Sales Campaign Overview'!$A11,#REF!,"open",#REF!,"6") -> #REF! | O11: =SUMIFS(#REF!,#REF!,'Sales Campaign Overview'!$A11,#REF!,"open",#REF!,"6") -> #REF! | P11: =COUNTIFS(#REF!,'Sales Campaign Overview'!$A11,#REF!,"open",#REF!,"7") -> #REF! | Q11: =SUMIFS(#REF!,#REF!,'Sales Campaign Overview'!$A11,#REF!,"open",#REF!,"7") -> #REF! | R11: =COUNTIFS(#REF!,'Sales Campaign Overview'!$A11,#REF!,"open",#REF!,"8") -> #REF! | S11: =SUMIFS(#REF!,#REF!,'Sales Campaign Overview'!$A11,#REF!,"open",#REF!,"8") -> #REF! | T11: =COUNTIFS(#REF!,'Sales Campaign Overview'!$A11,#REF!,"open",#REF!,"9") -> #REF! | U11: =SUMIFS(#REF!,#REF!,'Sales Campaign Overview'!$A11,#REF!,"open",#REF!,"9") -> #REF! | V11: =COUNTIFS(#REF!,'Sales Campaign Overview'!$A11,#REF!,"open",#REF!,"10") -> #REF! | W11: =SUMIFS(#REF!,#REF!,'Sales Campaign Overview'!$A11,#REF!,"open",#REF!,"10") -> #REF! | X11: =COUNTIFS(#REF!,'Sales Campaign Overview'!$A11,#REF!,"open",#REF!,"11") -> #REF! | Y11: =SUMIFS(#REF!,#REF!,'Sales Campaign Overview'!$A11,#REF!,"open",#REF!,"11") -> #REF! | Z11: =COUNTIFS(#REF!,'Sales Campaign Overview'!$A11,#REF!,"open",#REF!,"12") -> #REF! | AA11: =SUMIFS(#REF!,#REF!,'Sales Campaign Overview'!$A11,#REF!,"open",#REF!,"12") -> #REF!
A12: Total | B12: =SUM(B2+B3+B4+B5+B6+B7+B8+B9+B10+B11) -> #REF! | C12: =SUM(C2+C3+C4+C5+C6+C7+C8+C9+C10+C11) -> #REF! | D12: =SUM(D2+D3+D4+D5+D6+D7+D8+D9+D10+D11) -> #REF! | E12: =SUM(E2+E3+E4+E5+E6+E7+E8+E9+E10+E11) -> #REF! | F12: =SUM(F2:F11) -> #REF! | G12: =SUM(G2+G3+G4+G5+G6+G7+G8+G9+G10+G11) -> #REF! | H12: =SUM(H2+H3+H4+H5+H6+H7+H8+H9+H10+H11) -> #REF! | I12: =SUM(I2+I3+I4+I5+I6+I7+I8+I9+I10+I11) -> #REF! | J12: =SUM(J2+J3+J4+J5+J6+J7+J8+J9+J10+J11) -> #REF! | K12: =SUM(K2+K3+K4+K5+K6+K7+K8+K9+K10+K11) -> #REF! | L12: =SUM(L2+L3+L4+L5+L6+L7+L8+L9+L10+L11) -> #REF! | M12: =SUM(M2+M3+M4+M5+M6+M7+M8+M9+M10+M11) -> #REF! | N12: =SUM(N2+N3+N4+N5+N6+N7+N8+N9+N10+N11) -> #REF! | ... AA12: =SUM(AA2+AA3+AA4+AA5+AA6+AA7+AA8+AA9+AA10+AA11) -> #REF!
A16: Sales Campaign Forecast | B16: Total | D16: January | F16: February | H16: March | J16: April | L16: May | N16: June | P16: July | R16: August | T16: September | V16: October | X16: November | Z16: December
A17: POTS - 2011 Small Business Server | B17: =COUNTIFS(#REF!,'Sales Campaign Overview'!$A17,#REF!,"won") -> #REF! | C17: =SUMIFS(#REF!,#REF!,'Sales Campaign Overview'!$A17,#REF!,"won") -> #REF! | D17: =COUNTIFS(#REF!,'Sales Campaign Overview'!$A17,#REF!,"won",#REF!,"1") -> #REF! | E17: =SUMIFS(#REF!,#REF!,'Sales Campaign Overview'!$A17,#REF!,"won",#REF!,"1") -> #REF! | F17: =COUNTIFS(#REF!,'Sales Campaign Overview'!$A17,#REF!,"won",#REF!,"2") -> #REF! | G17: =SUMIFS(#REF!,#REF!,'Sales Campaign Overview'!$A17,#REF!,"won",#REF!,"2") -> #REF! | H17: =COUNTIFS(#REF!,'Sales Campaign Overview'!$A17,#REF!,"won",#REF!,"3") -> #REF! | I17: =SUMIFS(#REF!,#REF!,'Sales Campaign Overview'!$A17,#REF!,"won",#REF!,"3") -> #REF! | J17: =COUNTIFS(#REF!,'Sales Campaign Overview'!$A17,#REF!,"won",#REF!,"4") -> #REF! | K17: =SUMIFS(#REF!,#REF!,'Sales Campaign Overview'!$A17,#REF!,"won",#REF!,"4") -> #REF! | L17: =COUNTIFS(#REF!,'Sales Campaign Overview'!$A17,#REF!,"won",#REF!,"5") -> #REF! | M17: =SUMIFS(#REF!,#REF!,'Sales Campaign Overview'!$A17,#REF!,"won",#REF!,"5") -> #REF! | N17: =COUNTIFS(#REF!,'Sales Campaign Overview'!$A17,#REF!,"won",#REF!,"6") -> #REF! | O17: =SUMIFS(#REF!,#REF!,'Sales Campaign Overview'!$A17,#REF!,"won",#REF!,"6") -> #REF! | P17: =COUNTIFS(#REF!,'Sales Campaign Overview'!$A17,#REF!,"won",#REF!,"7") -> #REF! | Q17: =SUMIFS(#REF!,#REF!,'Sales Campaign Overview'!$A17,#REF!,"won",#REF!,"7") -> #REF! | R17: =COUNTIFS(#REF!,'Sales Campaign Overview'!$A17,#REF!,"won",#REF!,"8") -> #REF! | S17: =SUMIFS(#REF!,#REF!,'Sales Campaign Overview'!$A17,#REF!,"won",#REF!,"8") -> #REF! | T17: =COUNTIFS(#REF!,'Sales Campaign Overview'!$A17,#REF!,"won",#REF!,"9") -> #REF! | U17: =SUMIFS(#REF!,#REF!,'Sales Campaign Overview'!$A17,#REF!,"won",#REF!,"9") -> #REF! | V17: =COUNTIFS(#REF!,'Sales Campaign Overview'!$A17,#REF!,"won",#REF!,"10") -> #REF! | W17: =SUMIFS(#REF!,#REF!,'Sales Campaign Overview'!$A17,#REF!,"won",#REF!,"10") -> #REF! | X17: =COUNTIFS(#REF!,'Sales Campaign Overview'!$A17,#REF!,"won",#REF!,"11") -> #REF! | Y17: =SUMIFS(#REF!,#REF!,'Sales Campaign Overview'!$A17,#REF!,"won",#REF!,"11") -> #REF! | Z17: =COUNTIFS(#REF!,'Sales Campaign Overview'!$A17,#REF!,"won",#REF!,"12") -> #REF! | AA17: =SUMIFS(#REF!,#REF!,'Sales Campaign Overview'!$A17,#REF!,"won",#REF!,"12") -> #REF!
A18: POTS - Aerohive Renewal | B18: =COUNTIFS(#REF!,'Sales Campaign Overview'!$A18,#REF!,"won") -> #REF! | C18: =SUMIFS(#REF!,#REF!,'Sales Campaign Overview'!$A18,#REF!,"won") -> #REF! | D18: =COUNTIFS(#REF!,'Sales Campaign Overview'!$A18,#REF!,"won",#REF!,"1") -> #REF! | E18: =SUMIFS(#REF!,#REF!,'Sales Campaign Overview'!$A18,#REF!,"won",#REF!,"1") -> #REF! | F18: =COUNTIFS(#REF!,'Sales Campaign Overview'!$A18,#REF!,"won",#REF!,"2") -> #REF! | G18: =SUMIFS(#REF!,#REF!,'Sales Campaign Overview'!$A18,#REF!,"won",#REF!,"2") -> #REF! | H18: =COUNTIFS(#REF!,'Sales Campaign Overview'!$A18,#REF!,"won",#REF!,"3") -> #REF! | I18: =SUMIFS(#REF!,#REF!,'Sales Campaign Overview'!$A18,#REF!,"won",#REF!,"3") -> #REF! | J18: =COUNTIFS(#REF!,'Sales Campaign Overview'!$A18,#REF!,"won",#REF!,"4") -> #REF! | K18: =SUMIFS(#REF!,#REF!,'Sales Campaign Overview'!$A18,#REF!,"won",#REF!,"4") -> #REF! | L18: =COUNTIFS(#REF!,'Sales Campaign Overview'!$A18,#REF!,"won",#REF!,"5") -> #REF! | M18: =SUMIFS(#REF!,#REF!,'Sales Campaign Overview'!$A18,#REF!,"won",#REF!,"5") -> #REF! | N18: =COUNTIFS(#REF!,'Sales Campaign Overview'!$A18,#REF!,"won",#REF!,"6") -> #REF! | O18: =SUMIFS(#REF!,#REF!,'Sales Campaign Overview'!$A18,#REF!,"won",#REF!,"6") -> #REF! | P18: =COUNTIFS(#REF!,'Sales Campaign Overview'!$A18,#REF!,"won",#REF!,"7") -> #REF! | Q18: =SUMIFS(#REF!,#REF!,'Sales Campaign Overview'!$A18,#REF!,"won",#REF!,"7") -> #REF! | R18: =COUNTIFS(#REF!,'Sales Campaign Overview'!$A18,#REF!,"won",#REF!,"8") -> #REF! | S18: =SUMIFS(#REF!,#REF!,'Sales Campaign Overview'!$A18,#REF!,"won",#REF!,"8") -> #REF! | T18: =COUNTIFS(#REF!,'Sales Campaign Overview'!$A18,#REF!,"won",#REF!,"9") -> #REF! | U18: =SUMIFS(#REF!,#REF!,'Sales Campaign Overview'!$A18,#REF!,"won",#REF!,"9") -> #REF! | V18: =COUNTIFS(#REF!,'Sales Campaign Overview'!$A18,#REF!,"won",#REF!,"10") -> #REF! | W18: =SUMIFS(#REF!,#REF!,'Sales Campaign Overview'!$A18,#REF!,"won",#REF!,"10") -> #REF! | X18: =COUNTIFS(#REF!,'Sales Campaign Overview'!$A18,#REF!,"won",#REF!,"11") -> #REF! | Y18: =SUMIFS(#REF!,#REF!,'Sales Campaign Overview'!$A18,#REF!,"won",#REF!,"11") -> #REF! | Z18: =COUNTIFS(#REF!,'Sales Campaign Overview'!$A18,#REF!,"won",#REF!,"12") -> #REF! | AA18: =SUMIFS(#REF!,#REF!,'Sales Campaign Overview'!$A18,#REF!,"won",#REF!,"12") -> #REF!
A19: POTS - MSFT License Migration | B19: =COUNTIFS(#REF!,'Sales Campaign Overview'!$A19,#REF!,"won") -> #REF! | C19: =SUMIFS(#REF!,#REF!,'Sales Campaign Overview'!$A19,#REF!,"won") -> #REF! | D19: =COUNTIFS(#REF!,'Sales Campaign Overview'!$A19,#REF!,"won",#REF!,"1") -> #REF! | E19: =SUMIFS(#REF!,#REF!,'Sales Campaign Overview'!$A19,#REF!,"won",#REF!,"1") -> #REF! | F19: =COUNTIFS(#REF!,'Sales Campaign Overview'!$A19,#REF!,"won",#REF!,"2") -> #REF! | G19: =SUMIFS(#REF!,#REF!,'Sales Campaign Overview'!$A19,#REF!,"won",#REF!,"2") -> #REF! | H19: =COUNTIFS(#REF!,'Sales Campaign Overview'!$A19,#REF!,"won",#REF!,"3") -> #REF! | I19: =SUMIFS(#REF!,#REF!,'Sales Campaign Overview'!$A19,#REF!,"won",#REF!,"3") -> #REF! | J19: =COUNTIFS(#REF!,'Sales Campaign Overview'!$A19,#REF!,"won",#REF!,"4") -> #REF! | K19: =SUMIFS(#REF!,#REF!,'Sales Campaign Overview'!$A19,#REF!,"won",#REF!,"4") -> #REF! | L19: =COUNTIFS(#REF!,'Sales Campaign Overview'!$A19,#REF!,"won",#REF!,"5") -> #REF! | M19: =SUMIFS(#REF!,#REF!,'Sales Campaign Overview'!$A19,#REF!,"won",#REF!,"5") -> #REF! | N19: =COUNTIFS(#REF!,'Sales Campaign Overview'!$A19,#REF!,"won",#REF!,"6") -> #REF! | O19: =SUMIFS(#REF!,#REF!,'Sales Campaign Overview'!$A19,#REF!,"won",#REF!,"6") -> #REF! | P19: =COUNTIFS(#REF!,'Sales Campaign Overview'!$A19,#REF!,"won",#REF!,"7") -> #REF! | Q19: =SUMIFS(#REF!,#REF!,'Sales Campaign Overview'!$A19,#REF!,"won",#REF!,"7") -> #REF! | R19: =COUNTIFS(#REF!,'Sales Campaign Overview'!$A19,#REF!,"won",#REF!,"8") -> #REF! | S19: =SUMIFS(#REF!,#REF!,'Sales Campaign Overview'!$A19,#REF!,"won",#REF!,"8") -> #REF! | T19: =COUNTIFS(#REF!,'Sales Campaign Overview'!$A19,#REF!,"won",#REF!,"9") -> #REF! | U19: =SUMIFS(#REF!,#REF!,'Sales Campaign Overview'!$A19,#REF!,"won",#REF!,"9") -> #REF! | V19: =COUNTIFS(#REF!,'Sales Campaign Overview'!$A19,#REF!,"won",#REF!,"10") -> #REF! | W19: =SUMIFS(#REF!,#REF!,'Sales Campaign Overview'!$A19,#REF!,"won",#REF!,"10") -> #REF! | X19: =COUNTIFS(#REF!,'Sales Campaign Overview'!$A19,#REF!,"won",#REF!,"11") -> #REF! | Y19: =SUMIFS(#REF!,#REF!,'Sales Campaign Overview'!$A19,#REF!,"won",#REF!,"11") -> #REF! | Z19: =COUNTIFS(#REF!,'Sales Campaign Overview'!$A19,#REF!,"won",#REF!,"12") -> #REF! | AA19: =SUMIFS(#REF!,#REF!,'Sales Campaign Overview'!$A19,#REF!,"won",#REF!,"12") -> #REF!
A20: POTS - PC Refresh 2019 | B20: =COUNTIFS(#REF!,'Sales Campaign Overview'!$A20,#REF!,"won") -> #REF! | C20: =SUMIFS(#REF!,#REF!,'Sales Campaign Overview'!$A20,#REF!,"won") -> #REF! | D20: =COUNTIFS(#REF!,'Sales Campaign Overview'!$A20,#REF!,"won",#REF!,"1") -> #REF! | E20: =SUMIFS(#REF!,#REF!,'Sales Campaign Overview'!$A20,#REF!,"won",#REF!,"1") -> #REF! | F20: =COUNTIFS(#REF!,'Sales Campaign Overview'!$A20,#REF!,"won",#REF!,"2") -> #REF! | G20: =SUMIFS(#REF!,#REF!,'Sales Campaign Overview'!$A20,#REF!,"won",#REF!,"2") -> #REF! | H20: =COUNTIFS(#REF!,'Sales Campaign Overview'!$A20,#REF!,"won",#REF!,"3") -> #REF! | I20: =SUMIFS(#REF!,#REF!,'Sales Campaign Overview'!$A20,#REF!,"won",#REF!,"3") -> #REF! | J20: =COUNTIFS(#REF!,'Sales Campaign Overview'!$A20,#REF!,"won",#REF!,"4") -> #REF! | K20: =SUMIFS(#REF!,#REF!,'Sales Campaign Overview'!$A20,#REF!,"won",#REF!,"4") -> #REF! | L20: =COUNTIFS(#REF!,'Sales Campaign Overview'!$A20,#REF!,"won",#REF!,"5") -> #REF! | M20: =SUMIFS(#REF!,#REF!,'Sales Campaign Overview'!$A20,#REF!,"won",#REF!,"5") -> #REF! | N20: =COUNTIFS(#REF!,'Sales Campaign Overview'!$A20,#REF!,"won",#REF!,"6") -> #REF! | O20: =SUMIFS(#REF!,#REF!,'Sales Campaign Overview'!$A20,#REF!,"won",#REF!,"6") -> #REF! | P20: =COUNTIFS(#REF!,'Sales Campaign Overview'!$A20,#REF!,"won",#REF!,"7") -> #REF! | Q20: =SUMIFS(#REF!,#REF!,'Sales Campaign Overview'!$A20,#REF!,"won",#REF!,"7") -> #REF! | R20: =COUNTIFS(#REF!,'Sales Campaign Overview'!$A20,#REF!,"won",#REF!,"8") -> #REF! | S20: =SUMIFS(#REF!,#REF!,'Sales Campaign Overview'!$A20,#REF!,"won",#REF!,"8") -> #REF! | T20: =COUNTIFS(#REF!,'Sales Campaign Overview'!$A20,#REF!,"won",#REF!,"9") -> #REF! | U20: =SUMIFS(#REF!,#REF!,'Sales Campaign Overview'!$A20,#REF!,"won",#REF!,"9") -> #REF! | V20: =COUNTIFS(#REF!,'Sales Campaign Overview'!$A20,#REF!,"won",#REF!,"10") -> #REF! | W20: =SUMIFS(#REF!,#REF!,'Sales Campaign Overview'!$A20,#REF!,"won",#REF!,"10") -> #REF! | X20: =COUNTIFS(#REF!,'Sales Campaign Overview'!$A20,#REF!,"won",#REF!,"11") -> #REF! | Y20: =SUMIFS(#REF!,#REF!,'Sales Campaign Overview'!$A20,#REF!,"won",#REF!,"11") -> #REF! | Z20: =COUNTIFS(#REF!,'Sales Campaign Overview'!$A20,#REF!,"won",#REF!,"12") -> #REF! | AA20: =SUMIFS(#REF!,#REF!,'Sales Campaign Overview'!$A20,#REF!,"won",#REF!,"12") -> #REF!
A21: POTS - Server 2008 EOL | B21: =COUNTIFS(#REF!,'Sales Campaign Overview'!$A21,#REF!,"won") -> #REF! | C21: =SUMIFS(#REF!,#REF!,'Sales Campaign Overview'!$A21,#REF!,"won") -> #REF! | D21: =COUNTIFS(#REF!,'Sales Campaign Overview'!$A21,#REF!,"won",#REF!,"1") -> #REF! | E21: =SUMIFS(#REF!,#REF!,'Sales Campaign Overview'!$A21,#REF!,"won",#REF!,"1") -> #REF! | F21: =COUNTIFS(#REF!,'Sales Campaign Overview'!$A21,#REF!,"won",#REF!,"2") -> #REF! | G21: =SUMIFS(#REF!,#REF!,'Sales Campaign Overview'!$A21,#REF!,"won",#REF!,"2") -> #REF! | H21: =COUNTIFS(#REF!,'Sales Campaign Overview'!$A21,#REF!,"won",#REF!,"3") -> #REF! | I21: =SUMIFS(#REF!,#REF!,'Sales Campaign Overview'!$A21,#REF!,"won",#REF!,"3") -> #REF! | J21: =COUNTIFS(#REF!,'Sales Campaign Overview'!$A21,#REF!,"won",#REF!,"4") -> #REF! | K21: =SUMIFS(#REF!,#REF!,'Sales Campaign Overview'!$A21,#REF!,"won",#REF!,"4") -> #REF! | L21: =COUNTIFS(#REF!,'Sales Campaign Overview'!$A21,#REF!,"won",#REF!,"5") -> #REF! | M21: =SUMIFS(#REF!,#REF!,'Sales Campaign Overview'!$A21,#REF!,"won",#REF!,"5") -> #REF! | N21: =COUNTIFS(#REF!,'Sales Campaign Overview'!$A21,#REF!,"won",#REF!,"6") -> #REF! | O21: =SUMIFS(#REF!,#REF!,'Sales Campaign Overview'!$A21,#REF!,"won",#REF!,"6") -> #REF! | P21: =COUNTIFS(#REF!,'Sales Campaign Overview'!$A21,#REF!,"won",#REF!,"7") -> #REF! | Q21: =SUMIFS(#REF!,#REF!,'Sales Campaign Overview'!$A21,#REF!,"won",#REF!,"7") -> #REF! | R21: =COUNTIFS(#REF!,'Sales Campaign Overview'!$A21,#REF!,"won",#REF!,"8") -> #REF! | S21: =SUMIFS(#REF!,#REF!,'Sales Campaign Overview'!$A21,#REF!,"won",#REF!,"8") -> #REF! | T21: =COUNTIFS(#REF!,'Sales Campaign Overview'!$A21,#REF!,"won",#REF!,"9") -> #REF! | U21: =SUMIFS(#REF!,#REF!,'Sales Campaign Overview'!$A21,#REF!,"won",#REF!,"9") -> #REF! | V21: =COUNTIFS(#REF!,'Sales Campaign Overview'!$A21,#REF!,"won",#REF!,"10") -> #REF! | W21: =SUMIFS(#REF!,#REF!,'Sales Campaign Overview'!$A21,#REF!,"won",#REF!,"10") -> #REF! | X21: =COUNTIFS(#REF!,'Sales Campaign Overview'!$A21,#REF!,"won",#REF!,"11") -> #REF! | Y21: =SUMIFS(#REF!,#REF!,'Sales Campaign Overview'!$A21,#REF!,"won",#REF!,"11") -> #REF! | Z21: =COUNTIFS(#REF!,'Sales Campaign Overview'!$A21,#REF!,"won",#REF!,"12") -> #REF! | AA21: =SUMIFS(#REF!,#REF!,'Sales Campaign Overview'!$A21,#REF!,"won",#REF!,"12") -> #REF!
A22: POTS - Server Renewal | B22: =COUNTIFS(#REF!,'Sales Campaign Overview'!$A22,#REF!,"won") -> #REF! | C22: =SUMIFS(#REF!,#REF!,'Sales Campaign Overview'!$A22,#REF!,"won") -> #REF! | D22: =COUNTIFS(#REF!,'Sales Campaign Overview'!$A22,#REF!,"won",#REF!,"1") -> #REF! | E22: =SUMIFS(#REF!,#REF!,'Sales Campaign Overview'!$A22,#REF!,"won",#REF!,"1") -> #REF! | F22: =COUNTIFS(#REF!,'Sales Campaign Overview'!#REF!,#REF!,"won",#REF!,"2") -> #REF! | G22: =SUMIFS(#REF!,#REF!,'Sales Campaign Overview'!$A22,#REF!,"won",#REF!,"2") -> #REF! | H22: =COUNTIFS(#REF!,'Sales Campaign Overview'!$A22,#REF!,"won",#REF!,"3") -> #REF! | I22: =SUMIFS(#REF!,#REF!,'Sales Campaign Overview'!$A22,#REF!,"won",#REF!,"3") -> #REF! | J22: =COUNTIFS(#REF!,'Sales Campaign Overview'!$A22,#REF!,"won",#REF!,"4") -> #REF! | K22: =SUMIFS(#REF!,#REF!,'Sales Campaign Overview'!$A22,#REF!,"won",#REF!,"4") -> #REF! | L22: =COUNTIFS(#REF!,'Sales Campaign Overview'!$A22,#REF!,"won",#REF!,"5") -> #REF! | M22: =SUMIFS(#REF!,#REF!,'Sales Campaign Overview'!$A22,#REF!,"won",#REF!,"5") -> #REF! | N22: =COUNTIFS(#REF!,'Sales Campaign Overview'!$A22,#REF!,"won",#REF!,"6") -> #REF! | O22: =SUMIFS(#REF!,#REF!,'Sales Campaign Overview'!$A22,#REF!,"won",#REF!,"6") -> #REF! | P22: =COUNTIFS(#REF!,'Sales Campaign Overview'!$A22,#REF!,"won",#REF!,"7") -> #REF! | Q22: =SUMIFS(#REF!,#REF!,'Sales Campaign Overview'!$A22,#REF!,"won",#REF!,"7") -> #REF! | R22: =COUNTIFS(#REF!,'Sales Campaign Overview'!$A22,#REF!,"won",#REF!,"8") -> #REF! | S22: =SUMIFS(#REF!,#REF!,'Sales Campaign Overview'!$A22,#REF!,"won",#REF!,"8") -> #REF! | T22: =COUNTIFS(#REF!,'Sales Campaign Overview'!$A22,#REF!,"won",#REF!,"9") -> #REF! | U22: =SUMIFS(#REF!,#REF!,'Sales Campaign Overview'!$A22,#REF!,"won",#REF!,"9") -> #REF! | V22: =COUNTIFS(#REF!,'Sales Campaign Overview'!$A22,#REF!,"won",#REF!,"10") -> #REF! | W22: =SUMIFS(#REF!,#REF!,'Sales Campaign Overview'!$A22,#REF!,"won",#REF!,"10") -> #REF! | X22: =COUNTIFS(#REF!,'Sales Campaign Overview'!$A22,#REF!,"won",#REF!,"11") -> #REF! | Y22: =SUMIFS(#REF!,#REF!,'Sales Campaign Overview'!$A22,#REF!,"won",#REF!,"11") -> #REF! | Z22: =COUNTIFS(#REF!,'Sales Campaign Overview'!$A22,#REF!,"won",#REF!,"12") -> #REF! | AA22: =SUMIFS(#REF!,#REF!,'Sales Campaign Overview'!$A22,#REF!,"won",#REF!,"12") -> #REF!
A23: POTS - Sonicwall Renewal | B23: =COUNTIFS(#REF!,'Sales Campaign Overview'!$A23,#REF!,"won") -> #REF! | C23: =SUMIFS(#REF!,#REF!,'Sales Campaign Overview'!$A23,#REF!,"won") -> #REF! | D23: =COUNTIFS(#REF!,'Sales Campaign Overview'!$A23,#REF!,"won",#REF!,"1") -> #REF! | E23: =SUMIFS(#REF!,#REF!,'Sales Campaign Overview'!$A23,#REF!,"won",#REF!,"1") -> #REF! | F23: =COUNTIFS(#REF!,'Sales Campaign Overview'!$A23,#REF!,"won",#REF!,"2") -> #REF! | G23: =SUMIFS(#REF!,#REF!,'Sales Campaign Overview'!$A23,#REF!,"won",#REF!,"2") -> #REF! | H23: =COUNTIFS(#REF!,'Sales Campaign Overview'!$A23,#REF!,"won",#REF!,"3") -> #REF! | I23: =SUMIFS(#REF!,#REF!,'Sales Campaign Overview'!$A23,#REF!,"won",#REF!,"3") -> #REF! | J23: =COUNTIFS(#REF!,'Sales Campaign Overview'!$A23,#REF!,"won",#REF!,"4") -> #REF! | K23: =SUMIFS(#REF!,#REF!,'Sales Campaign Overview'!$A23,#REF!,"won",#REF!,"4") -> #REF! | L23: =COUNTIFS(#REF!,'Sales Campaign Overview'!$A23,#REF!,"won",#REF!,"5") -> #REF! | M23: =SUMIFS(#REF!,#REF!,'Sales Campaign Overview'!$A23,#REF!,"won",#REF!,"5") -> #REF! | N23: =COUNTIFS(#REF!,'Sales Campaign Overview'!$A23,#REF!,"won",#REF!,"6") -> #REF! | O23: =SUMIFS(#REF!,#REF!,'Sales Campaign Overview'!$A23,#REF!,"won",#REF!,"6") -> #REF! | P23: =COUNTIFS(#REF!,'Sales Campaign Overview'!$A23,#REF!,"won",#REF!,"7") -> #REF! | Q23: =SUMIFS(#REF!,#REF!,'Sales Campaign Overview'!$A23,#REF!,"won",#REF!,"7") -> #REF! | R23: =COUNTIFS(#REF!,'Sales Campaign Overview'!$A23,#REF!,"won",#REF!,"8") -> #REF! | S23: =SUMIFS(#REF!,#REF!,'Sales Campaign Overview'!$A23,#REF!,"won",#REF!,"8") -> #REF! | T23: =COUNTIFS(#REF!,'Sales Campaign Overview'!$A23,#REF!,"won",#REF!,"9") -> #REF! | U23: =SUMIFS(#REF!,#REF!,'Sales Campaign Overview'!$A23,#REF!,"won",#REF!,"9") -> #REF! | V23: =COUNTIFS(#REF!,'Sales Campaign Overview'!$A23,#REF!,"won",#REF!,"10") -> #REF! | W23: =SUMIFS(#REF!,#REF!,'Sales Campaign Overview'!$A23,#REF!,"won",#REF!,"10") -> #REF! | X23: =COUNTIFS(#REF!,'Sales Campaign Overview'!$A23,#REF!,"won",#REF!,"11") -> #REF! | Y23: =SUMIFS(#REF!,#REF!,'Sales Campaign Overview'!$A23,#REF!,"won",#REF!,"11") -> #REF! | Z23: =COUNTIFS(#REF!,'Sales Campaign Overview'!$A23,#REF!,"won",#REF!,"12") -> #REF! | AA23: =SUMIFS(#REF!,#REF!,'Sales Campaign Overview'!$A23,#REF!,"won",#REF!,"12") -> #REF!
A24: POTS - VoIP Migration | B24: =COUNTIFS(#REF!,'Sales Campaign Overview'!$A24,#REF!,"won") -> #REF! | C24: =SUMIFS(#REF!,#REF!,'Sales Campaign Overview'!$A24,#REF!,"won") -> #REF! | D24: =COUNTIFS(#REF!,'Sales Campaign Overview'!$A24,#REF!,"won",#REF!,"1") -> #REF! | E24: =SUMIFS(#REF!,#REF!,'Sales Campaign Overview'!$A24,#REF!,"won",#REF!,"1") -> #REF! | F24: =COUNTIFS(#REF!,'Sales Campaign Overview'!$A24,#REF!,"won",#REF!,"2") -> #REF! | G24: =SUMIFS(#REF!,#REF!,'Sales Campaign Overview'!$A24,#REF!,"won",#REF!,"2") -> #REF! | H24: =COUNTIFS(#REF!,'Sales Campaign Overview'!$A24,#REF!,"won",#REF!,"3") -> #REF! | I24: =SUMIFS(#REF!,#REF!,'Sales Campaign Overview'!$A24,#REF!,"won",#REF!,"3") -> #REF! | J24: =COUNTIFS(#REF!,'Sales Campaign Overview'!$A24,#REF!,"won",#REF!,"4") -> #REF! | K24: =SUMIFS(#REF!,#REF!,'Sales Campaign Overview'!$A24,#REF!,"won",#REF!,"4") -> #REF! | L24: =COUNTIFS(#REF!,'Sales Campaign Overview'!$A24,#REF!,"won",#REF!,"5") -> #REF! | M24: =SUMIFS(#REF!,#REF!,'Sales Campaign Overview'!$A24,#REF!,"won",#REF!,"5") -> #REF! | N24: =COUNTIFS(#REF!,'Sales Campaign Overview'!$A24,#REF!,"won",#REF!,"6") -> #REF! | O24: =SUMIFS(#REF!,#REF!,'Sales Campaign Overview'!$A24,#REF!,"won",#REF!,"6") -> #REF! | P24: =COUNTIFS(#REF!,'Sales Campaign Overview'!$A24,#REF!,"won",#REF!,"7") -> #REF! | Q24: =SUMIFS(#REF!,#REF!,'Sales Campaign Overview'!$A24,#REF!,"won",#REF!,"7") -> #REF! | R24: =COUNTIFS(#REF!,'Sales Campaign Overview'!$A24,#REF!,"won",#REF!,"8") -> #REF! | S24: =SUMIFS(#REF!,#REF!,'Sales Campaign Overview'!$A24,#REF!,"won",#REF!,"8") -> #REF! | T24: =COUNTIFS(#REF!,'Sales Campaign Overview'!$A24,#REF!,"won",#REF!,"9") -> #REF! | U24: =SUMIFS(#REF!,#REF!,'Sales Campaign Overview'!$A24,#REF!,"won",#REF!,"9") -> #REF! | V24: =COUNTIFS(#REF!,'Sales Campaign Overview'!$A24,#REF!,"won",#REF!,"10") -> #REF! | W24: =SUMIFS(#REF!,#REF!,'Sales Campaign Overview'!$A24,#REF!,"won",#REF!,"10") -> #REF! | X24: =COUNTIFS(#REF!,'Sales Campaign Overview'!$A24,#REF!,"won",#REF!,"11") -> #REF! | Y24: =SUMIFS(#REF!,#REF!,'Sales Campaign Overview'!$A24,#REF!,"won",#REF!,"11") -> #REF! | Z24: =COUNTIFS(#REF!,'Sales Campaign Overview'!$A24,#REF!,"won",#REF!,"12") -> #REF! | AA24: =SUMIFS(#REF!,#REF!,'Sales Campaign Overview'!$A24,#REF!,"won",#REF!,"12") -> #REF!
A25: POTS-Server Replacement | B25: =COUNTIFS(#REF!,'Sales Campaign Overview'!$A25,#REF!,"won") -> #REF! | C25: =SUMIFS(#REF!,#REF!,'Sales Campaign Overview'!$A25,#REF!,"won") -> #REF! | D25: =COUNTIFS(#REF!,'Sales Campaign Overview'!$A25,#REF!,"won",#REF!,"1") -> #REF! | E25: =SUMIFS(#REF!,#REF!,'Sales Campaign Overview'!$A25,#REF!,"won",#REF!,"1") -> #REF! | F25: =COUNTIFS(#REF!,'Sales Campaign Overview'!$A25,#REF!,"won",#REF!,"2") -> #REF! | G25: =SUMIFS(#REF!,#REF!,'Sales Campaign Overview'!$A25,#REF!,"won",#REF!,"2") -> #REF! | H25: =COUNTIFS(#REF!,'Sales Campaign Overview'!$A25,#REF!,"won",#REF!,"3") -> #REF! | I25: =SUMIFS(#REF!,#REF!,'Sales Campaign Overview'!$A25,#REF!,"won",#REF!,"3") -> #REF! | J25: =COUNTIFS(#REF!,'Sales Campaign Overview'!$A25,#REF!,"won",#REF!,"4") -> #REF! | K25: =SUMIFS(#REF!,#REF!,'Sales Campaign Overview'!$A25,#REF!,"won",#REF!,"4") -> #REF! | L25: =COUNTIFS(#REF!,'Sales Campaign Overview'!$A25,#REF!,"won",#REF!,"5") -> #REF! | M25: =SUMIFS(#REF!,#REF!,'Sales Campaign Overview'!$A25,#REF!,"won",#REF!,"5") -> #REF! | N25: =COUNTIFS(#REF!,'Sales Campaign Overview'!$A25,#REF!,"won",#REF!,"6") -> #REF! | O25: =SUMIFS(#REF!,#REF!,'Sales Campaign Overview'!$A25,#REF!,"won",#REF!,"6") -> #REF! | P25: =COUNTIFS(#REF!,'Sales Campaign Overview'!$A25,#REF!,"won",#REF!,"7") -> #REF! | Q25: =SUMIFS(#REF!,#REF!,'Sales Campaign Overview'!$A25,#REF!,"won",#REF!,"7") -> #REF! | R25: =COUNTIFS(#REF!,'Sales Campaign Overview'!$A25,#REF!,"won",#REF!,"8") -> #REF! | S25: =SUMIFS(#REF!,#REF!,'Sales Campaign Overview'!$A25,#REF!,"won",#REF!,"8") -> #REF! | T25: =COUNTIFS(#REF!,'Sales Campaign Overview'!$A25,#REF!,"won",#REF!,"9") -> #REF! | U25: =SUMIFS(#REF!,#REF!,'Sales Campaign Overview'!$A25,#REF!,"won",#REF!,"9") -> #REF! | V25: =COUNTIFS(#REF!,'Sales Campaign Overview'!$A25,#REF!,"won",#REF!,"10") -> #REF! | W25: =SUMIFS(#REF!,#REF!,'Sales Campaign Overview'!$A25,#REF!,"won",#REF!,"10") -> #REF! | X25: =COUNTIFS(#REF!,'Sales Campaign Overview'!$A25,#REF!,"won",#REF!,"11") -> #REF! | Y25: =SUMIFS(#REF!,#REF!,'Sales Campaign Overview'!$A25,#REF!,"won",#REF!,"11") -> #REF! | Z25: =COUNTIFS(#REF!,'Sales Campaign Overview'!$A25,#REF!,"won",#REF!,"12") -> #REF! | AA25: =SUMIFS(#REF!,#REF!,'Sales Campaign Overview'!$A25,#REF!,"won",#REF!,"12") -> #REF!
A26: POTS-SSL Renewal | B26: =COUNTIFS(#REF!,'Sales Campaign Overview'!$A26,#REF!,"won") -> #REF! | C26: =SUMIFS(#REF!,#REF!,'Sales Campaign Overview'!$A26,#REF!,"won") -> #REF! | D26: =COUNTIFS(#REF!,'Sales Campaign Overview'!$A26,#REF!,"won",#REF!,"1") -> #REF! | E26: =SUMIFS(#REF!,#REF!,'Sales Campaign Overview'!$A26,#REF!,"won",#REF!,"1") -> #REF! | F26: =COUNTIFS(#REF!,'Sales Campaign Overview'!$A26,#REF!,"won",#REF!,"2") -> #REF! | G26: =SUMIFS(#REF!,#REF!,'Sales Campaign Overview'!$A26,#REF!,"won",#REF!,"2") -> #REF! | H26: =COUNTIFS(#REF!,'Sales Campaign Overview'!$A26,#REF!,"won",#REF!,"3") -> #REF! | I26: =SUMIFS(#REF!,#REF!,'Sales Campaign Overview'!$A26,#REF!,"won",#REF!,"3") -> #REF! | J26: =COUNTIFS(#REF!,'Sales Campaign Overview'!$A26,#REF!,"won",#REF!,"4") -> #REF! | K26: =SUMIFS(#REF!,#REF!,'Sales Campaign Overview'!$A26,#REF!,"won",#REF!,"4") -> #REF! | L26: =COUNTIFS(#REF!,'Sales Campaign Overview'!$A26,#REF!,"won",#REF!,"5") -> #REF! | M26: =SUMIFS(#REF!,#REF!,'Sales Campaign Overview'!$A26,#REF!,"won",#REF!,"5") -> #REF! | N26: =COUNTIFS(#REF!,'Sales Campaign Overview'!$A26,#REF!,"won",#REF!,"6") -> #REF! | O26: =SUMIFS(#REF!,#REF!,'Sales Campaign Overview'!$A26,#REF!,"won",#REF!,"6") -> #REF! | P26: =COUNTIFS(#REF!,'Sales Campaign Overview'!$A26,#REF!,"won",#REF!,"7") -> #REF! | Q26: =SUMIFS(#REF!,#REF!,'Sales Campaign Overview'!$A26,#REF!,"won",#REF!,"7") -> #REF! | R26: =COUNTIFS(#REF!,'Sales Campaign Overview'!$A26,#REF!,"won",#REF!,"8") -> #REF! | S26: =SUMIFS(#REF!,#REF!,'Sales Campaign Overview'!$A26,#REF!,"won",#REF!,"8") -> #REF! | T26: =COUNTIFS(#REF!,'Sales Campaign Overview'!$A26,#REF!,"won",#REF!,"9") -> #REF! | U26: =SUMIFS(#REF!,#REF!,'Sales Campaign Overview'!$A26,#REF!,"won",#REF!,"9") -> #REF! | V26: =COUNTIFS(#REF!,'Sales Campaign Overview'!$A26,#REF!,"won",#REF!,"10") -> #REF! | W26: =SUMIFS(#REF!,#REF!,'Sales Campaign Overview'!$A26,#REF!,"won",#REF!,"10") -> #REF! | X26: =COUNTIFS(#REF!,'Sales Campaign Overview'!$A26,#REF!,"won",#REF!,"11") -> #REF! | Y26: =SUMIFS(#REF!,#REF!,'Sales Campaign Overview'!$A26,#REF!,"won",#REF!,"11") -> #REF! | Z26: =COUNTIFS(#REF!,'Sales Campaign Overview'!$A26,#REF!,"won",#REF!,"12") -> #REF! | AA26: =SUMIFS(#REF!,#REF!,'Sales Campaign Overview'!$A26,#REF!,"won",#REF!,"12") -> #REF!
A27: Total | B27: =SUM(B17+B18+B19+B20+B21+B22+B23+B24+B25+B26) -> #REF! | C27: =SUM(C17+C18+C19+C20+C21+C22+C23+C24+C25+C26) -> #REF! | D27: =SUM(D17+D18+D19+D20+D21+D22+D23+D24+D25+D26) -> #REF! | E27: =SUM(E17+E18+E19+E20+E21+E22+E23+E24+E25+E26) -> #REF! | F27: =SUM(F17:F26) -> #REF! | G27: =SUM(G17+G18+G19+G20+G21+G22+G23+G24+G25+G26) -> #REF! | H27: =SUM(H17+H18+H19+H20+H21+H22+H23+H24+H25+H26) -> #REF! | I27: =SUM(I17+I18+I19+I20+I21+I22+I23+I24+I25+I26) -> #REF! | J27: =SUM(J17+J18+J19+J20+J21+J22+J23+J24+J25+J26) -> #REF! | K27: =SUM(K17+K18+K19+K20+K21+K22+K23+K24+K25+K26) -> #REF! | L27: =SUM(L17+L18+L19+L20+L21+L22+L23+L24+L25+L26) -> #REF! | M27: =SUM(M17+M18+M19+M20+M21+M22+M23+M24+M25+M26) -> #REF! | N27: =SUM(N17+N18+N19+N20+N21+N22+N23+N24+N25+N26) -> #REF! | ... AA27: =SUM(AA17+AA18+AA19+AA20+AA21+AA22+AA23+AA24+AA25+AA26) -> #REF!

Sheet Campaign Pivot
A1: Year | B1: 2019
A2: Status2 | B2: (Multiple Items)
A3: Close Date | B3: (All)
A4: Years | B4: (All)
A6: Sum of Revenue | B6: Column Labels
A7: Row Labels | B7: Jan | C7: Feb | D7: Mar | E7: Apr | F7: May | G7: Jun | H7: Jul | I7: Aug | J7: Sep | K7: Oct | L7: Nov | M7: Dec | N7: Grand Total
A8: POTS - 2011 Small Business Server | D8: 5100 | E8: 14621.02 | F8: 7062.5 | I8: 250 | M8: 7250 | N8: 34283.52
A9: POTS - PC Refresh 2019 | B9: 9490.7 | C9: 172.12 | D9: 12286.8 | E9: 2265 | F9: 7920 | G9: 40775.24 | H9: 7820 | I9: 40438.36 | J9: 12000 | K9: 5000 | N9: 138168.22
A10: POTS - Server 2008 EOL | C10: 189 | D10: 12650 | F10: 500 | G10: 250 | M10: 4850 | N10: 18439
A11: POTS - Server Renewal | D11: 312 | E11: 754.12 | N11: 1066.12
A12: POTS - Sonicwall Renewal | B12: 1986 | C12: 1078 | D12: 1139 | F12: 1327 | N12: 5530
A13: POTS-Server Replacement | M13: 25000 | N13: 25000
A14: (blank) | B14: 34338.53 | C14: 45174.02 | D14: 58458.94 | E14: 62772.95 | F14: 105239.13 | G14: 14895.38 | H14: 25745.09 | I14: 7703.21 | J14: 22534.63 | L14: 0 | M14: 25000 | N14: 401861.88
A15: Grand Total | B15: 45815.23 | C15: 46613.14 | D15: 89946.74 | E15: 80413.09 | F15: 122048.63 | G15: 55920.62 | H15: 33565.09 | I15: 48391.57 | J15: 34534.63 | K15: 5000 | L15: 0 | M15: 62100 | N15: 624348.74
A19: Year | B19: 2019
A20: Status2 | B20: (Multiple Items)
A21: Close Date | B21: (All)
A22: Years | B22: (All)
A24: Count of Revenue | B24: Column Labels
A25: Row Labels | B25: Jan | C25: Feb | D25: Mar | E25: Apr | F25: May | G25: Jun | H25: Jul | I25: Aug | J25: Sep | K25: Oct | L25: Nov | M25: Dec | N25: Grand Total
A26: POTS - 2011 Small Business Server | D26: 1 | E26: 1 | F26: 2 | I26: 1 | M26: 2 | N26: 7
A27: POTS - PC Refresh 2019 | B27: 3 | C27: 1 | D27: 3 | E27: 1 | F27: 2 | G27: 6 | H27: 3 | I27: 5 | J27: 2 | K27: 1 | N27: 27
A28: POTS - Server 2008 EOL | C28: 1 | D28: 2 | F28: 1 | G28: 1 | M28: 2 | N28: 7
A29: POTS - Server Renewal | D29: 1 | E29: 3 | N29: 4
A30: POTS - Sonicwall Renewal | B30: 3 | C30: 1 | D30: 2 | F30: 3 | N30: 9
A31: POTS-Server Replacement | M31: 2 | N31: 2
A32: (blank) | B32: 32 | C32: 42 | D32: 42 | E32: 45 | F32: 44 | G32: 6 | H32: 2 | I32: 3 | J32: 1 | L32: 1 | M32: 3 | N32: 221
A33: Grand Total | B33: 38 | C33: 45 | D33: 51 | E33: 50 | F33: 52 | G33: 13 | H33: 5 | I33: 9 | J33: 3 | K33: 1 | L33: 1 | M33: 9 | N33: 277

Sheet Sheet1
A2: Company | B2: (All)
A3: Campaign | B3: (All)
A5: Sum of Revenue | B5: Column Labels
A6: Row Labels | B6: 1 | C6: 2 | D6: 3 | E6: 4 | F6: 5 | G6: 6 | H6: 7 | I6: 8 | J6: 9 | K6: 12 | L6: 11 | M6: 10 | N6: Grand Total
A7: CWiggins | D7: 2077.8 | N7: 2077.8
A8: Won | D8: 2077.8 | N8: 2077.8
A9: jelbek | B9: 36855.23 | C9: 45578.33 | D9: 58258.9 | E9: 35065.87 | F9: 49377.09 | G9: 48525.24 | H9: 7820 | I9: 45868.36 | J9: 12000 | M9: 5000 | N9: 344349.02
A10: Open | F10: 48860.21 | G10: 48525.24 | H10: 7820 | I10: 45868.36 | J10: 12000 | M10: 5000 | N10: 168073.81
A11: Won | B11: 36855.23 | C11: 45578.33 | D11: 58258.9 | E11: 35065.87 | F11: 516.88 | N11: 176275.21
A12: (blank) | B12: 8960 | C12: 1034.81 | D12: 29610.04 | E12: 45347.22 | F12: 72671.54 | G12: 7395.38 | H12: 25745.09 | I12: 2523.21 | J12: 22534.63 | K12: 62100 | L12: 0 | N12: 277921.92
A13: Open | F13: 72671.54 | G13: 7395.38 | H13: 25745.09 | I13: 2523.21 | J13: 22534.63 | K13: 57450 | L13: 0 | N13: 188319.85
A14: Won | B14: 8960 | C14: 1034.81 | D14: 29610.04 | E14: 45347.22 | K14: 4650 | N14: 89602.07
A15: Grand Total | B15: 45815.23 | C15: 46613.14 | D15: 89946.74 | E15: 80413.09 | F15: 122048.63 | G15: 55920.62 | H15: 33565.09 | I15: 48391.57 | J15: 34534.63 | K15: 62100 | L15: 0 | M15: 5000 | N15: 624348.74

Sheet Invoice by Line Item Categories
A1: Short Description | B1: Tag
A2: 8x8 VoIP Telephone | B2: VoIP
A3: Backup Data Offsite | B3: Licensing
A4: Backup Management License - Data | B4: Licensing
A5: Backup Management License - Exchange | B5: Licensing
A6: Backup Management License - Image | B6: Licensing
A7: Backup Management License - SQL | B7: Licensing
A8: Battery Backup - Desktop Computer
A9: Battery Backup - Server Grade
A10: Cabling Hardware
A11: Cabling Services
A12: California Fee - Electronic Waste Recycling
A13: Cloud Services/Hosted Server/Collocation | B13: Licensing
A14: Computer - Dell Monitor
A15: Computer - Desktop Standard
A16: Computer - Laptop Standard
A17: Computer - Monitor 24"
A18: Computer - Wireless Keyboard / Mouse
A19: Computer Cable DVI
A20: Computer Headset
A21: Dell Latitude HDD
A22: Desktop - Standard Optiplex
A23: Email Security Appliance
A24: Email Security System | B24: Licensing
A25: Ethernet Cable
A26: Firewall - Licenses SonicWall SSL VPN - Qty 5
A27: License - HeroTech O365 Business Essentials | B27: Licensing
A28: License - HeroTech O365 Business Premium | B28: Licensing
A29: License - HeroTech O365 Enterprise E3 | B29: Licensing
A30: License - HeroTech O365 Kiosk | B30: Licensing
A31: License - MS Azure Information Protection Plan 1 | B31: Licensing
A32: License - MS Exchange Online Kiosk | B32: Licensing
A33: License - MS Exchange Online Protection | B33: Licensing
A34: License - MS O365 Business Essentials | B34: Licensing
A35: License - MS O365 Business Premium | B35: Licensing
A36: License - MS O365 E3 | B36: Licensing
A37: License - MS O365 Enterprise E1 | B37: Licensing
A38: License - MS O365 Exchange Online (Plan 1) | B38: Licensing
... A59: Managed Workstation | B59: ITMS
A60: Miscellaneous
A61: Miscellaneous - Hardware
A62: Network Attached Storage Device (NAS)
A63: Office Relocation
A64: Optiplex 7060
A65: RAM Memory
A66: Refurbished Desktop
A67: Refurbished Laptop
A68: Security/Alerting/N.O.C. | B68: ITMS
A69: Server - Server Warranty
A70: Services - Admin Fee | B70: ITMS
A71: Services - Adword Marketing | B71: RedyRef
A72: Services - Client Discount
A73: Services - Cloud Services/Hosted Server/Collocation
A74: Services - Consulting Services Deferred
A75: Services - Directory/Kiosk Installation RedyRef
A76: Services - Directory/Kiosk Onsite Service RedyRef
A77: Services - End User Support Help Desk | B77: ITMS
A78: Services - FTE Onsite Technician 8 hrs | B78: ITMS
A79: Services - HeroTech Managed Services | B79: ITMS
A80: Services - HeroTech Monitoring Services | B80: ITMS
A81: Services - Monitoring and Alerting | B81: ITMS
A82: Services - Office 365 Hosted Exchange Project / Migration | B82: RedyRef
A83: Services - Sales Channel Development | B83: RedyRef
A84: Services - Sales Commission | B84: RedyRef
A85: Services - Sales Operations | B85: RedyRef
A86: Services - Server Warranty
A87: Services - Technology Managed Services | B87: ITMS
A88: Services - VOIP Monthly Services
A89: Services - VOIP Services | B89: ITMS
A90: Services - Website Development / Admin
A91: Services - Workstation Installation and Configuration
A92: Shipping and Handling Expedited
A93: Software - Add Description
A94: Technology Consulting Services
A95: Total Secure Annual Renewal
A96: TZ300 CGSS Renewal
A97: TZ400 CGSS Renewal
A98: TZ500 CGSS Renewal
A99: TZ600 CGSS Renewal
A100: WIFI - Aerohive HiveManager (1yr Support)
A101: Wyse 3040 Thin Client (TC OS)

Sheet 7.3.18
E1: 32490.48 | F1: Yes | G1: Maybe | H1: No | I1: Notes
F2: 23686.98 | G2: 8803.5 | H2: 2800
A3: Row Labels | B3: Opportunity Summary | C3: Close Date | D3: Stage | E3: Sum of Revenue
A4: <6/20/2018
A5: Jun
A6: A Change in Trajectory (ACT) | B6: POTS Sonicwall License Renewal | C6: 30-Jun | D6: 1 - New Opportunity | E6: 450 | F6: 450
A7: Advanced Chiropractic | B7: POTS tablets | C7: 30-Jun | D7: 8 - Quote in review | E7: 954 | G7: 954 | I7: approved? f/u with jasmine
A8: California Center for Public Health Advocacy | B8: POTS monthly website maintenance | C8: 30-Jun | D8: 1 - New Opportunity | E8: 100 | F8: 100
A9: Cool Pak | B9: POTS server warranty renewal | C9: 30-Jun | D9: 1 - New Opportunity | E9: 480 | F9: 480
A10: Nelson and Associates | B10: POTS server grade battery backup | C10: 30-Jun | D10: 10 - Awaiting Client Approval | E10: 1261.98 | F10: 1261.98 | I10: f/u with Jasmine
A11: Z&S Management Corporation | B11: POTS onsite visit Palm Desert | C11: 30-Jun | D11: 1 - New Opportunity | E11: 1000 | H11: 1000 | I11: already invoiced. Change $ to 0 and move to dec 2017 or won at $0
B12: POTS 4 Laptops | C12: 30-Jun | D12: 1 - New Opportunity | E12: 1800 | H12: 1800 | I12: already invocied
B13: POTS 12 Sonicwalls | C13: 30-Jun | D13: 1 - New Opportunity | E13: 16380 | F13: 16380
B14: POTS Palm Desert Site Visit 2 | C14: 30-Jun | D14: 1 - New Opportunity | E14: 450 | F14: 450
B15: POTS Z&S Sonicwall NSA2600 | C15: 30-Jun | D15: 1 - New Opportunity | E15: 2665 | F15: 2665
B16: Laptop for Brinton Watts | C16: 20-Jun | D16: 7 - Quoting | E16: 7849.5 | G16: 7849.5 | I16: update to POTS, $5000 = waiting for approval
A17: HeroTech | B17: POTS o365 migration (EDM Services) | C17: 30-Jun | D17: 1 - New Opportunity | E17: 1900 | F17: 1900 | I17: f/u with Shaun
A18: Jul
A19: Autism Response Team (ART) | B19: POTS PC Refresh | C19: 16-Jul | D19: 7 - Quoting | E19: 1000 | G19: 1000
A20: Cool Pak | B20: POTS AWS - MS | C20: 31-Jul | D20: 7 - Quoting | E20: 1879 | G20: 1879
A21: DITEC Manufacturing | B21: POTS DYNAMICS Migration Project | C21: 15-Jul | D21: 14 - On Hold | E21: 53430 | H21: 53430 | I21: move to Aug? how can we make this easier?
B22: POTS PC Refresh 1 of 6 | C22: 31-Jul | D22: 10 - Awaiting Client Approval | E22: 2010 | H22: 2010 | I22: move to aug
B23: POTS PC Refresh 2 of 6 | C23: 31-Jul | D23: 10 - Awaiting Client Approval | E23: 2010 | H23: 2010 | I23: move to aug
A24: Instrument Control Services | B24: POTS VoIP Proposal | C24: 31-Jul | D24: 1 - New Opportunity | E24: 2800 | F24: 2800
A25: Manduka | B25: POTS server environment upgrade | C25: 31-Jul | D25: 1 - New Opportunity | E25: 11500 | F25: 11500
A26: Ojai Oil Company | B26: POTS AWS - test server | C26: 31-Jul | D26: 10 - Awaiting Client Approval | E26: 6000 | F26: 6000
A27: Organic Certifiers | B27: POTS PC Refresh | C27: 2-Jul | D27: 14 - On Hold | E27: 1854.85 | F27: 1854.85 | I27: change stage
A28: Southland Stone USA Inc. | B28: POTS Migrate server T610 to AWS | C28: 1-Jul | D28: 8 - Quote in review | E28: 6665 | F28: 6665
A29: Studio Designs | B29: POTS Computer Purchase | C29: 1-Jul | D29: 10 - Awaiting Client Approval | E29: 5000 | G29: 5000
A30: Turning Point Foundation | B30: POTS AWS MS | C30: 31-Jul | D30: 10 - Awaiting Client Approval | E30: 2411.5 | F30: 2411.5
A31: Ventura Harley | B31: POTS MS | C31: 15-Jul | D31: 1 - New Opportunity | E31: 1317 | F31: 1317
B32: POTS 4 computers | C32: 31-Jul | D32: 1 - New Opportunity | E32: 3205.56 | F32: 3205.56
B33: POTS 4 computers - August | C33: 31-Jul | D33: 1 - New Opportunity | E33: 3205.56 | F33: 3205.56
A34: Z&S Management Corporation | B34: POTS MDaemon | C34: 31-Jul | D34: 1 - New Opportunity | E34: 12000 | F34: 12000
B35: POTS - aprox 20 site visits | C35: 31-Jul | D35: 1 - New Opportunity | E35: 12400 | F35: 12400
B36: POTS VoIP (MS) | C36: 31-Jul | D36: 1 - New Opportunity | E36: 10000 | H36: 10000
B37: POTS VoIP telephone configuration | C37: 31-Jul | D37: 1 - New Opportunity | E37: 9000 | H37: 9000
B38: POTS 20 user cals | C38: 1-Jul | D38: 1 - New Opportunity | E38: 3180 | F38: 3180
B39: POTS 10 computers | C39: 31-Jul | D39: 1 - New Opportunity | E39: 4500 | F39: 4500
B40: POTS Sonicwall replacements - qty 11 | C40: 31-Jul | D40: 1 - New Opportunity | E40: 15015 | F40: 15015
A41: HeroTech | B41: POTS computer replacement | C41: 31-Jul | D41: 1 - New Opportunity | E41: 2600 | F41: 2600
A42: Aug | E42: 110248 | F42: 88654.47 | G42: 7879
A43: Sep | E43: 6908 | G43: 96533.47

Sheet 6.19.18
E1: 25525.98 | F1: Yes | G1: Maybe | H1: No | I1: Notes
F2: 19525.98 | G2: 6000 | H2: 58247
A3: Row Labels | B3: Opportunity Summary | C3: Close Date | D3: Stage | E3: Sum of Revenue
A4: <6/15/2018
A5: Jun
A6: Advanced Chiropractic | B6: POTS tablets | C6: 30-Jun | D6: 8 - Quote in review | E6: 954 | F6: 954
A7: California Center for Public Health Advocacy | B7: POTS monthly website maintenance | C7: 30-Jun | D7: 1 - New Opportunity | E7: 100 | F7: 100
A8: DITEC Manufacturing | B8: POTS DYNAMICS Migration Project | C8: 15-Jun | D8: 14 - On Hold | E8: 53430 | H8: 53430 | I8: Chad to call tomorrow - push to July?
B9: POTS PC Refresh 1 of 6 | C9: 30-Jun | D9: 10 - Awaiting Client Approval | E9: 2010 | F9: 2010
A10: Manduka | B10: POTS server environment upgrade | C10: 30-Jun | D10: 1 - New Opportunity | E10: 11500 | F10: 11500 | I10: spoke last week - ready to move forward
A11: Nelson and Associates | B11: POTS server grade battery backup | C11: 30-Jun | D11: 10 - Awaiting Client Approval | E11: 1261.98 | F11: 1261.98
A12: Ojai Oil Company | B12: POTS AWS - test server | C12: 30-Jun | D12: 10 - Awaiting Client Approval | E12: 6000 | G12: 6000 | I12: move to July?
A13: Ventura Harley | B13: POTS MS | C13: 30-Jun | D13: 1 - New Opportunity | E13: 1317 | H13: 1317 | I13: 43282
A14: Z&S Management Corporation | B14: POTS Site location setup | C14: 30-Jun | D14: 1 - New Opportunity | E14: 1000 | H14: 1000 | I14: already invoiced - remove
B15: POTS onsite visit Palm Desert | C15: 30-Jun | D15: 1 - New Opportunity | E15: 1000 | H15: 1000 | I15: already invoiced - remove
B16: POTS San Diego Office | C16: 30-Jun | D16: 1 - New Opportunity | E16: 1500 | H16: 1500 | I16: already invoiced - remove
B17: POTS 4 Laptops | C17: 19-Jun | D17: 1 - New Opportunity | E17: 1800 | F17: 1800
A18: HeroTech | B18: POTS o365 migration (EDM Services) | C18: 30-Jun | D18: 1 - New Opportunity | E18: 1900 | F18: 1900 | I18: approved by EDM - invoice HT by EOM
A19: Jul
A20: Autism Response Team (ART) | B20: POTS PC Refresh | C20: 16-Jul | D20: 7 - Quoting | E20: 1000 | F20: 1000
A21: Cool Pak | B21: POTS AWS - MS | C21: 31-Jul | D21: 7 - Quoting | E21: 1879 | F21: 1879
A22: DITEC Manufacturing | B22: POTS PC Refresh 2 of 6 | C22: 31-Jul | D22: 10 - Awaiting Client Approval | E22: 2010 | F22: 2010
A23: Instrument Control Services | B23: POTS VoIP Proposal | C23: 31-Jul | D23: 1 - New Opportunity | E23: 2800 | G23: 2800
A24: Organic Certifiers | B24: POTS PC Refresh | C24: 2-Jul | D24: 14 - On Hold | E24: 1854.85 | F24: 1854.85
A25: Southland Stone USA Inc. | B25: POTS Migrate server T610 to AWS | C25: 1-Jul | D25: 8 - Quote in review | E25: 6665 | G25: 6665 | I25: verbally committed - need to f/u
A26: Studio Designs | B26: POTS Computer Purchase | C26: 1-Jul | D26: 10 - Awaiting Client Approval | E26: 5000 | G26: 5000 | I26: need to f/u - review oppty and validate
A27: Turning Point Foundation | B27: POTS AWS MS | C27: 31-Jul | D27: 10 - Awaiting Client Approval | E27: 2411.5 | G27: 2411.5 | I27: try to do a drop in
A28: Z&S Management Corporation | B28: POTS 20 computers | C28: 31-Jul | D28: 1 - New Opportunity | E28: 7980 | F28: 7980
B29: POTS MDaemon | C29: 31-Jul | D29: 1 - New Opportunity | E29: 30000 | F29: 15000 | I29: update price
B30: POTS - aprox 20 site visits | C30: 31-Jul | D30: 1 - New Opportunity | E30: 12400 | F30: 12400
B31: POTS Sonicwall Global Manager | C31: 31-Jul | D31: 1 - New Opportunity | E31: 7500 | F31: 7500
B32: POTS VoIP (MS) | C32: 31-Jul | D32: 1 - New Opportunity | E32: 10000 | G32: 10000 | I32: Charlie and Chad discuss
B33: POTS VoIP telephone configuration | C33: 31-Jul | D33: 1 - New Opportunity | E33: 9000 | G33: 9000
A34: HeroTech | B34: POTS computer replacement | C34: 31-Jul | D34: 1 - New Opportunity | E34: 2600 | F34: 2600
A35: Aug | E35: 103287 | F35: 52223.85 | G35: 35876.5 | H35: 0
A36: Sep | E36: 6908 | G36: 88100.35
A37: Oct | E37: 649
A38: Nov | E38: 1346
A39: Dec | E39: 342078.37
A40: Grand Total | E40: 641141.7

Sheet 6.12.18v2
E1: 149454.98 | F1: Yes | G1: Maybe | H1: No | I1: Notes
F2: 71909.98 | G2: 77545 | H2: 14600
A3: Row Labels | B3: Opportunity Summary | C3: Close Date | D3: Stage | E3: Sum of Revenue
A4: <12/31/2017
A5: May
A6: Turning Point Foundation | B6: POTS Migrate to cloud and o365 | C6: 31-May | D6: 10 - Awaiting Client Approval | E6: 9204 | G6: 9204 | I6: Move close date.
A7: Jun
A8: A Change in Trajectory (ACT) | B8: POTS ACT DT additional hardware | C8: 15-Jun | D8: 13 - Needs Invoice | E8: 532.5 | F8: 532.5
A9: Advanced Chiropractic | B9: POTS tablets | C9: 11-Jun | D9: 8 - Quote in review | E9: 954 | F9: 954
A10: Autism Response Team (ART) | B10: POTS Raise AWS amount they pay | C10: 27-Jun | D10: 1 - New Opportunity | E10: 300 | H10: 300 | I10: Pending relationship
A11: California Center for Public Health Advocacy | B11: POTS monthly website maintenance | C11: 30-Jun | D11: 1 - New Opportunity | E11: 100 | F11: 100
A12: Cool Pak | B12: POTS AWS - MS | C12: 30-Jun | D12: 7 - Quoting | E12: 1879 | G12: 1879 | I12: Sch call with client
A13: DITEC Manufacturing | B13: POTS DYNAMICS Migration Project | C13: 15-Jun | D13: 14 - On Hold | E13: 53430 | G13: 25000 | I13: Waiting for call back from owner
B14: POTS PC Refresh 1 of 6 | C14: 30-Jun | D14: 10 - Awaiting Client Approval | E14: 2010 | F14: 2010
A15: Instrument Control Services | B15: POTS VoIP Proposal | C15: 30-Jun | D15: 1 - New Opportunity | E15: 2800 | H15: 2800 | I15: Move close date to July
A16: Manduka | B16: POTS server environment upgrade | C16: 30-Jun | D16: 1 - New Opportunity | E16: 11500 | H16: 11500 | I16: Move close date to July
A17: Nelson and Associates | B17: POTS server grade battery backup | C17: 30-Jun | D17: 10 - Awaiting Client Approval | E17: 1261.98 | F17: 1261.98 | I17: F/u on invoice
A18: Ojai Oil Company | B18: POTS AWS - test server | C18: 30-Jun | D18: 10 - Awaiting Client Approval | E18: 6000 | F18: 6000 | I18: Liking, testing, pointing to yes
A19: Turning Point Foundation | B19: POTS AWS MS | C19: 30-Jun | D19: 10 - Awaiting Client Approval | E19: 2411.5 | G19: 2411.5
A20: Ventura Harley | B20: POTS MS | C20: 30-Jun | D20: 1 - New Opportunity | E20: 1317 | F20: 1317
A21: Z&S Management Corporation | B21: POTS Site location setup | C21: 30-Jun | D21: 1 - New Opportunity | E21: 1000 | F21: 1000
B22: POTS onsite visit Palm Desert | C22: 30-Jun | D22: 1 - New Opportunity | E22: 1000 | F22: 1000
B23: POTS 20 computers | C23: 30-Jun | D23: 1 - New Opportunity | E23: 7980 | F23: 7980
B24: POTS Hybrid Exchange | C24: 30-Jun | D24: 1 - New Opportunity | E24: 96509 | F24: 48254.5 | G24: 48254.5 | I24: :) - making decision this week
B25: POTS San Diego Office | C25: 30-Jun | D25: 1 - New Opportunity | E25: 1500 | F25: 1500
A26: Jul
A27: Autism Response Team (ART) | B27: POTS PC Refresh | C27: 16-Jul | D27: 7 - Quoting | E27: 1000 | F27: 1000
A28: BLUDOG Telecom | B28: POTS Lead Generation Project | C28: 1-Jul | D28: 10 - Awaiting Client Approval | E28: 3500 | H28: 3500 | I28: remove opp
A29: DITEC Manufacturing | B29: POTS PC Refresh 2 of 6 | C29: 31-Jul | D29: 10 - Awaiting Client Approval | E29: 2010 | F29: 2010
B30: POTS PC Refresh 3 of 6 | C30: 31-Jul | D30: 1 - New Opportunity | E30: 2188 | H30: 2188
A31: Organic Certifiers | B31: POTS PC Refresh | C31: 2-Jul | D31: 14 - On Hold | E31: 1854.85 | F31: 1854.85
A32: Southland Stone USA Inc. | B32: POTS Migrate server T610 to AWS | C32: 1-Jul | D32: 8 - Quote in review | E32: 6665 | F32: 6665
A33: Studio Designs | B33: POTS Computer Purchase | C33: 1-Jul | D33: 10 - Awaiting Client Approval | E33: 5000 | G33: 5000
